Compiled from "GhidraSourceBundle.java"
public class ghidra.app.plugin.core.osgi.GhidraSourceBundle extends ghidra.app.plugin.core.osgi.GhidraBundle {
  private static final java.lang.String INSTRCTION_ACTIVATOR;

  private static final java.lang.String GENERATED_ACTIVATOR_CLASSNAME;

  private static final java.lang.String GENERATED_VERSION;

  private static final java.util.function.Predicate<java.lang.String> IS_CLASS_FILE;

  private final java.lang.String symbolicName;

  private final java.nio.file.Path binaryDir;

  private final java.lang.String bundleLocationId;

  private final java.util.List<generic.jar.ResourceFile> newSources;

  private final java.util.List<java.nio.file.Path> oldBinaries;

  private javax.tools.JavaCompiler compiler;

  private final java.util.Map<generic.jar.ResourceFile, ghidra.app.plugin.core.osgi.BuildError> buildErrors;

  private final java.util.Map<generic.jar.ResourceFile, java.util.List<org.osgi.framework.wiring.BundleRequirement>> sourceFileToRequirements;

  private final java.util.Map<java.lang.String, java.util.List<generic.jar.ResourceFile>> requirementToSourceFileMap;

  private final java.util.Set<java.lang.String> missedRequirements;

  private final java.util.Set<java.lang.String> importPackageValues;

  public ghidra.app.plugin.core.osgi.GhidraSourceBundle(ghidra.app.plugin.core.osgi.BundleHost, generic.jar.ResourceFile, boolean, boolean);
    Code:
         0: aload_0
         1: aload_1
         2: aload_2
         3: iload_3
         4: iload         4
         6: invokespecial #1                  // Method ghidra/app/plugin/core/osgi/GhidraBundle."<init>":(Lghidra/app/plugin/core/osgi/BundleHost;Lgeneric/jar/ResourceFile;ZZ)V
         9: aload_0
        10: new           #7                  // class java/util/ArrayList
        13: dup
        14: invokespecial #9                  // Method java/util/ArrayList."<init>":()V
        17: putfield      #12                 // Field newSources:Ljava/util/List;
        20: aload_0
        21: new           #7                  // class java/util/ArrayList
        24: dup
        25: invokespecial #9                  // Method java/util/ArrayList."<init>":()V
        28: putfield      #18                 // Field oldBinaries:Ljava/util/List;
        31: aload_0
        32: invokestatic  #21                 // Method javax/tools/ToolProvider.getSystemJavaCompiler:()Ljavax/tools/JavaCompiler;
        35: putfield      #27                 // Field compiler:Ljavax/tools/JavaCompiler;
        38: aload_0
        39: new           #31                 // class java/util/HashMap
        42: dup
        43: invokespecial #33                 // Method java/util/HashMap."<init>":()V
        46: putfield      #34                 // Field buildErrors:Ljava/util/Map;
        49: aload_0
        50: new           #31                 // class java/util/HashMap
        53: dup
        54: invokespecial #33                 // Method java/util/HashMap."<init>":()V
        57: putfield      #38                 // Field sourceFileToRequirements:Ljava/util/Map;
        60: aload_0
        61: new           #31                 // class java/util/HashMap
        64: dup
        65: invokespecial #33                 // Method java/util/HashMap."<init>":()V
        68: putfield      #41                 // Field requirementToSourceFileMap:Ljava/util/Map;
        71: aload_0
        72: new           #44                 // class java/util/HashSet
        75: dup
        76: invokespecial #46                 // Method java/util/HashSet."<init>":()V
        79: putfield      #47                 // Field missedRequirements:Ljava/util/Set;
        82: aload_0
        83: new           #44                 // class java/util/HashSet
        86: dup
        87: invokespecial #46                 // Method java/util/HashSet."<init>":()V
        90: putfield      #51                 // Field importPackageValues:Ljava/util/Set;
        93: aload_0
        94: aload_0
        95: invokevirtual #54                 // Method getSourceDirectory:()Lgeneric/jar/ResourceFile;
        98: invokestatic  #58                 // Method sourceDirHash:(Lgeneric/jar/ResourceFile;)Ljava/lang/String;
       101: putfield      #62                 // Field symbolicName:Ljava/lang/String;
       104: aload_0
       105: invokestatic  #66                 // Method getCompiledBundlesDir:()Ljava/nio/file/Path;
       108: aload_0
       109: getfield      #62                 // Field symbolicName:Ljava/lang/String;
       112: invokeinterface #70,  2           // InterfaceMethod java/nio/file/Path.resolve:(Ljava/lang/String;)Ljava/nio/file/Path;
       117: putfield      #76                 // Field binaryDir:Ljava/nio/file/Path;
       120: aload_0
       121: aload_0
       122: getfield      #76                 // Field binaryDir:Ljava/nio/file/Path;
       125: invokeinterface #80,  1           // InterfaceMethod java/nio/file/Path.toAbsolutePath:()Ljava/nio/file/Path;
       130: invokeinterface #83,  1           // InterfaceMethod java/nio/file/Path.normalize:()Ljava/nio/file/Path;
       135: invokeinterface #86,  1           // InterfaceMethod java/nio/file/Path.toString:()Ljava/lang/String;
       140: invokedynamic #90,  0             // InvokeDynamic #0:makeConcatWithConstants:(Ljava/lang/String;)Ljava/lang/String;
       145: putfield      #94                 // Field bundleLocationId:Ljava/lang/String;
       148: return

  private final generic.jar.ResourceFile getSourceDirectory();
    Code:
         0: aload_0
         1: getfield      #97                 // Field bundleFile:Lgeneric/jar/ResourceFile;
         4: areturn

  public static java.nio.file.Path getCompiledBundlesDir();
    Code:
         0: invokestatic  #101                // Method ghidra/app/plugin/core/osgi/BundleHost.getOsgiDir:()Ljava/nio/file/Path;
         3: ldc           #106                // String compiled-bundles
         5: invokeinterface #70,  2           // InterfaceMethod java/nio/file/Path.resolve:(Ljava/lang/String;)Ljava/nio/file/Path;
        10: areturn

  public static java.lang.String sourceDirHash(generic.jar.ResourceFile);
    Code:
         0: aload_0
         1: invokevirtual #108                // Method generic/jar/ResourceFile.getAbsolutePath:()Ljava/lang/String;
         4: invokevirtual #113                // Method java/lang/String.hashCode:()I
         7: invokestatic  #119                // Method java/lang/Integer.toHexString:(I)Ljava/lang/String;
        10: areturn

  public java.lang.String classNameForScript(generic.jar.ResourceFile) throws java.lang.ClassNotFoundException;
    Code:
         0: aload_0
         1: invokevirtual #54                 // Method getSourceDirectory:()Lgeneric/jar/ResourceFile;
         4: aload_1
         5: invokestatic  #125                // Method utilities/util/FileUtilities.relativizePath:(Lgeneric/jar/ResourceFile;Lgeneric/jar/ResourceFile;)Ljava/lang/String;
         8: astore_2
         9: aload_2
        10: ifnonnull     41
        13: new           #131                // class java/lang/ClassNotFoundException
        16: dup
        17: ldc           #133                // String Failed to find script file \'%s\' in source directory \'%s\'
        19: iconst_2
        20: anewarray     #135                // class java/lang/Object
        23: dup
        24: iconst_0
        25: aload_1
        26: aastore
        27: dup
        28: iconst_1
        29: aload_0
        30: invokevirtual #54                 // Method getSourceDirectory:()Lgeneric/jar/ResourceFile;
        33: aastore
        34: invokestatic  #137                // Method java/lang/String.format:(Ljava/lang/String;[Ljava/lang/Object;)Ljava/lang/String;
        37: invokespecial #141                // Method java/lang/ClassNotFoundException."<init>":(Ljava/lang/String;)V
        40: athrow
        41: aload_2
        42: iconst_0
        43: aload_2
        44: invokevirtual #144                // Method java/lang/String.length:()I
        47: iconst_5
        48: isub
        49: invokevirtual #147                // Method java/lang/String.substring:(II)Ljava/lang/String;
        52: astore_2
        53: aload_2
        54: getstatic     #151                // Field java/io/File.separatorChar:C
        57: bipush        46
        59: invokevirtual #157                // Method java/lang/String.replace:(CC)Ljava/lang/String;
        62: areturn

  private void clearBuildErrors(generic.jar.ResourceFile);
    Code:
         0: aload_0
         1: getfield      #34                 // Field buildErrors:Ljava/util/Map;
         4: aload_1
         5: invokeinterface #161,  2          // InterfaceMethod java/util/Map.remove:(Ljava/lang/Object;)Ljava/lang/Object;
        10: pop
        11: return

  private void buildError(generic.jar.ResourceFile, java.lang.String);
    Code:
         0: aload_0
         1: getfield      #34                 // Field buildErrors:Ljava/util/Map;
         4: aload_1
         5: invokedynamic #167,  0            // InvokeDynamic #1:apply:()Ljava/util/function/Function;
        10: invokeinterface #171,  3          // InterfaceMethod java/util/Map.computeIfAbsent:(Ljava/lang/Object;Ljava/util/function/Function;)Ljava/lang/Object;
        15: checkcast     #175                // class ghidra/app/plugin/core/osgi/BuildError
        18: astore_3
        19: aload_3
        20: aload_2
        21: invokevirtual #177                // Method ghidra/app/plugin/core/osgi/BuildError.append:(Ljava/lang/String;)V
        24: return

  public ghidra.app.plugin.core.osgi.BuildError getErrors(generic.jar.ResourceFile);
    Code:
         0: aload_0
         1: getfield      #34                 // Field buildErrors:Ljava/util/Map;
         4: aload_1
         5: invokeinterface #180,  2          // InterfaceMethod java/util/Map.get:(Ljava/lang/Object;)Ljava/lang/Object;
        10: checkcast     #175                // class ghidra/app/plugin/core/osgi/BuildError
        13: areturn

  public java.util.Map<generic.jar.ResourceFile, ghidra.app.plugin.core.osgi.BuildError> getAllErrors();
    Code:
         0: aload_0
         1: getfield      #34                 // Field buildErrors:Ljava/util/Map;
         4: invokestatic  #183                // Method java/util/Collections.unmodifiableMap:(Ljava/util/Map;)Ljava/util/Map;
         7: areturn

  private java.lang.String getPreviousBuildErrors();
    Code:
         0: aload_0
         1: getfield      #34                 // Field buildErrors:Ljava/util/Map;
         4: invokeinterface #189,  1          // InterfaceMethod java/util/Map.values:()Ljava/util/Collection;
         9: invokeinterface #193,  1          // InterfaceMethod java/util/Collection.stream:()Ljava/util/stream/Stream;
        14: invokedynamic #199,  0            // InvokeDynamic #2:apply:()Ljava/util/function/Function;
        19: invokeinterface #200,  2          // InterfaceMethod java/util/stream/Stream.map:(Ljava/util/function/Function;)Ljava/util/stream/Stream;
        24: invokestatic  #206                // Method java/util/stream/Collectors.joining:()Ljava/util/stream/Collector;
        27: invokeinterface #212,  2          // InterfaceMethod java/util/stream/Stream.collect:(Ljava/util/stream/Collector;)Ljava/lang/Object;
        32: checkcast     #114                // class java/lang/String
        35: areturn

  private java.lang.String parseImportPackageMetadata(generic.jar.ResourceFile);
    Code:
         0: aload_1
         1: invokestatic  #216                // Method ghidra/app/script/GhidraScriptUtil.newScriptInfo:(Lgeneric/jar/ResourceFile;)Lghidra/app/script/ScriptInfo;
         4: invokevirtual #222                // Method ghidra/app/script/ScriptInfo.getImportPackage:()Ljava/lang/String;
         7: areturn

  private void updateRequirementsFromMetadata() throws ghidra.app.plugin.core.osgi.GhidraBundleException;
    Code:
         0: aload_0
         1: getfield      #38                 // Field sourceFileToRequirements:Ljava/util/Map;
         4: invokeinterface #227,  1          // InterfaceMethod java/util/Map.clear:()V
         9: aload_0
        10: getfield      #41                 // Field requirementToSourceFileMap:Ljava/util/Map;
        13: invokeinterface #227,  1          // InterfaceMethod java/util/Map.clear:()V
        18: aload_0
        19: getfield      #51                 // Field importPackageValues:Ljava/util/Set;
        22: invokeinterface #230,  1          // InterfaceMethod java/util/Set.clear:()V
        27: aload_0
        28: invokevirtual #54                 // Method getSourceDirectory:()Lgeneric/jar/ResourceFile;
        31: invokevirtual #233                // Method generic/jar/ResourceFile.listFiles:()[Lgeneric/jar/ResourceFile;
        34: astore_1
        35: aload_1
        36: arraylength
        37: istore_2
        38: iconst_0
        39: istore_3
        40: iload_3
        41: iload_2
        42: if_icmpge     230
        45: aload_1
        46: iload_3
        47: aaload
        48: astore        4
        50: aload         4
        52: invokevirtual #237                // Method generic/jar/ResourceFile.getName:()Ljava/lang/String;
        55: ldc           #240                // String .java
        57: invokevirtual #242                // Method java/lang/String.endsWith:(Ljava/lang/String;)Z
        60: ifne          66
        63: goto          224
        66: aload_0
        67: aload         4
        69: invokevirtual #246                // Method parseImportPackageMetadata:(Lgeneric/jar/ResourceFile;)Ljava/lang/String;
        72: astore        5
        74: aload         5
        76: ifnull        224
        79: aload         5
        81: invokevirtual #249                // Method java/lang/String.isEmpty:()Z
        84: ifeq          90
        87: goto          224
        90: aload         5
        92: invokevirtual #253                // Method java/lang/String.strip:()Ljava/lang/String;
        95: ldc_w         #256                // String ,
        98: invokestatic  #258                // Method org/apache/felix/framework/util/manifestparser/ManifestParser.parseDelimitedString:(Ljava/lang/String;Ljava/lang/String;)Ljava/util/List;
       101: astore        6
       103: aload_0
       104: getfield      #51                 // Field importPackageValues:Ljava/util/Set;
       107: aload         6
       109: invokeinterface #264,  2          // InterfaceMethod java/util/Set.addAll:(Ljava/util/Collection;)Z
       114: pop
       115: aload         5
       117: invokestatic  #268                // Method ghidra/app/plugin/core/osgi/OSGiUtils.parseImportPackage:(Ljava/lang/String;)Ljava/util/List;
       120: astore        7
       122: goto          144
       125: astore        8
       127: new           #276                // class ghidra/app/plugin/core/osgi/GhidraBundleException
       130: dup
       131: aload_0
       132: invokevirtual #278                // Method getLocationIdentifier:()Ljava/lang/String;
       135: ldc_w         #281                // String @importpackage error
       138: aload         8
       140: invokespecial #283                // Method ghidra/app/plugin/core/osgi/GhidraBundleException."<init>":(Ljava/lang/String;Ljava/lang/String;Lorg/osgi/framework/BundleException;)V
       143: athrow
       144: aload_0
       145: getfield      #38                 // Field sourceFileToRequirements:Ljava/util/Map;
       148: aload         4
       150: aload         7
       152: invokeinterface #286,  3          // InterfaceMethod java/util/Map.put:(Ljava/lang/Object;Ljava/lang/Object;)Ljava/lang/Object;
       157: pop
       158: aload         7
       160: invokeinterface #290,  1          // InterfaceMethod java/util/List.iterator:()Ljava/util/Iterator;
       165: astore        8
       167: aload         8
       169: invokeinterface #296,  1          // InterfaceMethod java/util/Iterator.hasNext:()Z
       174: ifeq          224
       177: aload         8
       179: invokeinterface #301,  1          // InterfaceMethod java/util/Iterator.next:()Ljava/lang/Object;
       184: checkcast     #305                // class org/osgi/framework/wiring/BundleRequirement
       187: astore        9
       189: aload_0
       190: getfield      #41                 // Field requirementToSourceFileMap:Ljava/util/Map;
       193: aload         9
       195: invokeinterface #307,  1          // InterfaceMethod org/osgi/framework/wiring/BundleRequirement.toString:()Ljava/lang/String;
       200: invokedynamic #308,  0            // InvokeDynamic #3:apply:()Ljava/util/function/Function;
       205: invokeinterface #171,  3          // InterfaceMethod java/util/Map.computeIfAbsent:(Ljava/lang/Object;Ljava/util/function/Function;)Ljava/lang/Object;
       210: checkcast     #291                // class java/util/List
       213: aload         4
       215: invokeinterface #309,  2          // InterfaceMethod java/util/List.add:(Ljava/lang/Object;)Z
       220: pop
       221: goto          167
       224: iinc          3, 1
       227: goto          40
       230: return
      Exception table:
         from    to  target type
           115   122   125   Class org/osgi/framework/BundleException

  private java.util.Map<java.lang.String, org.osgi.framework.wiring.BundleRequirement> getComputedReqs();
    Code:
         0: new           #31                 // class java/util/HashMap
         3: dup
         4: invokespecial #33                 // Method java/util/HashMap."<init>":()V
         7: astore_1
         8: aload_0
         9: getfield      #38                 // Field sourceFileToRequirements:Ljava/util/Map;
        12: invokeinterface #189,  1          // InterfaceMethod java/util/Map.values:()Ljava/util/Collection;
        17: invokeinterface #193,  1          // InterfaceMethod java/util/Collection.stream:()Ljava/util/stream/Stream;
        22: invokedynamic #313,  0            // InvokeDynamic #4:apply:()Ljava/util/function/Function;
        27: invokeinterface #314,  2          // InterfaceMethod java/util/stream/Stream.flatMap:(Ljava/util/function/Function;)Ljava/util/stream/Stream;
        32: aload_1
        33: invokedynamic #317,  0            // InvokeDynamic #5:accept:(Ljava/util/Map;)Ljava/util/function/Consumer;
        38: invokeinterface #321,  2          // InterfaceMethod java/util/stream/Stream.forEach:(Ljava/util/function/Consumer;)V
        43: aload_1
        44: areturn

  private org.apache.felix.framework.util.manifestparser.ManifestParser createSourceManifestParser();
    Code:
         0: aload_0
         1: invokevirtual #325                // Method getSourceManifestFile:()Lgeneric/jar/ResourceFile;
         4: astore_1
         5: aload_1
         6: invokevirtual #328                // Method generic/jar/ResourceFile.exists:()Z
         9: ifne          14
        12: aconst_null
        13: areturn
        14: aload_1
        15: invokevirtual #331                // Method generic/jar/ResourceFile.getInputStream:()Ljava/io/InputStream;
        18: astore_2
        19: new           #335                // class java/util/jar/Manifest
        22: dup
        23: aload_2
        24: invokespecial #337                // Method java/util/jar/Manifest."<init>":(Ljava/io/InputStream;)V
        27: astore_3
        28: aload_3
        29: invokevirtual #340                // Method java/util/jar/Manifest.getMainAttributes:()Ljava/util/jar/Attributes;
        32: astore        4
        34: aload         4
        36: invokevirtual #344                // Method java/util/jar/Attributes.entrySet:()Ljava/util/Set;
        39: invokeinterface #350,  1          // InterfaceMethod java/util/Set.stream:()Ljava/util/stream/Stream;
        44: invokedynamic #351,  0            // InvokeDynamic #6:apply:()Ljava/util/function/Function;
        49: invokedynamic #352,  0            // InvokeDynamic #7:apply:()Ljava/util/function/Function;
        54: invokestatic  #353                // Method java/util/stream/Collectors.toMap:(Ljava/util/function/Function;Ljava/util/function/Function;)Ljava/util/stream/Collector;
        57: invokeinterface #212,  2          // InterfaceMethod java/util/stream/Stream.collect:(Ljava/util/stream/Collector;)Ljava/lang/Object;
        62: checkcast     #162                // class java/util/Map
        65: astore        5
        67: new           #259                // class org/apache/felix/framework/util/manifestparser/ManifestParser
        70: dup
        71: aconst_null
        72: aconst_null
        73: aconst_null
        74: aload         5
        76: invokespecial #357                // Method org/apache/felix/framework/util/manifestparser/ManifestParser."<init>":(Lorg/apache/felix/framework/Logger;Ljava/util/Map;Lorg/osgi/framework/wiring/BundleRevision;Ljava/util/Map;)V
        79: astore        6
        81: aload_2
        82: ifnull        89
        85: aload_2
        86: invokevirtual #360                // Method java/io/InputStream.close:()V
        89: aload         6
        91: areturn
        92: astore_3
        93: aload_2
        94: ifnull        112
        97: aload_2
        98: invokevirtual #360                // Method java/io/InputStream.close:()V
       101: goto          112
       104: astore        4
       106: aload_3
       107: aload         4
       109: invokevirtual #367                // Method java/lang/Throwable.addSuppressed:(Ljava/lang/Throwable;)V
       112: aload_3
       113: athrow
       114: astore_2
       115: new           #373                // class java/lang/RuntimeException
       118: dup
       119: aload_2
       120: invokespecial #375                // Method java/lang/RuntimeException."<init>":(Ljava/lang/Throwable;)V
       123: athrow
      Exception table:
         from    to  target type
            19    81    92   Class java/lang/Throwable
            97   101   104   Class java/lang/Throwable
            14    89   114   Class java/io/IOException
            14    89   114   Class org/osgi/framework/BundleException
            92   114   114   Class java/io/IOException
            92   114   114   Class org/osgi/framework/BundleException

  public java.util.List<org.osgi.framework.wiring.BundleRequirement> getAllRequirements() throws ghidra.app.plugin.core.osgi.GhidraBundleException;
    Code:
         0: aload_0
         1: invokevirtual #377                // Method createSourceManifestParser:()Lorg/apache/felix/framework/util/manifestparser/ManifestParser;
         4: astore_1
         5: aload_1
         6: ifnull        14
         9: aload_1
        10: invokevirtual #381                // Method org/apache/felix/framework/util/manifestparser/ManifestParser.getRequirements:()Ljava/util/List;
        13: areturn
        14: aload_0
        15: invokevirtual #385                // Method updateRequirementsFromMetadata:()V
        18: aload_0
        19: invokevirtual #388                // Method getComputedReqs:()Ljava/util/Map;
        22: astore_2
        23: new           #7                  // class java/util/ArrayList
        26: dup
        27: aload_2
        28: invokeinterface #189,  1          // InterfaceMethod java/util/Map.values:()Ljava/util/Collection;
        33: invokespecial #392                // Method java/util/ArrayList."<init>":(Ljava/util/Collection;)V
        36: areturn

  private static void findPackageDirs(java.util.List<java.lang.String>, generic.jar.ResourceFile);
    Code:
         0: iconst_0
         1: istore_2
         2: aload_1
         3: invokedynamic #395,  0            // InvokeDynamic #8:accept:()Lgeneric/jar/ResourceFileFilter;
         8: invokevirtual #398                // Method generic/jar/ResourceFile.listFiles:(Lgeneric/jar/ResourceFileFilter;)[Lgeneric/jar/ResourceFile;
        11: astore_3
        12: aload_3
        13: ifnull        95
        16: aload_3
        17: astore        4
        19: aload         4
        21: arraylength
        22: istore        5
        24: iconst_0
        25: istore        6
        27: iload         6
        29: iload         5
        31: if_icmpge     95
        34: aload         4
        36: iload         6
        38: aaload
        39: astore        7
        41: aload         7
        43: invokevirtual #237                // Method generic/jar/ResourceFile.getName:()Ljava/lang/String;
        46: ldc_w         #401                // String internal|private
        49: invokevirtual #403                // Method java/lang/String.matches:(Ljava/lang/String;)Z
        52: ifne          89
        55: aload         7
        57: invokevirtual #406                // Method generic/jar/ResourceFile.isDirectory:()Z
        60: ifeq          72
        63: aload_0
        64: aload         7
        66: invokestatic  #409                // Method findPackageDirs:(Ljava/util/List;Lgeneric/jar/ResourceFile;)V
        69: goto          89
        72: iload_2
        73: ifne          89
        76: iconst_1
        77: istore_2
        78: aload_0
        79: aload_1
        80: invokevirtual #108                // Method generic/jar/ResourceFile.getAbsolutePath:()Ljava/lang/String;
        83: invokeinterface #309,  2          // InterfaceMethod java/util/List.add:(Ljava/lang/Object;)Z
        88: pop
        89: iinc          6, 1
        92: goto          27
        95: return

  public java.util.List<org.osgi.framework.wiring.BundleCapability> getAllCapabilities() throws ghidra.app.plugin.core.osgi.GhidraBundleException;
    Code:
         0: aload_0
         1: invokevirtual #377                // Method createSourceManifestParser:()Lorg/apache/felix/framework/util/manifestparser/ManifestParser;
         4: astore_1
         5: aload_1
         6: ifnull        14
         9: aload_1
        10: invokevirtual #413                // Method org/apache/felix/framework/util/manifestparser/ManifestParser.getCapabilities:()Ljava/util/List;
        13: areturn
        14: aload_0
        15: invokevirtual #54                 // Method getSourceDirectory:()Lgeneric/jar/ResourceFile;
        18: invokevirtual #108                // Method generic/jar/ResourceFile.getAbsolutePath:()Ljava/lang/String;
        21: invokevirtual #144                // Method java/lang/String.length:()I
        24: iconst_1
        25: iadd
        26: istore_2
        27: new           #7                  // class java/util/ArrayList
        30: dup
        31: invokespecial #9                  // Method java/util/ArrayList."<init>":()V
        34: astore_3
        35: aload_3
        36: aload_0
        37: invokevirtual #54                 // Method getSourceDirectory:()Lgeneric/jar/ResourceFile;
        40: invokestatic  #409                // Method findPackageDirs:(Ljava/util/List;Lgeneric/jar/ResourceFile;)V
        43: new           #416                // class java/lang/StringBuilder
        46: dup
        47: invokespecial #418                // Method java/lang/StringBuilder."<init>":()V
        50: astore        4
        52: aload_3
        53: invokeinterface #290,  1          // InterfaceMethod java/util/List.iterator:()Ljava/util/Iterator;
        58: astore        5
        60: aload         5
        62: invokeinterface #296,  1          // InterfaceMethod java/util/Iterator.hasNext:()Z
        67: ifeq          135
        70: aload         5
        72: invokeinterface #301,  1          // InterfaceMethod java/util/Iterator.next:()Ljava/lang/Object;
        77: checkcast     #114                // class java/lang/String
        80: astore        6
        82: aload         6
        84: invokevirtual #144                // Method java/lang/String.length:()I
        87: iload_2
        88: if_icmple     132
        91: aload         6
        93: iload_2
        94: invokevirtual #419                // Method java/lang/String.substring:(I)Ljava/lang/String;
        97: getstatic     #151                // Field java/io/File.separatorChar:C
       100: bipush        46
       102: invokevirtual #157                // Method java/lang/String.replace:(CC)Ljava/lang/String;
       105: astore        7
       107: aload         4
       109: bipush        44
       111: invokevirtual #421                // Method java/lang/StringBuilder.append:(C)Ljava/lang/StringBuilder;
       114: pop
       115: aload         4
       117: aload         7
       119: invokevirtual #424                // Method java/lang/StringBuilder.append:(Ljava/lang/String;)Ljava/lang/StringBuilder;
       122: pop
       123: aload         4
       125: ldc_w         #427                // String ;version=\"1.0\"
       128: invokevirtual #424                // Method java/lang/StringBuilder.append:(Ljava/lang/String;)Ljava/lang/StringBuilder;
       131: pop
       132: goto          60
       135: aload         4
       137: invokevirtual #429                // Method java/lang/StringBuilder.length:()I
       140: ifne          147
       143: invokestatic  #430                // Method java/util/Collections.emptyList:()Ljava/util/List;
       146: areturn
       147: aload         4
       149: iconst_1
       150: invokevirtual #433                // Method java/lang/StringBuilder.substring:(I)Ljava/lang/String;
       153: invokestatic  #434                // Method ghidra/app/plugin/core/osgi/OSGiUtils.parseExportPackage:(Ljava/lang/String;)Ljava/util/List;
       156: areturn
       157: astore        5
       159: new           #276                // class ghidra/app/plugin/core/osgi/GhidraBundleException
       162: dup
       163: aload_0
       164: invokevirtual #278                // Method getLocationIdentifier:()Ljava/lang/String;
       167: ldc_w         #437                // String Exports error
       170: aload         5
       172: invokespecial #283                // Method ghidra/app/plugin/core/osgi/GhidraBundleException."<init>":(Ljava/lang/String;Ljava/lang/String;Lorg/osgi/framework/BundleException;)V
       175: athrow
      Exception table:
         from    to  target type
           135   146   157   Class org/osgi/framework/BundleException
           147   156   157   Class org/osgi/framework/BundleException

  private void updateFromFilesystem(java.io.PrintWriter) throws java.io.IOException, ghidra.app.plugin.core.osgi.OSGiException;
    Code:
         0: aload_0
         1: getfield      #12                 // Field newSources:Ljava/util/List;
         4: invokeinterface #439,  1          // InterfaceMethod java/util/List.clear:()V
         9: aload_0
        10: getfield      #18                 // Field oldBinaries:Ljava/util/List;
        13: invokeinterface #439,  1          // InterfaceMethod java/util/List.clear:()V
        18: aload_0
        19: aload_0
        20: invokedynamic #440,  0            // InvokeDynamic #9:found:(Lghidra/app/plugin/core/osgi/GhidraSourceBundle;)Lghidra/app/plugin/core/osgi/GhidraSourceBundle$DiscrepancyCallback;
        25: invokevirtual #444                // Method visitDiscrepancies:(Lghidra/app/plugin/core/osgi/GhidraSourceBundle$DiscrepancyCallback;)V
        28: aload_0
        29: getfield      #12                 // Field newSources:Ljava/util/List;
        32: invokeinterface #290,  1          // InterfaceMethod java/util/List.iterator:()Ljava/util/Iterator;
        37: astore_2
        38: aload_2
        39: invokeinterface #296,  1          // InterfaceMethod java/util/Iterator.hasNext:()Z
        44: ifeq          88
        47: aload_2
        48: invokeinterface #301,  1          // InterfaceMethod java/util/Iterator.next:()Ljava/lang/Object;
        53: checkcast     #109                // class generic/jar/ResourceFile
        56: astore_3
        57: aload_0
        58: aload_3
        59: invokevirtual #448                // Method stillHasErrors:(Lgeneric/jar/ResourceFile;)Z
        62: ifeq          74
        65: aload_2
        66: invokeinterface #452,  1          // InterfaceMethod java/util/Iterator.remove:()V
        71: goto          85
        74: aload_0
        75: getfield      #34                 // Field buildErrors:Ljava/util/Map;
        78: aload_3
        79: invokeinterface #161,  2          // InterfaceMethod java/util/Map.remove:(Ljava/lang/Object;)Ljava/lang/Object;
        84: pop
        85: goto          38
        88: return

  private boolean stillHasErrors(generic.jar.ResourceFile);
    Code:
         0: aload_0
         1: getfield      #34                 // Field buildErrors:Ljava/util/Map;
         4: aload_1
         5: invokeinterface #180,  2          // InterfaceMethod java/util/Map.get:(Ljava/lang/Object;)Ljava/lang/Object;
        10: checkcast     #175                // class ghidra/app/plugin/core/osgi/BuildError
        13: astore_2
        14: aload_2
        15: ifnull        32
        18: aload_2
        19: invokevirtual #454                // Method ghidra/app/plugin/core/osgi/BuildError.getLastModified:()J
        22: aload_1
        23: invokevirtual #458                // Method generic/jar/ResourceFile.lastModified:()J
        26: lcmp
        27: ifne          32
        30: iconst_1
        31: ireturn
        32: iconst_0
        33: ireturn

  private void deleteOldBinaries() throws java.io.IOException;
    Code:
         0: aload_0
         1: getfield      #18                 // Field oldBinaries:Ljava/util/List;
         4: aconst_null
         5: invokeinterface #461,  2          // InterfaceMethod java/util/List.sort:(Ljava/util/Comparator;)V
        10: aload_0
        11: getfield      #18                 // Field oldBinaries:Ljava/util/List;
        14: invokeinterface #465,  1          // InterfaceMethod java/util/List.stream:()Ljava/util/stream/Stream;
        19: invokeinterface #466,  1          // InterfaceMethod java/util/stream/Stream.distinct:()Ljava/util/stream/Stream;
        24: invokedynamic #469,  0            // InvokeDynamic #10:test:()Ljava/util/function/Predicate;
        29: invokeinterface #473,  2          // InterfaceMethod java/util/stream/Stream.filter:(Ljava/util/function/Predicate;)Ljava/util/stream/Stream;
        34: invokeinterface #477,  1          // InterfaceMethod java/util/stream/Stream.sorted:()Ljava/util/stream/Stream;
        39: invokeinterface #480,  1          // InterfaceMethod java/util/stream/Stream.iterator:()Ljava/util/Iterator;
        44: astore_1
        45: aload_1
        46: invokestatic  #481                // Method util/CollectionUtils.asIterable:(Ljava/util/Iterator;)Ljava/lang/Iterable;
        49: invokeinterface #487,  1          // InterfaceMethod java/lang/Iterable.iterator:()Ljava/util/Iterator;
        54: astore_2
        55: aload_2
        56: invokeinterface #296,  1          // InterfaceMethod java/util/Iterator.hasNext:()Z
        61: ifeq          81
        64: aload_2
        65: invokeinterface #301,  1          // InterfaceMethod java/util/Iterator.next:()Ljava/lang/Object;
        70: checkcast     #71                 // class java/nio/file/Path
        73: astore_3
        74: aload_3
        75: invokestatic  #490                // Method java/nio/file/Files.delete:(Ljava/nio/file/Path;)V
        78: goto          55
        81: aload_0
        82: getfield      #18                 // Field oldBinaries:Ljava/util/List;
        85: invokeinterface #439,  1          // InterfaceMethod java/util/List.clear:()V
        90: return

  private int getBuildErrorCount();
    Code:
         0: aload_0
         1: getfield      #34                 // Field buildErrors:Ljava/util/Map;
         4: invokeinterface #496,  1          // InterfaceMethod java/util/Map.size:()I
         9: ireturn

  private int getNewSourcesCount();
    Code:
         0: aload_0
         1: getfield      #12                 // Field newSources:Ljava/util/List;
         4: invokeinterface #499,  1          // InterfaceMethod java/util/List.size:()I
         9: ireturn

  public java.util.List<generic.jar.ResourceFile> getNewSources();
    Code:
         0: aload_0
         1: getfield      #12                 // Field newSources:Ljava/util/List;
         4: invokestatic  #500                // Method java/util/Collections.unmodifiableList:(Ljava/util/List;)Ljava/util/List;
         7: areturn

  public java.lang.String getLocationIdentifier();
    Code:
         0: aload_0
         1: getfield      #94                 // Field bundleLocationId:Ljava/lang/String;
         4: areturn

  private generic.jar.ResourceFile getSourceManifestFile();
    Code:
         0: new           #109                // class generic/jar/ResourceFile
         3: dup
         4: aload_0
         5: invokevirtual #54                 // Method getSourceDirectory:()Lgeneric/jar/ResourceFile;
         8: getstatic     #504                // Field java/io/File.separator:Ljava/lang/String;
        11: invokedynamic #507,  0            // InvokeDynamic #11:makeConcatWithConstants:(Ljava/lang/String;)Ljava/lang/String;
        16: invokespecial #508                // Method generic/jar/ResourceFile."<init>":(Lgeneric/jar/ResourceFile;Ljava/lang/String;)V
        19: areturn

  private java.nio.file.Path getBinaryManifestPath();
    Code:
         0: aload_0
         1: getfield      #76                 // Field binaryDir:Ljava/nio/file/Path;
         4: ldc_w         #511                // String META-INF
         7: invokeinterface #70,  2           // InterfaceMethod java/nio/file/Path.resolve:(Ljava/lang/String;)Ljava/nio/file/Path;
        12: ldc_w         #513                // String MANIFEST.MF
        15: invokeinterface #70,  2           // InterfaceMethod java/nio/file/Path.resolve:(Ljava/lang/String;)Ljava/nio/file/Path;
        20: areturn

  private boolean hasSourceManifest();
    Code:
         0: aload_0
         1: invokevirtual #325                // Method getSourceManifestFile:()Lgeneric/jar/ResourceFile;
         4: invokevirtual #328                // Method generic/jar/ResourceFile.exists:()Z
         7: ireturn

  private boolean hasNewManifest();
    Code:
         0: aload_0
         1: invokevirtual #325                // Method getSourceManifestFile:()Lgeneric/jar/ResourceFile;
         4: astore_1
         5: aload_0
         6: invokevirtual #515                // Method getBinaryManifestPath:()Ljava/nio/file/Path;
         9: astore_2
        10: aload_2
        11: iconst_0
        12: anewarray     #518                // class java/nio/file/LinkOption
        15: invokestatic  #520                // Method java/nio/file/Files.notExists:(Ljava/nio/file/Path;[Ljava/nio/file/LinkOption;)Z
        18: ifne          38
        21: aload_1
        22: invokevirtual #458                // Method generic/jar/ResourceFile.lastModified:()J
        25: aload_2
        26: invokeinterface #524,  1          // InterfaceMethod java/nio/file/Path.toFile:()Ljava/io/File;
        31: invokevirtual #528                // Method java/io/File.lastModified:()J
        34: lcmp
        35: ifle          42
        38: iconst_1
        39: goto          43
        42: iconst_0
        43: istore_3
        44: aload_1
        45: invokevirtual #328                // Method generic/jar/ResourceFile.exists:()Z
        48: ifeq          59
        51: iload_3
        52: ifeq          59
        55: iconst_1
        56: goto          60
        59: iconst_0
        60: ireturn

  private static boolean wipeContents(java.nio.file.Path) throws java.io.IOException;
    Code:
         0: aload_0
         1: iconst_0
         2: anewarray     #518                // class java/nio/file/LinkOption
         5: invokestatic  #529                // Method java/nio/file/Files.exists:(Ljava/nio/file/Path;[Ljava/nio/file/LinkOption;)Z
         8: ifeq          117
        11: iconst_0
        12: istore_1
        13: aload_0
        14: iconst_0
        15: anewarray     #531                // class java/nio/file/FileVisitOption
        18: invokestatic  #533                // Method java/nio/file/Files.walk:(Ljava/nio/file/Path;[Ljava/nio/file/FileVisitOption;)Ljava/util/stream/Stream;
        21: astore_2
        22: aload_2
        23: invokestatic  #537                // InterfaceMethod java/util/Comparator.reverseOrder:()Ljava/util/Comparator;
        26: invokeinterface #543,  2          // InterfaceMethod java/util/stream/Stream.sorted:(Ljava/util/Comparator;)Ljava/util/stream/Stream;
        31: dup
        32: invokestatic  #546                // Method java/util/Objects.requireNonNull:(Ljava/lang/Object;)Ljava/lang/Object;
        35: pop
        36: invokedynamic #551,  0            // InvokeDynamic #12:iterator:(Ljava/util/stream/Stream;)Ljava/lang/Iterable;
        41: invokeinterface #487,  1          // InterfaceMethod java/lang/Iterable.iterator:()Ljava/util/Iterator;
        46: astore_3
        47: aload_3
        48: invokeinterface #296,  1          // InterfaceMethod java/util/Iterator.hasNext:()Z
        53: ifeq          78
        56: aload_3
        57: invokeinterface #301,  1          // InterfaceMethod java/util/Iterator.next:()Ljava/lang/Object;
        62: checkcast     #71                 // class java/nio/file/Path
        65: astore        4
        67: iload_1
        68: aload         4
        70: invokestatic  #554                // Method java/nio/file/Files.deleteIfExists:(Ljava/nio/file/Path;)Z
        73: ior
        74: istore_1
        75: goto          47
        78: aload_2
        79: ifnull        115
        82: aload_2
        83: invokeinterface #558,  1          // InterfaceMethod java/util/stream/Stream.close:()V
        88: goto          115
        91: astore_3
        92: aload_2
        93: ifnull        113
        96: aload_2
        97: invokeinterface #558,  1          // InterfaceMethod java/util/stream/Stream.close:()V
       102: goto          113
       105: astore        4
       107: aload_3
       108: aload         4
       110: invokevirtual #367                // Method java/lang/Throwable.addSuppressed:(Ljava/lang/Throwable;)V
       113: aload_3
       114: athrow
       115: iload_1
       116: ireturn
       117: iconst_0
       118: ireturn
      Exception table:
         from    to  target type
            22    78    91   Class java/lang/Throwable
            96   102   105   Class java/lang/Throwable

  private boolean wipeBinDir() throws java.io.IOException;
    Code:
         0: aload_0
         1: getfield      #76                 // Field binaryDir:Ljava/nio/file/Path;
         4: invokestatic  #559                // Method wipeContents:(Ljava/nio/file/Path;)Z
         7: ireturn

  private void addSourcesThatNoLongerHaveMissingRequirements();
    Code:
         0: aload_0
         1: getfield      #34                 // Field buildErrors:Ljava/util/Map;
         4: invokeinterface #562,  1          // InterfaceMethod java/util/Map.keySet:()Ljava/util/Set;
         9: invokeinterface #565,  1          // InterfaceMethod java/util/Set.iterator:()Ljava/util/Iterator;
        14: astore_1
        15: aload_1
        16: invokeinterface #296,  1          // InterfaceMethod java/util/Iterator.hasNext:()Z
        21: ifeq          140
        24: aload_1
        25: invokeinterface #301,  1          // InterfaceMethod java/util/Iterator.next:()Ljava/lang/Object;
        30: checkcast     #109                // class generic/jar/ResourceFile
        33: astore_2
        34: aload_0
        35: getfield      #38                 // Field sourceFileToRequirements:Ljava/util/Map;
        38: aload_2
        39: invokeinterface #180,  2          // InterfaceMethod java/util/Map.get:(Ljava/lang/Object;)Ljava/lang/Object;
        44: checkcast     #291                // class java/util/List
        47: astore_3
        48: aload_3
        49: ifnull        137
        52: aload_3
        53: invokeinterface #566,  1          // InterfaceMethod java/util/List.isEmpty:()Z
        58: ifne          137
        61: aload_0
        62: getfield      #567                // Field bundleHost:Lghidra/app/plugin/core/osgi/BundleHost;
        65: aload_3
        66: invokevirtual #571                // Method ghidra/app/plugin/core/osgi/BundleHost.canResolveAll:(Ljava/util/Collection;)Z
        69: ifeq          137
        72: aload_0
        73: getfield      #12                 // Field newSources:Ljava/util/List;
        76: aload_2
        77: invokeinterface #574,  2          // InterfaceMethod java/util/List.contains:(Ljava/lang/Object;)Z
        82: ifne          96
        85: aload_0
        86: getfield      #12                 // Field newSources:Ljava/util/List;
        89: aload_2
        90: invokeinterface #309,  2          // InterfaceMethod java/util/List.add:(Ljava/lang/Object;)Z
        95: pop
        96: aload_0
        97: aload_2
        98: invokevirtual #577                // Method correspondingBinaries:(Lgeneric/jar/ResourceFile;)[Lgeneric/jar/ResourceFile;
       101: astore        4
       103: aload         4
       105: arraylength
       106: istore        5
       108: iconst_0
       109: istore        6
       111: iload         6
       113: iload         5
       115: if_icmpge     137
       118: aload         4
       120: iload         6
       122: aaload
       123: astore        7
       125: aload         7
       127: invokevirtual #581                // Method generic/jar/ResourceFile.delete:()Z
       130: pop
       131: iinc          6, 1
       134: goto          111
       137: goto          15
       140: return

  private void addSourcesThatNowHaveMissingRequirements();
    Code:
         0: aload_0
         1: getfield      #38                 // Field sourceFileToRequirements:Ljava/util/Map;
         4: invokeinterface #583,  1          // InterfaceMethod java/util/Map.entrySet:()Ljava/util/Set;
         9: invokeinterface #565,  1          // InterfaceMethod java/util/Set.iterator:()Ljava/util/Iterator;
        14: astore_1
        15: aload_1
        16: invokeinterface #296,  1          // InterfaceMethod java/util/Iterator.hasNext:()Z
        21: ifeq          159
        24: aload_1
        25: invokeinterface #301,  1          // InterfaceMethod java/util/Iterator.next:()Ljava/lang/Object;
        30: checkcast     #584                // class java/util/Map$Entry
        33: astore_2
        34: aload_2
        35: invokeinterface #586,  1          // InterfaceMethod java/util/Map$Entry.getKey:()Ljava/lang/Object;
        40: checkcast     #109                // class generic/jar/ResourceFile
        43: astore_3
        44: aload_2
        45: invokeinterface #589,  1          // InterfaceMethod java/util/Map$Entry.getValue:()Ljava/lang/Object;
        50: checkcast     #291                // class java/util/List
        53: astore        4
        55: aload         4
        57: ifnull        156
        60: aload         4
        62: invokeinterface #566,  1          // InterfaceMethod java/util/List.isEmpty:()Z
        67: ifne          156
        70: aload_0
        71: getfield      #34                 // Field buildErrors:Ljava/util/Map;
        74: aload_3
        75: invokeinterface #592,  2          // InterfaceMethod java/util/Map.containsKey:(Ljava/lang/Object;)Z
        80: ifne          156
        83: aload_0
        84: getfield      #567                // Field bundleHost:Lghidra/app/plugin/core/osgi/BundleHost;
        87: aload         4
        89: invokevirtual #571                // Method ghidra/app/plugin/core/osgi/BundleHost.canResolveAll:(Ljava/util/Collection;)Z
        92: ifne          156
        95: aload_0
        96: getfield      #12                 // Field newSources:Ljava/util/List;
        99: aload_3
       100: invokeinterface #574,  2          // InterfaceMethod java/util/List.contains:(Ljava/lang/Object;)Z
       105: ifne          119
       108: aload_0
       109: getfield      #12                 // Field newSources:Ljava/util/List;
       112: aload_3
       113: invokeinterface #309,  2          // InterfaceMethod java/util/List.add:(Ljava/lang/Object;)Z
       118: pop
       119: aload_0
       120: aload_3
       121: invokevirtual #577                // Method correspondingBinaries:(Lgeneric/jar/ResourceFile;)[Lgeneric/jar/ResourceFile;
       124: invokestatic  #595                // Method java/util/Arrays.stream:([Ljava/lang/Object;)Ljava/util/stream/Stream;
       127: invokedynamic #600,  0            // InvokeDynamic #13:apply:()Ljava/util/function/Function;
       132: invokeinterface #200,  2          // InterfaceMethod java/util/stream/Stream.map:(Ljava/util/function/Function;)Ljava/util/stream/Stream;
       137: aload_0
       138: getfield      #18                 // Field oldBinaries:Ljava/util/List;
       141: dup
       142: invokestatic  #546                // Method java/util/Objects.requireNonNull:(Ljava/lang/Object;)Ljava/lang/Object;
       145: pop
       146: invokedynamic #601,  0            // InvokeDynamic #14:accept:(Ljava/util/List;)Ljava/util/function/Consumer;
       151: invokeinterface #321,  2          // InterfaceMethod java/util/stream/Stream.forEach:(Ljava/util/function/Consumer;)V
       156: goto          15
       159: return

  public boolean build(java.io.PrintWriter) throws java.lang.Exception;
    Code:
         0: aload_1
         1: invokestatic  #604                // Method generic/io/NullPrintWriter.dummyIfNull:(Ljava/io/PrintWriter;)Ljava/io/PrintWriter;
         4: astore_1
         5: iconst_0
         6: istore_2
         7: aload_0
         8: invokevirtual #610                // Method hasSourceManifest:()Z
        11: ifeq          174
        14: aload_0
        15: getfield      #38                 // Field sourceFileToRequirements:Ljava/util/Map;
        18: invokeinterface #227,  1          // InterfaceMethod java/util/Map.clear:()V
        23: aload_0
        24: getfield      #41                 // Field requirementToSourceFileMap:Ljava/util/Map;
        27: invokeinterface #227,  1          // InterfaceMethod java/util/Map.clear:()V
        32: new           #7                  // class java/util/ArrayList
        35: dup
        36: aload_0
        37: invokevirtual #613                // Method getAllRequirements:()Ljava/util/List;
        40: invokespecial #392                // Method java/util/ArrayList."<init>":(Ljava/util/Collection;)V
        43: astore_3
        44: aload_0
        45: getfield      #567                // Field bundleHost:Lghidra/app/plugin/core/osgi/BundleHost;
        48: aload_3
        49: invokevirtual #616                // Method ghidra/app/plugin/core/osgi/BundleHost.resolve:(Ljava/util/List;)Ljava/util/List;
        52: pop
        53: new           #44                 // class java/util/HashSet
        56: dup
        57: invokespecial #46                 // Method java/util/HashSet."<init>":()V
        60: astore        4
        62: aload_3
        63: invokeinterface #290,  1          // InterfaceMethod java/util/List.iterator:()Ljava/util/Iterator;
        68: astore        5
        70: aload         5
        72: invokeinterface #296,  1          // InterfaceMethod java/util/Iterator.hasNext:()Z
        77: ifeq          110
        80: aload         5
        82: invokeinterface #301,  1          // InterfaceMethod java/util/Iterator.next:()Ljava/lang/Object;
        87: checkcast     #305                // class org/osgi/framework/wiring/BundleRequirement
        90: astore        6
        92: aload         4
        94: aload         6
        96: invokeinterface #618,  1          // InterfaceMethod org/osgi/framework/wiring/BundleRequirement.toString:()Ljava/lang/String;
       101: invokeinterface #619,  2          // InterfaceMethod java/util/Set.add:(Ljava/lang/Object;)Z
       106: pop
       107: goto          70
       110: aload_0
       111: invokevirtual #620                // Method hasNewManifest:()Z
       114: ifne          131
       117: aload         4
       119: aload_0
       120: getfield      #47                 // Field missedRequirements:Ljava/util/Set;
       123: invokeinterface #623,  2          // InterfaceMethod java/util/Set.equals:(Ljava/lang/Object;)Z
       128: ifne          166
       131: aload_0
       132: getfield      #47                 // Field missedRequirements:Ljava/util/Set;
       135: invokeinterface #230,  1          // InterfaceMethod java/util/Set.clear:()V
       140: aload_0
       141: getfield      #47                 // Field missedRequirements:Ljava/util/Set;
       144: aload         4
       146: invokeinterface #264,  2          // InterfaceMethod java/util/Set.addAll:(Ljava/util/Collection;)Z
       151: pop
       152: aload_0
       153: invokevirtual #626                // Method wipeBinDir:()Z
       156: pop
       157: aload_0
       158: getfield      #34                 // Field buildErrors:Ljava/util/Map;
       161: invokeinterface #227,  1          // InterfaceMethod java/util/Map.clear:()V
       166: aload_0
       167: aload_1
       168: invokevirtual #629                // Method updateFromFilesystem:(Ljava/io/PrintWriter;)V
       171: goto          191
       174: aload_0
       175: aload_1
       176: invokevirtual #629                // Method updateFromFilesystem:(Ljava/io/PrintWriter;)V
       179: aload_0
       180: invokevirtual #385                // Method updateRequirementsFromMetadata:()V
       183: aload_0
       184: invokevirtual #633                // Method addSourcesThatNoLongerHaveMissingRequirements:()V
       187: aload_0
       188: invokevirtual #636                // Method addSourcesThatNowHaveMissingRequirements:()V
       191: aload_0
       192: invokevirtual #639                // Method getBuildErrorCount:()I
       195: istore_3
       196: aload_0
       197: invokevirtual #642                // Method getNewSourcesCount:()I
       200: istore        4
       202: iload         4
       204: ifne          283
       207: iload_3
       208: ifle          285
       211: aload_1
       212: ldc_w         #645                // String %s hasn\'t changed, with %d file%s failing in previous build(s):\n
       215: iconst_3
       216: anewarray     #135                // class java/lang/Object
       219: dup
       220: iconst_0
       221: aload_0
       222: invokevirtual #54                 // Method getSourceDirectory:()Lgeneric/jar/ResourceFile;
       225: invokevirtual #647                // Method generic/jar/ResourceFile.toString:()Ljava/lang/String;
       228: aastore
       229: dup
       230: iconst_1
       231: iload_3
       232: invokestatic  #648                // Method java/lang/Integer.valueOf:(I)Ljava/lang/Integer;
       235: aastore
       236: dup
       237: iconst_2
       238: iload_3
       239: iconst_1
       240: if_icmple     249
       243: ldc_w         #652                // String s
       246: goto          252
       249: ldc_w         #654                // String
       252: aastore
       253: invokevirtual #656                // Method java/io/PrintWriter.printf:(Ljava/lang/String;[Ljava/lang/Object;)Ljava/io/PrintWriter;
       256: pop
       257: aload_1
       258: ldc_w         #662                // String %s\n
       261: iconst_1
       262: anewarray     #135                // class java/lang/Object
       265: dup
       266: iconst_0
       267: aload_0
       268: invokevirtual #664                // Method getPreviousBuildErrors:()Ljava/lang/String;
       271: aastore
       272: invokevirtual #656                // Method java/io/PrintWriter.printf:(Ljava/lang/String;[Ljava/lang/Object;)Ljava/io/PrintWriter;
       275: pop
       276: aload_1
       277: invokevirtual #667                // Method java/io/PrintWriter.flush:()V
       280: goto          285
       283: iconst_1
       284: istore_2
       285: aload_0
       286: getfield      #76                 // Field binaryDir:Ljava/nio/file/Path;
       289: invokeinterface #524,  1          // InterfaceMethod java/nio/file/Path.toFile:()Ljava/io/File;
       294: invokevirtual #670                // Method java/io/File.exists:()Z
       297: ifne          302
       300: iconst_1
       301: istore_2
       302: iload_2
       303: ifeq          356
       306: aload_0
       307: getfield      #567                // Field bundleHost:Lghidra/app/plugin/core/osgi/BundleHost;
       310: aload_0
       311: invokevirtual #278                // Method getLocationIdentifier:()Ljava/lang/String;
       314: invokevirtual #671                // Method ghidra/app/plugin/core/osgi/BundleHost.getOSGiBundle:(Ljava/lang/String;)Lorg/osgi/framework/Bundle;
       317: astore        5
       319: aload         5
       321: ifnull        333
       324: aload_0
       325: getfield      #567                // Field bundleHost:Lghidra/app/plugin/core/osgi/BundleHost;
       328: aload         5
       330: invokevirtual #675                // Method ghidra/app/plugin/core/osgi/BundleHost.deactivateSynchronously:(Lorg/osgi/framework/Bundle;)V
       333: aload_0
       334: invokevirtual #679                // Method deleteOldBinaries:()V
       337: aload_0
       338: aload_1
       339: invokevirtual #682                // Method compileToExplodedBundle:(Ljava/io/PrintWriter;)Ljava/lang/String;
       342: astore        6
       344: aload_0
       345: getfield      #567                // Field bundleHost:Lghidra/app/plugin/core/osgi/BundleHost;
       348: aload_0
       349: aload         6
       351: invokevirtual #686                // Method ghidra/app/plugin/core/osgi/BundleHost.notifyBundleBuilt:(Lghidra/app/plugin/core/osgi/GhidraBundle;Ljava/lang/String;)V
       354: iconst_1
       355: ireturn
       356: aload_0
       357: getfield      #567                // Field bundleHost:Lghidra/app/plugin/core/osgi/BundleHost;
       360: aload_0
       361: aconst_null
       362: invokevirtual #686                // Method ghidra/app/plugin/core/osgi/BundleHost.notifyBundleBuilt:(Lghidra/app/plugin/core/osgi/GhidraBundle;Ljava/lang/String;)V
       365: iconst_0
       366: ireturn

  public boolean clean();
    Code:
         0: iconst_0
         1: istore_1
         2: aload_0
         3: getfield      #34                 // Field buildErrors:Ljava/util/Map;
         6: invokeinterface #690,  1          // InterfaceMethod java/util/Map.isEmpty:()Z
        11: ifne          27
        14: aload_0
        15: getfield      #34                 // Field buildErrors:Ljava/util/Map;
        18: invokeinterface #227,  1          // InterfaceMethod java/util/Map.clear:()V
        23: iload_1
        24: iconst_1
        25: ior
        26: istore_1
        27: aload_0
        28: invokevirtual #691                // Method getOSGiBundle:()Lorg/osgi/framework/Bundle;
        31: astore_2
        32: aload_2
        33: ifnull        44
        36: aload_0
        37: getfield      #567                // Field bundleHost:Lghidra/app/plugin/core/osgi/BundleHost;
        40: aload_2
        41: invokevirtual #675                // Method ghidra/app/plugin/core/osgi/BundleHost.deactivateSynchronously:(Lorg/osgi/framework/Bundle;)V
        44: iload_1
        45: aload_0
        46: invokevirtual #626                // Method wipeBinDir:()Z
        49: ior
        50: ireturn
        51: astore_2
        52: aload_0
        53: aconst_null
        54: ldc_w         #694                // String Source bundle clean error
        57: ldc_w         #696                // String While attempting to delete the compiled directory, an exception was thrown
        60: aload_2
        61: invokestatic  #698                // Method ghidra/util/Msg.showError:(Ljava/lang/Object;Ljava/awt/Component;Ljava/lang/String;Ljava/lang/Object;Ljava/lang/Throwable;)V
        64: iload_1
        65: ireturn
      Exception table:
         from    to  target type
            27    50    51   Class java/io/IOException
            27    50    51   Class ghidra/app/plugin/core/osgi/GhidraBundleException

  private generic.jar.ResourceFile[] correspondingBinaries(generic.jar.ResourceFile);
    Code:
         0: aload_1
         1: invokevirtual #704                // Method generic/jar/ResourceFile.getParentFile:()Lgeneric/jar/ResourceFile;
         4: invokevirtual #108                // Method generic/jar/ResourceFile.getAbsolutePath:()Ljava/lang/String;
         7: astore_2
         8: aload_0
         9: invokevirtual #54                 // Method getSourceDirectory:()Lgeneric/jar/ResourceFile;
        12: invokevirtual #108                // Method generic/jar/ResourceFile.getAbsolutePath:()Ljava/lang/String;
        15: invokevirtual #144                // Method java/lang/String.length:()I
        18: istore_3
        19: aload_2
        20: iload_3
        21: invokevirtual #419                // Method java/lang/String.substring:(I)Ljava/lang/String;
        24: astore        4
        26: aload         4
        28: getstatic     #504                // Field java/io/File.separator:Ljava/lang/String;
        31: invokevirtual #707                // Method java/lang/String.startsWith:(Ljava/lang/String;)Z
        34: ifeq          45
        37: aload         4
        39: iconst_1
        40: invokevirtual #419                // Method java/lang/String.substring:(I)Ljava/lang/String;
        43: astore        4
        45: aload_1
        46: invokevirtual #237                // Method generic/jar/ResourceFile.getName:()Ljava/lang/String;
        49: astore        5
        51: aload         5
        53: iconst_0
        54: aload         5
        56: invokevirtual #144                // Method java/lang/String.length:()I
        59: iconst_5
        60: isub
        61: invokevirtual #147                // Method java/lang/String.substring:(II)Ljava/lang/String;
        64: astore        6
        66: new           #109                // class generic/jar/ResourceFile
        69: dup
        70: aload_0
        71: getfield      #76                 // Field binaryDir:Ljava/nio/file/Path;
        74: aload         4
        76: invokeinterface #70,  2           // InterfaceMethod java/nio/file/Path.resolve:(Ljava/lang/String;)Ljava/nio/file/Path;
        81: invokeinterface #524,  1          // InterfaceMethod java/nio/file/Path.toFile:()Ljava/io/File;
        86: invokespecial #710                // Method generic/jar/ResourceFile."<init>":(Ljava/io/File;)V
        89: astore        7
        91: aload         7
        93: invokevirtual #328                // Method generic/jar/ResourceFile.exists:()Z
        96: ifeq          107
        99: aload         7
       101: invokevirtual #406                // Method generic/jar/ResourceFile.isDirectory:()Z
       104: ifne          112
       107: iconst_0
       108: anewarray     #109                // class generic/jar/ResourceFile
       111: areturn
       112: aload         7
       114: aload         6
       116: invokedynamic #713,  0            // InvokeDynamic #15:accept:(Ljava/lang/String;)Lgeneric/jar/ResourceFileFilter;
       121: invokevirtual #398                // Method generic/jar/ResourceFile.listFiles:(Lgeneric/jar/ResourceFileFilter;)[Lgeneric/jar/ResourceFile;
       124: areturn

  protected void visitDiscrepancies(ghidra.app.plugin.core.osgi.GhidraSourceBundle$DiscrepancyCallback);
    Code:
         0: new           #716                // class java/util/ArrayDeque
         3: dup
         4: invokespecial #718                // Method java/util/ArrayDeque."<init>":()V
         7: astore_2
         8: aload_0
         9: invokevirtual #54                 // Method getSourceDirectory:()Lgeneric/jar/ResourceFile;
        12: astore_3
        13: aload_2
        14: aload_3
        15: invokeinterface #719,  2          // InterfaceMethod java/util/Deque.add:(Ljava/lang/Object;)Z
        20: pop
        21: aload_2
        22: invokeinterface #722,  1          // InterfaceMethod java/util/Deque.isEmpty:()Z
        27: ifne          211
        30: aload_2
        31: invokeinterface #723,  1          // InterfaceMethod java/util/Deque.pop:()Ljava/lang/Object;
        36: checkcast     #109                // class generic/jar/ResourceFile
        39: astore        4
        41: aload         4
        43: invokevirtual #108                // Method generic/jar/ResourceFile.getAbsolutePath:()Ljava/lang/String;
        46: aload_3
        47: invokevirtual #108                // Method generic/jar/ResourceFile.getAbsolutePath:()Ljava/lang/String;
        50: invokevirtual #144                // Method java/lang/String.length:()I
        53: invokevirtual #419                // Method java/lang/String.substring:(I)Ljava/lang/String;
        56: astore        5
        58: aload         5
        60: getstatic     #504                // Field java/io/File.separator:Ljava/lang/String;
        63: invokevirtual #707                // Method java/lang/String.startsWith:(Ljava/lang/String;)Z
        66: ifeq          77
        69: aload         5
        71: iconst_1
        72: invokevirtual #419                // Method java/lang/String.substring:(I)Ljava/lang/String;
        75: astore        5
        77: aload_0
        78: getfield      #76                 // Field binaryDir:Ljava/nio/file/Path;
        81: aload         5
        83: invokeinterface #70,  2           // InterfaceMethod java/nio/file/Path.resolve:(Ljava/lang/String;)Ljava/nio/file/Path;
        88: astore        6
        90: new           #726                // class ghidra/app/plugin/core/osgi/GhidraSourceBundle$ClassMapper
        93: dup
        94: aload         6
        96: invokespecial #728                // Method ghidra/app/plugin/core/osgi/GhidraSourceBundle$ClassMapper."<init>":(Ljava/nio/file/Path;)V
        99: astore        7
       101: aload         4
       103: invokevirtual #233                // Method generic/jar/ResourceFile.listFiles:()[Lgeneric/jar/ResourceFile;
       106: astore        8
       108: aload         8
       110: ifnull        188
       113: aload         8
       115: astore        9
       117: aload         9
       119: arraylength
       120: istore        10
       122: iconst_0
       123: istore        11
       125: iload         11
       127: iload         10
       129: if_icmpge     188
       132: aload         9
       134: iload         11
       136: aaload
       137: astore        12
       139: aload         12
       141: invokevirtual #406                // Method generic/jar/ResourceFile.isDirectory:()Z
       144: ifeq          158
       147: aload_2
       148: aload         12
       150: invokeinterface #730,  2          // InterfaceMethod java/util/Deque.push:(Ljava/lang/Object;)V
       155: goto          182
       158: aload         7
       160: aload         12
       162: invokevirtual #734                // Method ghidra/app/plugin/core/osgi/GhidraSourceBundle$ClassMapper.findAndRemove:(Lgeneric/jar/ResourceFile;)Ljava/util/List;
       165: astore        13
       167: aload         13
       169: ifnull        182
       172: aload_1
       173: aload         12
       175: aload         13
       177: invokeinterface #738,  3          // InterfaceMethod ghidra/app/plugin/core/osgi/GhidraSourceBundle$DiscrepancyCallback.found:(Lgeneric/jar/ResourceFile;Ljava/util/Collection;)V
       182: iinc          11, 1
       185: goto          125
       188: aload         7
       190: invokevirtual #743                // Method ghidra/app/plugin/core/osgi/GhidraSourceBundle$ClassMapper.hasExtraClassFiles:()Z
       193: ifeq          208
       196: aload_1
       197: aconst_null
       198: aload         7
       200: invokevirtual #746                // Method ghidra/app/plugin/core/osgi/GhidraSourceBundle$ClassMapper.extraClassFiles:()Ljava/util/Collection;
       203: invokeinterface #738,  3          // InterfaceMethod ghidra/app/plugin/core/osgi/GhidraSourceBundle$DiscrepancyCallback.found:(Lgeneric/jar/ResourceFile;Ljava/util/Collection;)V
       208: goto          21
       211: goto          223
       214: astore_2
       215: aload_0
       216: ldc_w         #749                // String Exception while searching for file system discrepancies
       219: aload_2
       220: invokestatic  #751                // Method ghidra/util/Msg.error:(Ljava/lang/Object;Ljava/lang/Object;Ljava/lang/Throwable;)V
       223: return
      Exception table:
         from    to  target type
             0   211   214   Class java/lang/Throwable

  private boolean resolveInternally(java.util.List<org.osgi.framework.wiring.BundleRequirement>) throws ghidra.app.plugin.core.osgi.GhidraBundleException;
    Code:
         0: aload_1
         1: invokeinterface #566,  1          // InterfaceMethod java/util/List.isEmpty:()Z
         6: ifeq          11
         9: iconst_1
        10: ireturn
        11: aload_0
        12: invokevirtual #755                // Method getAllCapabilities:()Ljava/util/List;
        15: astore_2
        16: aload_1
        17: invokeinterface #290,  1          // InterfaceMethod java/util/List.iterator:()Ljava/util/Iterator;
        22: astore_3
        23: iconst_0
        24: istore        4
        26: aload_3
        27: invokeinterface #296,  1          // InterfaceMethod java/util/Iterator.hasNext:()Z
        32: ifeq          87
        35: aload_3
        36: invokeinterface #301,  1          // InterfaceMethod java/util/Iterator.next:()Ljava/lang/Object;
        41: checkcast     #305                // class org/osgi/framework/wiring/BundleRequirement
        44: astore        5
        46: aload_2
        47: invokeinterface #465,  1          // InterfaceMethod java/util/List.stream:()Ljava/util/stream/Stream;
        52: aload         5
        54: dup
        55: invokestatic  #546                // Method java/util/Objects.requireNonNull:(Ljava/lang/Object;)Ljava/lang/Object;
        58: pop
        59: invokedynamic #758,  0            // InvokeDynamic #16:test:(Lorg/osgi/framework/wiring/BundleRequirement;)Ljava/util/function/Predicate;
        64: invokeinterface #761,  2          // InterfaceMethod java/util/stream/Stream.anyMatch:(Ljava/util/function/Predicate;)Z
        69: ifeq          81
        72: aload_3
        73: invokeinterface #452,  1          // InterfaceMethod java/util/Iterator.remove:()V
        78: goto          84
        81: iconst_1
        82: istore        4
        84: goto          26
        87: iload         4
        89: ifne          96
        92: iconst_1
        93: goto          97
        96: iconst_0
        97: ireturn

  private org.phidias.compile.BundleJavaManager createBundleJavaManager(java.io.PrintWriter, ghidra.app.plugin.core.osgi.GhidraSourceBundle$Summary, java.util.List<java.lang.String>) throws java.io.IOException, ghidra.app.plugin.core.osgi.GhidraBundleException;
    Code:
         0: new           #765                // class ghidra/app/script/ResourceFileJavaFileManager
         3: dup
         4: aload_0
         5: invokevirtual #54                 // Method getSourceDirectory:()Lgeneric/jar/ResourceFile;
         8: invokestatic  #767                // Method java/util/Collections.singletonList:(Ljava/lang/Object;)Ljava/util/List;
        11: aload_0
        12: getfield      #34                 // Field buildErrors:Ljava/util/Map;
        15: invokeinterface #562,  1          // InterfaceMethod java/util/Map.keySet:()Ljava/util/Set;
        20: invokespecial #771                // Method ghidra/app/script/ResourceFileJavaFileManager."<init>":(Ljava/util/List;Ljava/util/Set;)V
        23: astore        4
        25: new           #774                // class ghidra/app/plugin/core/osgi/GhidraSourceBundle$MyBundleJavaManager
        28: dup
        29: aload_0
        30: getfield      #567                // Field bundleHost:Lghidra/app/plugin/core/osgi/BundleHost;
        33: invokevirtual #776                // Method ghidra/app/plugin/core/osgi/BundleHost.getHostFramework:()Lorg/osgi/framework/launch/Framework;
        36: aload         4
        38: aload_3
        39: invokespecial #780                // Method ghidra/app/plugin/core/osgi/GhidraSourceBundle$MyBundleJavaManager."<init>":(Lorg/osgi/framework/Bundle;Ljavax/tools/JavaFileManager;Ljava/util/List;)V
        42: astore        5
        44: aload_0
        45: invokevirtual #613                // Method getAllRequirements:()Ljava/util/List;
        48: astore        6
        50: aload_0
        51: getfield      #567                // Field bundleHost:Lghidra/app/plugin/core/osgi/BundleHost;
        54: aload         6
        56: invokevirtual #616                // Method ghidra/app/plugin/core/osgi/BundleHost.resolve:(Ljava/util/List;)Ljava/util/List;
        59: astore        7
        61: aload_0
        62: aload         6
        64: invokevirtual #783                // Method resolveInternally:(Ljava/util/List;)Z
        67: ifne          78
        70: aload_0
        71: aload_1
        72: aload_2
        73: aload         6
        75: invokevirtual #787                // Method writeErrorUnresolved:(Ljava/io/PrintWriter;Lghidra/app/plugin/core/osgi/GhidraSourceBundle$Summary;Ljava/util/List;)V
        78: aload         7
        80: aload         5
        82: dup
        83: invokestatic  #546                // Method java/util/Objects.requireNonNull:(Ljava/lang/Object;)Ljava/lang/Object;
        86: pop
        87: invokedynamic #791,  0            // InvokeDynamic #17:accept:(Lorg/phidias/compile/BundleJavaManager;)Ljava/util/function/Consumer;
        92: invokeinterface #794,  2          // InterfaceMethod java/util/List.forEach:(Ljava/util/function/Consumer;)V
        97: aload         5
        99: areturn

  private void writeErrorUnresolved(java.io.PrintWriter, ghidra.app.plugin.core.osgi.GhidraSourceBundle$Summary, java.util.List<org.osgi.framework.wiring.BundleRequirement>);
    Code:
         0: aload_1
         1: ldc_w         #795                // String %d import requirement%s remain%s unresolved:\n
         4: iconst_3
         5: anewarray     #135                // class java/lang/Object
         8: dup
         9: iconst_0
        10: aload_3
        11: invokeinterface #499,  1          // InterfaceMethod java/util/List.size:()I
        16: invokestatic  #648                // Method java/lang/Integer.valueOf:(I)Ljava/lang/Integer;
        19: aastore
        20: dup
        21: iconst_1
        22: aload_3
        23: invokeinterface #499,  1          // InterfaceMethod java/util/List.size:()I
        28: iconst_1
        29: if_icmple     38
        32: ldc_w         #652                // String s
        35: goto          41
        38: ldc_w         #654                // String
        41: aastore
        42: dup
        43: iconst_2
        44: aload_3
        45: invokeinterface #499,  1          // InterfaceMethod java/util/List.size:()I
        50: iconst_1
        51: if_icmple     60
        54: ldc_w         #654                // String
        57: goto          63
        60: ldc_w         #652                // String s
        63: aastore
        64: invokevirtual #656                // Method java/io/PrintWriter.printf:(Ljava/lang/String;[Ljava/lang/Object;)Ljava/io/PrintWriter;
        67: pop
        68: aload_3
        69: invokeinterface #290,  1          // InterfaceMethod java/util/List.iterator:()Ljava/util/Iterator;
        74: astore        4
        76: aload         4
        78: invokeinterface #296,  1          // InterfaceMethod java/util/Iterator.hasNext:()Z
        83: ifeq          278
        86: aload         4
        88: invokeinterface #301,  1          // InterfaceMethod java/util/Iterator.next:()Ljava/lang/Object;
        93: checkcast     #305                // class org/osgi/framework/wiring/BundleRequirement
        96: astore        5
        98: aload_0
        99: getfield      #41                 // Field requirementToSourceFileMap:Ljava/util/Map;
       102: aload         5
       104: invokeinterface #797,  1          // InterfaceMethod org/osgi/framework/wiring/BundleRequirement.toString:()Ljava/lang/String;
       109: invokeinterface #180,  2          // InterfaceMethod java/util/Map.get:(Ljava/lang/Object;)Ljava/lang/Object;
       114: checkcast     #291                // class java/util/List
       117: astore        6
       119: aload         6
       121: ifnull        253
       124: aload         6
       126: invokeinterface #499,  1          // InterfaceMethod java/util/List.size:()I
       131: ifle          253
       134: aload_1
       135: ldc_w         #798                // String   %s, from %s\n
       138: iconst_2
       139: anewarray     #135                // class java/lang/Object
       142: dup
       143: iconst_0
       144: aload         5
       146: invokeinterface #800,  1          // InterfaceMethod org/osgi/framework/wiring/BundleRequirement.toString:()Ljava/lang/String;
       151: aastore
       152: dup
       153: iconst_1
       154: aload         6
       156: invokeinterface #465,  1          // InterfaceMethod java/util/List.stream:()Ljava/util/stream/Stream;
       161: invokedynamic #801,  0            // InvokeDynamic #18:apply:()Ljava/util/function/Function;
       166: invokeinterface #200,  2          // InterfaceMethod java/util/stream/Stream.map:(Ljava/util/function/Function;)Ljava/util/stream/Stream;
       171: ldc_w         #256                // String ,
       174: invokestatic  #802                // Method java/util/stream/Collectors.joining:(Ljava/lang/CharSequence;)Ljava/util/stream/Collector;
       177: invokeinterface #212,  2          // InterfaceMethod java/util/stream/Stream.collect:(Ljava/util/stream/Collector;)Ljava/lang/Object;
       182: aastore
       183: invokevirtual #656                // Method java/io/PrintWriter.printf:(Ljava/lang/String;[Ljava/lang/Object;)Ljava/io/PrintWriter;
       186: pop
       187: aload         6
       189: invokeinterface #290,  1          // InterfaceMethod java/util/List.iterator:()Ljava/util/Iterator;
       194: astore        7
       196: aload         7
       198: invokeinterface #296,  1          // InterfaceMethod java/util/Iterator.hasNext:()Z
       203: ifeq          250
       206: aload         7
       208: invokeinterface #301,  1          // InterfaceMethod java/util/Iterator.next:()Ljava/lang/Object;
       213: checkcast     #109                // class generic/jar/ResourceFile
       216: astore        8
       218: aload_0
       219: aload         8
       221: aload         8
       223: invokestatic  #805                // Method generic/util/Path.toPathString:(Lgeneric/jar/ResourceFile;)Ljava/lang/String;
       226: aload         5
       228: invokeinterface #810,  1          // InterfaceMethod org/osgi/framework/wiring/BundleRequirement.toString:()Ljava/lang/String;
       233: invokestatic  #811                // Method ghidra/app/plugin/core/osgi/OSGiUtils.extractPackageNamesFromFailedResolution:(Ljava/lang/String;)Ljava/util/List;
       236: invokestatic  #814                // Method java/lang/String.valueOf:(Ljava/lang/Object;)Ljava/lang/String;
       239: invokedynamic #817,  0            // InvokeDynamic #19:makeConcatWithConstants:(Ljava/lang/String;Ljava/lang/String;)Ljava/lang/String;
       244: invokevirtual #820                // Method buildError:(Lgeneric/jar/ResourceFile;Ljava/lang/String;)V
       247: goto          196
       250: goto          275
       253: aload_1
       254: ldc_w         #823                // String   %s\n
       257: iconst_1
       258: anewarray     #135                // class java/lang/Object
       261: dup
       262: iconst_0
       263: aload         5
       265: invokeinterface #825,  1          // InterfaceMethod org/osgi/framework/wiring/BundleRequirement.toString:()Ljava/lang/String;
       270: aastore
       271: invokevirtual #656                // Method java/io/PrintWriter.printf:(Ljava/lang/String;[Ljava/lang/Object;)Ljava/io/PrintWriter;
       274: pop
       275: goto          76
       278: aload_3
       279: invokeinterface #499,  1          // InterfaceMethod java/util/List.size:()I
       284: iconst_1
       285: if_icmple     294
       288: ldc_w         #652                // String s
       291: goto          297
       294: ldc_w         #654                // String
       297: astore        4
       299: aload_3
       300: invokeinterface #465,  1          // InterfaceMethod java/util/List.stream:()Ljava/util/stream/Stream;
       305: invokedynamic #826,  0            // InvokeDynamic #20:apply:()Ljava/util/function/Function;
       310: invokeinterface #314,  2          // InterfaceMethod java/util/stream/Stream.flatMap:(Ljava/util/function/Function;)Ljava/util/stream/Stream;
       315: invokeinterface #466,  1          // InterfaceMethod java/util/stream/Stream.distinct:()Ljava/util/stream/Stream;
       320: ldc_w         #256                // String ,
       323: invokestatic  #802                // Method java/util/stream/Collectors.joining:(Ljava/lang/CharSequence;)Ljava/util/stream/Collector;
       326: invokeinterface #212,  2          // InterfaceMethod java/util/stream/Stream.collect:(Ljava/util/stream/Collector;)Ljava/lang/Object;
       331: checkcast     #114                // class java/lang/String
       334: astore        5
       336: aload_2
       337: ldc_w         #827                // String %d missing package import%s:%s
       340: iconst_3
       341: anewarray     #135                // class java/lang/Object
       344: dup
       345: iconst_0
       346: aload_3
       347: invokeinterface #499,  1          // InterfaceMethod java/util/List.size:()I
       352: invokestatic  #648                // Method java/lang/Integer.valueOf:(I)Ljava/lang/Integer;
       355: aastore
       356: dup
       357: iconst_1
       358: aload         4
       360: aastore
       361: dup
       362: iconst_2
       363: aload         5
       365: aastore
       366: invokevirtual #829                // Method ghidra/app/plugin/core/osgi/GhidraSourceBundle$Summary.printf:(Ljava/lang/String;[Ljava/lang/Object;)V
       369: return

  private boolean tryBuild(java.io.PrintWriter, org.phidias.compile.BundleJavaManager, java.util.List<ghidra.app.script.ResourceFileJavaFileObject>, java.util.List<java.lang.String>) throws java.io.IOException;
    Code:
         0: new           #834                // class javax/tools/DiagnosticCollector
         3: dup
         4: invokespecial #836                // Method javax/tools/DiagnosticCollector."<init>":()V
         7: astore        5
         9: aload_0
        10: getfield      #27                 // Field compiler:Ljavax/tools/JavaCompiler;
        13: aload_1
        14: aload_2
        15: aload         5
        17: aload         4
        19: aconst_null
        20: aload_3
        21: invokeinterface #837,  7          // InterfaceMethod javax/tools/JavaCompiler.getTask:(Ljava/io/Writer;Ljavax/tools/JavaFileManager;Ljavax/tools/DiagnosticListener;Ljava/lang/Iterable;Ljava/lang/Iterable;Ljava/lang/Iterable;)Ljavax/tools/JavaCompiler$CompilationTask;
        26: astore        6
        28: aload         6
        30: invokeinterface #843,  1          // InterfaceMethod javax/tools/JavaCompiler$CompilationTask.call:()Ljava/lang/Boolean;
        35: astore        7
        37: aload         7
        39: invokevirtual #849                // Method java/lang/Boolean.booleanValue:()Z
        42: ifeq          47
        45: iconst_1
        46: ireturn
        47: new           #44                 // class java/util/HashSet
        50: dup
        51: invokespecial #46                 // Method java/util/HashSet."<init>":()V
        54: astore        8
        56: aload         5
        58: invokevirtual #854                // Method javax/tools/DiagnosticCollector.getDiagnostics:()Ljava/util/List;
        61: invokeinterface #290,  1          // InterfaceMethod java/util/List.iterator:()Ljava/util/Iterator;
        66: astore        9
        68: aload         9
        70: invokeinterface #296,  1          // InterfaceMethod java/util/Iterator.hasNext:()Z
        75: ifeq          150
        78: aload         9
        80: invokeinterface #301,  1          // InterfaceMethod java/util/Iterator.next:()Ljava/lang/Object;
        85: checkcast     #857                // class javax/tools/Diagnostic
        88: astore        10
        90: aload         10
        92: invokeinterface #859,  1          // InterfaceMethod javax/tools/Diagnostic.toString:()Ljava/lang/String;
        97: invokedynamic #860,  0            // InvokeDynamic #21:makeConcatWithConstants:(Ljava/lang/String;)Ljava/lang/String;
       102: astore        11
       104: aload_1
       105: aload         11
       107: invokevirtual #861                // Method java/io/PrintWriter.write:(Ljava/lang/String;)V
       110: aload         10
       112: invokeinterface #864,  1          // InterfaceMethod javax/tools/Diagnostic.getSource:()Ljava/lang/Object;
       117: checkcast     #867                // class ghidra/app/script/ResourceFileJavaFileObject
       120: astore        12
       122: aload         12
       124: invokevirtual #869                // Method ghidra/app/script/ResourceFileJavaFileObject.getFile:()Lgeneric/jar/ResourceFile;
       127: astore        13
       129: aload_0
       130: aload         13
       132: aload         11
       134: invokevirtual #820                // Method buildError:(Lgeneric/jar/ResourceFile;Ljava/lang/String;)V
       137: aload         8
       139: aload         12
       141: invokeinterface #619,  2          // InterfaceMethod java/util/Set.add:(Ljava/lang/Object;)Z
       146: pop
       147: goto          68
       150: aload         8
       152: invokeinterface #565,  1          // InterfaceMethod java/util/Set.iterator:()Ljava/util/Iterator;
       157: astore        9
       159: aload         9
       161: invokeinterface #296,  1          // InterfaceMethod java/util/Iterator.hasNext:()Z
       166: ifeq          242
       169: aload         9
       171: invokeinterface #301,  1          // InterfaceMethod java/util/Iterator.next:()Ljava/lang/Object;
       176: checkcast     #867                // class ghidra/app/script/ResourceFileJavaFileObject
       179: astore        10
       181: aload_3
       182: aload         10
       184: invokeinterface #872,  2          // InterfaceMethod java/util/List.remove:(Ljava/lang/Object;)Z
       189: ifeq          218
       192: aload_1
       193: ldc_w         #874                // String skipping %s\n
       196: iconst_1
       197: anewarray     #135                // class java/lang/Object
       200: dup
       201: iconst_0
       202: aload         10
       204: invokevirtual #869                // Method ghidra/app/script/ResourceFileJavaFileObject.getFile:()Lgeneric/jar/ResourceFile;
       207: invokevirtual #647                // Method generic/jar/ResourceFile.toString:()Ljava/lang/String;
       210: aastore
       211: invokevirtual #656                // Method java/io/PrintWriter.printf:(Ljava/lang/String;[Ljava/lang/Object;)Ljava/io/PrintWriter;
       214: pop
       215: goto          239
       218: new           #371                // class java/io/IOException
       221: dup
       222: aload         10
       224: invokevirtual #869                // Method ghidra/app/script/ResourceFileJavaFileObject.getFile:()Lgeneric/jar/ResourceFile;
       227: invokevirtual #647                // Method generic/jar/ResourceFile.toString:()Ljava/lang/String;
       230: invokedynamic #876,  0            // InvokeDynamic #22:makeConcatWithConstants:(Ljava/lang/String;)Ljava/lang/String;
       235: invokespecial #877                // Method java/io/IOException."<init>":(Ljava/lang/String;)V
       238: athrow
       239: goto          159
       242: iconst_0
       243: ireturn

  private java.lang.String generateManifest(java.io.PrintWriter, ghidra.app.plugin.core.osgi.GhidraSourceBundle$Summary, java.nio.file.Path) throws ghidra.app.plugin.core.osgi.OSGiException, java.io.IOException;
    Code:
         0: new           #878                // class aQute/bnd/osgi/Analyzer
         3: dup
         4: invokespecial #880                // Method aQute/bnd/osgi/Analyzer."<init>":()V
         7: astore        4
         9: aload         4
        11: new           #881                // class aQute/bnd/osgi/Jar
        14: dup
        15: aload_0
        16: getfield      #76                 // Field binaryDir:Ljava/nio/file/Path;
        19: invokeinterface #524,  1          // InterfaceMethod java/nio/file/Path.toFile:()Ljava/io/File;
        24: invokespecial #883                // Method aQute/bnd/osgi/Jar."<init>":(Ljava/io/File;)V
        27: invokevirtual #884                // Method aQute/bnd/osgi/Analyzer.setJar:(LaQute/bnd/osgi/Jar;)LaQute/bnd/osgi/Jar;
        30: pop
        31: aload         4
        33: ldc_w         #888                // String Bundle-SymbolicName
        36: aload_0
        37: invokevirtual #54                 // Method getSourceDirectory:()Lgeneric/jar/ResourceFile;
        40: invokestatic  #58                 // Method sourceDirHash:(Lgeneric/jar/ResourceFile;)Ljava/lang/String;
        43: invokevirtual #890                // Method aQute/bnd/osgi/Analyzer.setProperty:(Ljava/lang/String;Ljava/lang/String;)V
        46: aload         4
        48: ldc_w         #894                // String Bundle-Version
        51: ldc_w         #896                // String 1.0
        54: invokevirtual #890                // Method aQute/bnd/osgi/Analyzer.setProperty:(Ljava/lang/String;Ljava/lang/String;)V
        57: aload_0
        58: getfield      #51                 // Field importPackageValues:Ljava/util/Set;
        61: invokeinterface #898,  1          // InterfaceMethod java/util/Set.isEmpty:()Z
        66: ifeq          83
        69: aload         4
        71: ldc_w         #899                // String Import-Package
        74: ldc_w         #901                // String *
        77: invokevirtual #890                // Method aQute/bnd/osgi/Analyzer.setProperty:(Ljava/lang/String;Ljava/lang/String;)V
        80: goto          119
        83: aload         4
        85: ldc_w         #899                // String Import-Package
        88: aload_0
        89: getfield      #51                 // Field importPackageValues:Ljava/util/Set;
        92: invokeinterface #350,  1          // InterfaceMethod java/util/Set.stream:()Ljava/util/stream/Stream;
        97: ldc_w         #256                // String ,
       100: invokestatic  #802                // Method java/util/stream/Collectors.joining:(Ljava/lang/CharSequence;)Ljava/util/stream/Collector;
       103: invokeinterface #212,  2          // InterfaceMethod java/util/stream/Stream.collect:(Ljava/util/stream/Collector;)Ljava/lang/Object;
       108: checkcast     #114                // class java/lang/String
       111: invokedynamic #903,  0            // InvokeDynamic #23:makeConcatWithConstants:(Ljava/lang/String;)Ljava/lang/String;
       116: invokevirtual #890                // Method aQute/bnd/osgi/Analyzer.setProperty:(Ljava/lang/String;Ljava/lang/String;)V
       119: aload         4
       121: ldc_w         #904                // String Export-Package
       124: ldc_w         #906                // String !*.private.*,!*.internal.*,*
       127: invokevirtual #890                // Method aQute/bnd/osgi/Analyzer.setProperty:(Ljava/lang/String;Ljava/lang/String;)V
       130: ldc_w         #910                // String application.java.min
       133: invokestatic  #912                // Method ghidra/framework/Application.getApplicationProperty:(Ljava/lang/String;)Ljava/lang/String;
       136: astore        5
       138: aload         5
       140: ifnull        166
       143: aload         4
       145: ldc_w         #917                // String Require-Capability
       148: ldc_w         #919                // String osgi.ee;filter:=\"(&(osgi.ee=JavaSE)(version>=%s))\"
       151: iconst_1
       152: anewarray     #135                // class java/lang/Object
       155: dup
       156: iconst_0
       157: aload         5
       159: aastore
       160: invokevirtual #921                // Method java/lang/String.formatted:([Ljava/lang/Object;)Ljava/lang/String;
       163: invokevirtual #890                // Method aQute/bnd/osgi/Analyzer.setProperty:(Ljava/lang/String;Ljava/lang/String;)V
       166: aload         4
       168: invokevirtual #925                // Method aQute/bnd/osgi/Analyzer.calcManifest:()Ljava/util/jar/Manifest;
       171: astore        6
       173: goto          198
       176: astore        7
       178: aload_2
       179: ldc_w         #931                // String Bad manifest
       182: invokevirtual #933                // Method ghidra/app/plugin/core/osgi/GhidraSourceBundle$Summary.print:(Ljava/lang/String;)V
       185: new           #936                // class ghidra/app/plugin/core/osgi/OSGiException
       188: dup
       189: ldc_w         #938                // String Failed to calculate manifest by analyzing code
       192: aload         7
       194: invokespecial #940                // Method ghidra/app/plugin/core/osgi/OSGiException."<init>":(Ljava/lang/String;Ljava/lang/Throwable;)V
       197: athrow
       198: aload_0
       199: aload_1
       200: aload         4
       202: aload         6
       204: aload_2
       205: invokevirtual #943                // Method addActivatorClass:(Ljava/io/PrintWriter;LaQute/bnd/osgi/Analyzer;Ljava/util/jar/Manifest;Lghidra/app/plugin/core/osgi/GhidraSourceBundle$Summary;)Z
       208: ifne          225
       211: aload_2
       212: invokevirtual #947                // Method ghidra/app/plugin/core/osgi/GhidraSourceBundle$Summary.getValue:()Ljava/lang/String;
       215: astore        7
       217: aload         4
       219: invokevirtual #949                // Method aQute/bnd/osgi/Analyzer.close:()V
       222: aload         7
       224: areturn
       225: aload_3
       226: invokeinterface #950,  1          // InterfaceMethod java/nio/file/Path.getParent:()Ljava/nio/file/Path;
       231: iconst_0
       232: anewarray     #953                // class java/nio/file/attribute/FileAttribute
       235: invokestatic  #955                // Method java/nio/file/Files.createDirectories:(Ljava/nio/file/Path;[Ljava/nio/file/attribute/FileAttribute;)Ljava/nio/file/Path;
       238: pop
       239: aload_3
       240: iconst_0
       241: anewarray     #959                // class java/nio/file/OpenOption
       244: invokestatic  #961                // Method java/nio/file/Files.newOutputStream:(Ljava/nio/file/Path;[Ljava/nio/file/OpenOption;)Ljava/io/OutputStream;
       247: astore        7
       249: aload         6
       251: aload         7
       253: invokevirtual #965                // Method java/util/jar/Manifest.write:(Ljava/io/OutputStream;)V
       256: aload         7
       258: ifnull        296
       261: aload         7
       263: invokevirtual #968                // Method java/io/OutputStream.close:()V
       266: goto          296
       269: astore        8
       271: aload         7
       273: ifnull        293
       276: aload         7
       278: invokevirtual #968                // Method java/io/OutputStream.close:()V
       281: goto          293
       284: astore        9
       286: aload         8
       288: aload         9
       290: invokevirtual #367                // Method java/lang/Throwable.addSuppressed:(Ljava/lang/Throwable;)V
       293: aload         8
       295: athrow
       296: aload         4
       298: invokevirtual #949                // Method aQute/bnd/osgi/Analyzer.close:()V
       301: goto          314
       304: astore        10
       306: aload         4
       308: invokevirtual #949                // Method aQute/bnd/osgi/Analyzer.close:()V
       311: aload         10
       313: athrow
       314: aload_2
       315: invokevirtual #947                // Method ghidra/app/plugin/core/osgi/GhidraSourceBundle$Summary.getValue:()Ljava/lang/String;
       318: areturn
      Exception table:
         from    to  target type
           166   173   176   Class java/lang/Exception
           249   256   269   Class java/lang/Throwable
           276   281   284   Class java/lang/Throwable
           166   217   304   any
           225   296   304   any
           304   306   304   any

  private boolean addActivatorClass(java.io.PrintWriter, aQute.bnd.osgi.Analyzer, java.util.jar.Manifest, ghidra.app.plugin.core.osgi.GhidraSourceBundle$Summary) throws ghidra.app.plugin.core.osgi.OSGiException, java.io.IOException;
    Code:
         0: aconst_null
         1: astore        5
         3: aload_2
         4: invokevirtual #971                // Method aQute/bnd/osgi/Analyzer.getClassspace:()Ljava/util/Map;
         7: invokeinterface #189,  1          // InterfaceMethod java/util/Map.values:()Ljava/util/Collection;
        12: invokeinterface #974,  1          // InterfaceMethod java/util/Collection.iterator:()Ljava/util/Iterator;
        17: astore        6
        19: aload         6
        21: invokeinterface #296,  1          // InterfaceMethod java/util/Iterator.hasNext:()Z
        26: ifeq          87
        29: aload         6
        31: invokeinterface #301,  1          // InterfaceMethod java/util/Iterator.next:()Ljava/lang/Object;
        36: checkcast     #975                // class aQute/bnd/osgi/Clazz
        39: astore        7
        41: aload         7
        43: getstatic     #977                // Field aQute/bnd/osgi/Clazz$QUERY.IMPLEMENTS:LaQute/bnd/osgi/Clazz$QUERY;
        46: new           #983                // class aQute/bnd/osgi/Instruction
        49: dup
        50: ldc_w         #985                // String org.osgi.framework.BundleActivator
        53: invokespecial #987                // Method aQute/bnd/osgi/Instruction."<init>":(Ljava/lang/String;)V
        56: aload_2
        57: invokevirtual #988                // Method aQute/bnd/osgi/Clazz.is:(LaQute/bnd/osgi/Clazz$QUERY;LaQute/bnd/osgi/Instruction;LaQute/bnd/osgi/Analyzer;)Z
        60: ifeq          84
        63: aload_0
        64: aload         7
        66: invokestatic  #814                // Method java/lang/String.valueOf:(Ljava/lang/Object;)Ljava/lang/String;
        69: invokedynamic #992,  0            // InvokeDynamic #24:makeConcatWithConstants:(Ljava/lang/String;)Ljava/lang/String;
        74: invokestatic  #993                // Method ghidra/util/Msg.trace:(Ljava/lang/Object;Ljava/lang/Object;)V
        77: aload         7
        79: invokevirtual #997                // Method aQute/bnd/osgi/Clazz.toString:()Ljava/lang/String;
        82: astore        5
        84: goto          19
        87: goto          113
        90: astore        6
        92: aload         4
        94: ldc_w         #998                // String Failed bnd analysis
        97: invokevirtual #933                // Method ghidra/app/plugin/core/osgi/GhidraSourceBundle$Summary.print:(Ljava/lang/String;)V
       100: new           #936                // class ghidra/app/plugin/core/osgi/OSGiException
       103: dup
       104: ldc_w         #1000               // String Failed to query classes while searching for activator
       107: aload         6
       109: invokespecial #940                // Method ghidra/app/plugin/core/osgi/OSGiException."<init>":(Ljava/lang/String;Ljava/lang/Throwable;)V
       112: athrow
       113: aload_3
       114: invokevirtual #340                // Method java/util/jar/Manifest.getMainAttributes:()Ljava/util/jar/Attributes;
       117: astore        6
       119: aload         5
       121: ifnull        137
       124: aload         6
       126: ldc_w         #1004               // String Bundle-Activator
       129: aload         5
       131: invokevirtual #1006               // Method java/util/jar/Attributes.putValue:(Ljava/lang/String;Ljava/lang/String;)Ljava/lang/String;
       134: pop
       135: iconst_1
       136: ireturn
       137: ldc_w         #1009               // String GeneratedActivator
       140: astore        5
       142: aload_0
       143: aload_0
       144: getfield      #76                 // Field binaryDir:Ljava/nio/file/Path;
       147: aload         5
       149: aload_1
       150: invokevirtual #1011               // Method buildDefaultActivator:(Ljava/nio/file/Path;Ljava/lang/String;Ljava/io/Writer;)Z
       153: ifne          166
       156: aload         4
       158: ldc_w         #1015               // String Failed to build generated activator
       161: invokevirtual #933                // Method ghidra/app/plugin/core/osgi/GhidraSourceBundle$Summary.print:(Ljava/lang/String;)V
       164: iconst_0
       165: ireturn
       166: aload         6
       168: ldc_w         #899                // String Import-Package
       171: invokevirtual #1017               // Method java/util/jar/Attributes.getValue:(Ljava/lang/String;)Ljava/lang/String;
       174: astore        7
       176: ldc_w         #1019               // class ghidra/app/plugin/core/osgi/GhidraBundleActivator
       179: invokevirtual #1021               // Method java/lang/Class.getPackageName:()Ljava/lang/String;
       182: astore        8
       184: aload         7
       186: ifnonnull     203
       189: aload         6
       191: ldc_w         #899                // String Import-Package
       194: aload         8
       196: invokevirtual #1006               // Method java/util/jar/Attributes.putValue:(Ljava/lang/String;Ljava/lang/String;)Ljava/lang/String;
       199: pop
       200: goto          221
       203: aload         6
       205: ldc_w         #899                // String Import-Package
       208: aload         7
       210: aload         8
       212: invokedynamic #1026,  0           // InvokeDynamic #25:makeConcatWithConstants:(Ljava/lang/String;Ljava/lang/String;)Ljava/lang/String;
       217: invokevirtual #1006               // Method java/util/jar/Attributes.putValue:(Ljava/lang/String;Ljava/lang/String;)Ljava/lang/String;
       220: pop
       221: aload         6
       223: ldc_w         #1004               // String Bundle-Activator
       226: aload         5
       228: invokevirtual #1006               // Method java/util/jar/Attributes.putValue:(Ljava/lang/String;Ljava/lang/String;)Ljava/lang/String;
       231: pop
       232: iconst_1
       233: ireturn
      Exception table:
         from    to  target type
             3    87    90   Class java/lang/Exception

  private boolean buildDefaultActivator(java.nio.file.Path, java.lang.String, java.io.Writer) throws java.io.IOException;
    Code:
         0: aload_1
         1: aload_2
         2: invokedynamic #1027,  0           // InvokeDynamic #26:makeConcatWithConstants:(Ljava/lang/String;)Ljava/lang/String;
         7: invokeinterface #70,  2           // InterfaceMethod java/nio/file/Path.resolve:(Ljava/lang/String;)Ljava/nio/file/Path;
        12: astore        4
        14: new           #657                // class java/io/PrintWriter
        17: dup
        18: aload         4
        20: ldc_w         #1028               // String UTF-8
        23: invokestatic  #1030               // Method java/nio/charset/Charset.forName:(Ljava/lang/String;)Ljava/nio/charset/Charset;
        26: iconst_0
        27: anewarray     #959                // class java/nio/file/OpenOption
        30: invokestatic  #1036               // Method java/nio/file/Files.newBufferedWriter:(Ljava/nio/file/Path;Ljava/nio/charset/Charset;[Ljava/nio/file/OpenOption;)Ljava/io/BufferedWriter;
        33: invokespecial #1040               // Method java/io/PrintWriter."<init>":(Ljava/io/Writer;)V
        36: astore        5
        38: aload         5
        40: ldc_w         #1019               // class ghidra/app/plugin/core/osgi/GhidraBundleActivator
        43: invokevirtual #1043               // Method java/lang/Class.getName:()Ljava/lang/String;
        46: invokedynamic #1044,  0           // InvokeDynamic #27:makeConcatWithConstants:(Ljava/lang/String;)Ljava/lang/String;
        51: invokevirtual #1045               // Method java/io/PrintWriter.println:(Ljava/lang/String;)V
        54: aload         5
        56: ldc_w         #1048               // String import org.osgi.framework.BundleActivator;
        59: invokevirtual #1045               // Method java/io/PrintWriter.println:(Ljava/lang/String;)V
        62: aload         5
        64: ldc_w         #1050               // String import org.osgi.framework.BundleContext;
        67: invokevirtual #1045               // Method java/io/PrintWriter.println:(Ljava/lang/String;)V
        70: aload         5
        72: ldc_w         #1052               // String public class GeneratedActivator extends GhidraBundleActivator {
        75: invokevirtual #1045               // Method java/io/PrintWriter.println:(Ljava/lang/String;)V
        78: aload         5
        80: ldc_w         #1054               // String   protected void start(BundleContext bc, Object api) {
        83: invokevirtual #1045               // Method java/io/PrintWriter.println:(Ljava/lang/String;)V
        86: aload         5
        88: ldc_w         #1056               // String     // TODO: stuff to do on bundle start
        91: invokevirtual #1045               // Method java/io/PrintWriter.println:(Ljava/lang/String;)V
        94: aload         5
        96: ldc_w         #1058               // String   }
        99: invokevirtual #1045               // Method java/io/PrintWriter.println:(Ljava/lang/String;)V
       102: aload         5
       104: ldc_w         #1060               // String   protected void stop(BundleContext bc, Object api) {
       107: invokevirtual #1045               // Method java/io/PrintWriter.println:(Ljava/lang/String;)V
       110: aload         5
       112: ldc_w         #1062               // String     // TODO: stuff to do on bundle stop
       115: invokevirtual #1045               // Method java/io/PrintWriter.println:(Ljava/lang/String;)V
       118: aload         5
       120: ldc_w         #1058               // String   }
       123: invokevirtual #1045               // Method java/io/PrintWriter.println:(Ljava/lang/String;)V
       126: aload         5
       128: invokevirtual #1064               // Method java/io/PrintWriter.println:()V
       131: aload         5
       133: ldc_w         #1066               // String }
       136: invokevirtual #1045               // Method java/io/PrintWriter.println:(Ljava/lang/String;)V
       139: aload         5
       141: invokevirtual #1068               // Method java/io/PrintWriter.close:()V
       144: goto          169
       147: astore        6
       149: aload         5
       151: invokevirtual #1068               // Method java/io/PrintWriter.close:()V
       154: goto          166
       157: astore        7
       159: aload         6
       161: aload         7
       163: invokevirtual #367                // Method java/lang/Throwable.addSuppressed:(Ljava/lang/Throwable;)V
       166: aload         6
       168: athrow
       169: new           #7                  // class java/util/ArrayList
       172: dup
       173: invokespecial #9                  // Method java/util/ArrayList."<init>":()V
       176: astore        5
       178: aload         5
       180: ldc_w         #1069               // String -g
       183: invokeinterface #309,  2          // InterfaceMethod java/util/List.add:(Ljava/lang/Object;)Z
       188: pop
       189: aload         5
       191: ldc_w         #1071               // String -d
       194: invokeinterface #309,  2          // InterfaceMethod java/util/List.add:(Ljava/lang/Object;)Z
       199: pop
       200: aload         5
       202: aload_1
       203: invokeinterface #86,  1           // InterfaceMethod java/nio/file/Path.toString:()Ljava/lang/String;
       208: invokeinterface #309,  2          // InterfaceMethod java/util/List.add:(Ljava/lang/Object;)Z
       213: pop
       214: aload         5
       216: ldc_w         #1073               // String -sourcepath
       219: invokeinterface #309,  2          // InterfaceMethod java/util/List.add:(Ljava/lang/Object;)Z
       224: pop
       225: aload         5
       227: aload_1
       228: invokeinterface #86,  1           // InterfaceMethod java/nio/file/Path.toString:()Ljava/lang/String;
       233: invokeinterface #309,  2          // InterfaceMethod java/util/List.add:(Ljava/lang/Object;)Z
       238: pop
       239: aload         5
       241: ldc_w         #1075               // String -classpath
       244: invokeinterface #309,  2          // InterfaceMethod java/util/List.add:(Ljava/lang/Object;)Z
       249: pop
       250: aload         5
       252: ldc_w         #1077               // String java.class.path
       255: invokestatic  #1079               // Method java/lang/System.getProperty:(Ljava/lang/String;)Ljava/lang/String;
       258: invokeinterface #309,  2          // InterfaceMethod java/util/List.add:(Ljava/lang/Object;)Z
       263: pop
       264: aload         5
       266: ldc_w         #1084               // String -proc:none
       269: invokeinterface #309,  2          // InterfaceMethod java/util/List.add:(Ljava/lang/Object;)Z
       274: pop
       275: aload_0
       276: getfield      #27                 // Field compiler:Ljavax/tools/JavaCompiler;
       279: aconst_null
       280: aconst_null
       281: aconst_null
       282: invokeinterface #1086,  4         // InterfaceMethod javax/tools/JavaCompiler.getStandardFileManager:(Ljavax/tools/DiagnosticListener;Ljava/util/Locale;Ljava/nio/charset/Charset;)Ljavax/tools/StandardJavaFileManager;
       287: astore        6
       289: new           #774                // class ghidra/app/plugin/core/osgi/GhidraSourceBundle$MyBundleJavaManager
       292: dup
       293: aload_0
       294: getfield      #567                // Field bundleHost:Lghidra/app/plugin/core/osgi/BundleHost;
       297: invokevirtual #776                // Method ghidra/app/plugin/core/osgi/BundleHost.getHostFramework:()Lorg/osgi/framework/launch/Framework;
       300: aload         6
       302: aload         5
       304: invokespecial #780                // Method ghidra/app/plugin/core/osgi/GhidraSourceBundle$MyBundleJavaManager."<init>":(Lorg/osgi/framework/Bundle;Ljavax/tools/JavaFileManager;Ljava/util/List;)V
       307: astore        7
       309: aload         6
       311: aload         4
       313: invokestatic  #1090               // InterfaceMethod java/util/List.of:(Ljava/lang/Object;)Ljava/util/List;
       316: invokeinterface #1093,  2         // InterfaceMethod javax/tools/StandardJavaFileManager.getJavaFileObjectsFromPaths:(Ljava/util/Collection;)Ljava/lang/Iterable;
       321: astore        8
       323: new           #834                // class javax/tools/DiagnosticCollector
       326: dup
       327: invokespecial #836                // Method javax/tools/DiagnosticCollector."<init>":()V
       330: astore        9
       332: aload_0
       333: getfield      #27                 // Field compiler:Ljavax/tools/JavaCompiler;
       336: aload_3
       337: aload         7
       339: aload         9
       341: aload         5
       343: aconst_null
       344: aload         8
       346: invokeinterface #837,  7          // InterfaceMethod javax/tools/JavaCompiler.getTask:(Ljava/io/Writer;Ljavax/tools/JavaFileManager;Ljavax/tools/DiagnosticListener;Ljava/lang/Iterable;Ljava/lang/Iterable;Ljava/lang/Iterable;)Ljavax/tools/JavaCompiler$CompilationTask;
       351: astore        10
       353: aload         10
       355: invokeinterface #843,  1          // InterfaceMethod javax/tools/JavaCompiler$CompilationTask.call:()Ljava/lang/Boolean;
       360: invokevirtual #849                // Method java/lang/Boolean.booleanValue:()Z
       363: ifeq          389
       366: iconst_1
       367: istore        11
       369: aload         7
       371: invokevirtual #1099               // Method org/phidias/compile/BundleJavaManager.close:()V
       374: aload         6
       376: ifnull        386
       379: aload         6
       381: invokeinterface #1102,  1         // InterfaceMethod javax/tools/StandardJavaFileManager.close:()V
       386: iload         11
       388: ireturn
       389: aload         9
       391: invokevirtual #854                // Method javax/tools/DiagnosticCollector.getDiagnostics:()Ljava/util/List;
       394: invokeinterface #290,  1          // InterfaceMethod java/util/List.iterator:()Ljava/util/Iterator;
       399: astore        11
       401: aload         11
       403: invokeinterface #296,  1          // InterfaceMethod java/util/Iterator.hasNext:()Z
       408: ifeq          458
       411: aload         11
       413: invokeinterface #301,  1          // InterfaceMethod java/util/Iterator.next:()Ljava/lang/Object;
       418: checkcast     #857                // class javax/tools/Diagnostic
       421: astore        12
       423: aload_3
       424: aload         12
       426: invokeinterface #864,  1          // InterfaceMethod javax/tools/Diagnostic.getSource:()Ljava/lang/Object;
       431: checkcast     #1103               // class javax/tools/JavaFileObject
       434: invokeinterface #1105,  1         // InterfaceMethod javax/tools/JavaFileObject.toString:()Ljava/lang/String;
       439: aload         12
       441: aconst_null
       442: invokeinterface #1106,  2         // InterfaceMethod javax/tools/Diagnostic.getMessage:(Ljava/util/Locale;)Ljava/lang/String;
       447: invokedynamic #1110,  0           // InvokeDynamic #28:makeConcatWithConstants:(Ljava/lang/String;Ljava/lang/String;)Ljava/lang/String;
       452: invokevirtual #1111               // Method java/io/Writer.write:(Ljava/lang/String;)V
       455: goto          401
       458: iconst_0
       459: istore        11
       461: aload         7
       463: invokevirtual #1099               // Method org/phidias/compile/BundleJavaManager.close:()V
       466: aload         6
       468: ifnull        478
       471: aload         6
       473: invokeinterface #1102,  1         // InterfaceMethod javax/tools/StandardJavaFileManager.close:()V
       478: iload         11
       480: ireturn
       481: astore        8
       483: aload         7
       485: invokevirtual #1099               // Method org/phidias/compile/BundleJavaManager.close:()V
       488: goto          500
       491: astore        9
       493: aload         8
       495: aload         9
       497: invokevirtual #367                // Method java/lang/Throwable.addSuppressed:(Ljava/lang/Throwable;)V
       500: aload         8
       502: athrow
       503: astore        7
       505: aload         6
       507: ifnull        529
       510: aload         6
       512: invokeinterface #1102,  1         // InterfaceMethod javax/tools/StandardJavaFileManager.close:()V
       517: goto          529
       520: astore        8
       522: aload         7
       524: aload         8
       526: invokevirtual #367                // Method java/lang/Throwable.addSuppressed:(Ljava/lang/Throwable;)V
       529: aload         7
       531: athrow
      Exception table:
         from    to  target type
            38   139   147   Class java/lang/Throwable
           149   154   157   Class java/lang/Throwable
           309   369   481   Class java/lang/Throwable
           389   461   481   Class java/lang/Throwable
           483   488   491   Class java/lang/Throwable
           289   374   503   Class java/lang/Throwable
           389   466   503   Class java/lang/Throwable
           481   503   503   Class java/lang/Throwable
           510   517   520   Class java/lang/Throwable

  private java.lang.String compileToExplodedBundle(java.io.PrintWriter) throws java.io.IOException, ghidra.app.plugin.core.osgi.OSGiException;
    Code:
         0: aload_0
         1: getfield      #76                 // Field binaryDir:Ljava/nio/file/Path;
         4: iconst_0
         5: anewarray     #953                // class java/nio/file/attribute/FileAttribute
         8: invokestatic  #955                // Method java/nio/file/Files.createDirectories:(Ljava/nio/file/Path;[Ljava/nio/file/attribute/FileAttribute;)Ljava/nio/file/Path;
        11: pop
        12: new           #830                // class ghidra/app/plugin/core/osgi/GhidraSourceBundle$Summary
        15: dup
        16: invokespecial #1114               // Method ghidra/app/plugin/core/osgi/GhidraSourceBundle$Summary."<init>":()V
        19: astore_2
        20: new           #7                  // class java/util/ArrayList
        23: dup
        24: invokespecial #9                  // Method java/util/ArrayList."<init>":()V
        27: astore_3
        28: aload_3
        29: ldc_w         #1069               // String -g
        32: invokeinterface #309,  2          // InterfaceMethod java/util/List.add:(Ljava/lang/Object;)Z
        37: pop
        38: aload_3
        39: ldc_w         #1071               // String -d
        42: invokeinterface #309,  2          // InterfaceMethod java/util/List.add:(Ljava/lang/Object;)Z
        47: pop
        48: aload_3
        49: aload_0
        50: getfield      #76                 // Field binaryDir:Ljava/nio/file/Path;
        53: invokeinterface #86,  1           // InterfaceMethod java/nio/file/Path.toString:()Ljava/lang/String;
        58: invokeinterface #309,  2          // InterfaceMethod java/util/List.add:(Ljava/lang/Object;)Z
        63: pop
        64: aload_3
        65: ldc_w         #1073               // String -sourcepath
        68: invokeinterface #309,  2          // InterfaceMethod java/util/List.add:(Ljava/lang/Object;)Z
        73: pop
        74: aload_3
        75: aload_0
        76: invokevirtual #54                 // Method getSourceDirectory:()Lgeneric/jar/ResourceFile;
        79: invokevirtual #647                // Method generic/jar/ResourceFile.toString:()Ljava/lang/String;
        82: invokeinterface #309,  2          // InterfaceMethod java/util/List.add:(Ljava/lang/Object;)Z
        87: pop
        88: aload_3
        89: ldc_w         #1075               // String -classpath
        92: invokeinterface #309,  2          // InterfaceMethod java/util/List.add:(Ljava/lang/Object;)Z
        97: pop
        98: aload_3
        99: ldc_w         #1077               // String java.class.path
       102: invokestatic  #1079               // Method java/lang/System.getProperty:(Ljava/lang/String;)Ljava/lang/String;
       105: getstatic     #1115               // Field java/io/File.pathSeparator:Ljava/lang/String;
       108: aload_0
       109: getfield      #76                 // Field binaryDir:Ljava/nio/file/Path;
       112: invokeinterface #86,  1           // InterfaceMethod java/nio/file/Path.toString:()Ljava/lang/String;
       117: invokedynamic #1118,  0           // InvokeDynamic #29:makeConcatWithConstants:(Ljava/lang/String;Ljava/lang/String;Ljava/lang/String;)Ljava/lang/String;
       122: invokeinterface #309,  2          // InterfaceMethod java/util/List.add:(Ljava/lang/Object;)Z
       127: pop
       128: aload_3
       129: ldc_w         #1084               // String -proc:none
       132: invokeinterface #309,  2          // InterfaceMethod java/util/List.add:(Ljava/lang/Object;)Z
       137: pop
       138: aload_0
       139: getfield      #12                 // Field newSources:Ljava/util/List;
       142: invokeinterface #290,  1          // InterfaceMethod java/util/List.iterator:()Ljava/util/Iterator;
       147: astore        4
       149: aload         4
       151: invokeinterface #296,  1          // InterfaceMethod java/util/Iterator.hasNext:()Z
       156: ifeq          180
       159: aload         4
       161: invokeinterface #301,  1          // InterfaceMethod java/util/Iterator.next:()Ljava/lang/Object;
       166: checkcast     #109                // class generic/jar/ResourceFile
       169: astore        5
       171: aload_0
       172: aload         5
       174: invokevirtual #1121               // Method clearBuildErrors:(Lgeneric/jar/ResourceFile;)V
       177: goto          149
       180: aload_0
       181: aload_1
       182: aload_2
       183: aload_3
       184: invokevirtual #1125               // Method createBundleJavaManager:(Ljava/io/PrintWriter;Lghidra/app/plugin/core/osgi/GhidraSourceBundle$Summary;Ljava/util/List;)Lorg/phidias/compile/BundleJavaManager;
       187: astore        4
       189: aload_0
       190: getfield      #12                 // Field newSources:Ljava/util/List;
       193: invokeinterface #465,  1          // InterfaceMethod java/util/List.stream:()Ljava/util/stream/Stream;
       198: invokedynamic #1129,  0           // InvokeDynamic #30:apply:()Ljava/util/function/Function;
       203: invokeinterface #200,  2          // InterfaceMethod java/util/stream/Stream.map:(Ljava/util/function/Function;)Ljava/util/stream/Stream;
       208: invokestatic  #1130               // Method java/util/stream/Collectors.toList:()Ljava/util/stream/Collector;
       211: invokeinterface #212,  2          // InterfaceMethod java/util/stream/Stream.collect:(Ljava/util/stream/Collector;)Ljava/lang/Object;
       216: checkcast     #291                // class java/util/List
       219: astore        5
       221: aload_0
       222: invokevirtual #515                // Method getBinaryManifestPath:()Ljava/nio/file/Path;
       225: astore        6
       227: aload         6
       229: iconst_0
       230: anewarray     #518                // class java/nio/file/LinkOption
       233: invokestatic  #529                // Method java/nio/file/Files.exists:(Ljava/nio/file/Path;[Ljava/nio/file/LinkOption;)Z
       236: ifeq          244
       239: aload         6
       241: invokestatic  #490                // Method java/nio/file/Files.delete:(Ljava/nio/file/Path;)V
       244: aload         5
       246: invokeinterface #566,  1          // InterfaceMethod java/util/List.isEmpty:()Z
       251: ifne          270
       254: aload_0
       255: aload_1
       256: aload         4
       258: aload         5
       260: aload_3
       261: invokevirtual #1133               // Method tryBuild:(Ljava/io/PrintWriter;Lorg/phidias/compile/BundleJavaManager;Ljava/util/List;Ljava/util/List;)Z
       264: ifeq          244
       267: goto          270
       270: aload_0
       271: invokevirtual #639                // Method getBuildErrorCount:()I
       274: ifle          320
       277: aload_0
       278: invokevirtual #639                // Method getBuildErrorCount:()I
       281: istore        7
       283: aload_2
       284: ldc_w         #1137               // String %d source file%s with errors
       287: iconst_2
       288: anewarray     #135                // class java/lang/Object
       291: dup
       292: iconst_0
       293: iload         7
       295: invokestatic  #648                // Method java/lang/Integer.valueOf:(I)Ljava/lang/Integer;
       298: aastore
       299: dup
       300: iconst_1
       301: iload         7
       303: iconst_1
       304: if_icmple     313
       307: ldc_w         #652                // String s
       310: goto          316
       313: ldc_w         #654                // String
       316: aastore
       317: invokevirtual #829                // Method ghidra/app/plugin/core/osgi/GhidraSourceBundle$Summary.printf:(Ljava/lang/String;[Ljava/lang/Object;)V
       320: aload_0
       321: invokevirtual #325                // Method getSourceManifestFile:()Lgeneric/jar/ResourceFile;
       324: astore        7
       326: aload         7
       328: invokevirtual #328                // Method generic/jar/ResourceFile.exists:()Z
       331: ifeq          433
       334: aload         6
       336: invokeinterface #950,  1          // InterfaceMethod java/nio/file/Path.getParent:()Ljava/nio/file/Path;
       341: iconst_0
       342: anewarray     #953                // class java/nio/file/attribute/FileAttribute
       345: invokestatic  #955                // Method java/nio/file/Files.createDirectories:(Ljava/nio/file/Path;[Ljava/nio/file/attribute/FileAttribute;)Ljava/nio/file/Path;
       348: pop
       349: aload         7
       351: invokevirtual #331                // Method generic/jar/ResourceFile.getInputStream:()Ljava/io/InputStream;
       354: astore        8
       356: aload         8
       358: aload         6
       360: iconst_1
       361: anewarray     #1139               // class java/nio/file/CopyOption
       364: dup
       365: iconst_0
       366: getstatic     #1141               // Field java/nio/file/StandardCopyOption.REPLACE_EXISTING:Ljava/nio/file/StandardCopyOption;
       369: aastore
       370: invokestatic  #1147               // Method java/nio/file/Files.copy:(Ljava/io/InputStream;Ljava/nio/file/Path;[Ljava/nio/file/CopyOption;)J
       373: pop2
       374: aload         8
       376: ifnull        414
       379: aload         8
       381: invokevirtual #360                // Method java/io/InputStream.close:()V
       384: goto          414
       387: astore        9
       389: aload         8
       391: ifnull        411
       394: aload         8
       396: invokevirtual #360                // Method java/io/InputStream.close:()V
       399: goto          411
       402: astore        10
       404: aload         9
       406: aload         10
       408: invokevirtual #367                // Method java/lang/Throwable.addSuppressed:(Ljava/lang/Throwable;)V
       411: aload         9
       413: athrow
       414: aload_2
       415: invokevirtual #947                // Method ghidra/app/plugin/core/osgi/GhidraSourceBundle$Summary.getValue:()Ljava/lang/String;
       418: astore        8
       420: aload         4
       422: ifnull        430
       425: aload         4
       427: invokevirtual #1099               // Method org/phidias/compile/BundleJavaManager.close:()V
       430: aload         8
       432: areturn
       433: aload_0
       434: aload_1
       435: aload_2
       436: aload         6
       438: invokevirtual #1151               // Method generateManifest:(Ljava/io/PrintWriter;Lghidra/app/plugin/core/osgi/GhidraSourceBundle$Summary;Ljava/nio/file/Path;)Ljava/lang/String;
       441: astore        8
       443: aload         4
       445: ifnull        453
       448: aload         4
       450: invokevirtual #1099               // Method org/phidias/compile/BundleJavaManager.close:()V
       453: aload         8
       455: areturn
       456: astore        5
       458: aload         4
       460: ifnull        480
       463: aload         4
       465: invokevirtual #1099               // Method org/phidias/compile/BundleJavaManager.close:()V
       468: goto          480
       471: astore        6
       473: aload         5
       475: aload         6
       477: invokevirtual #367                // Method java/lang/Throwable.addSuppressed:(Ljava/lang/Throwable;)V
       480: aload         5
       482: athrow
      Exception table:
         from    to  target type
           356   374   387   Class java/lang/Throwable
           394   399   402   Class java/lang/Throwable
           189   420   456   Class java/lang/Throwable
           433   443   456   Class java/lang/Throwable
           463   468   471   Class java/lang/Throwable

  private static ghidra.app.script.ResourceFileJavaFileObject lambda$compileToExplodedBundle$10(generic.jar.ResourceFile);
    Code:
         0: new           #867                // class ghidra/app/script/ResourceFileJavaFileObject
         3: dup
         4: aload_0
         5: invokevirtual #704                // Method generic/jar/ResourceFile.getParentFile:()Lgeneric/jar/ResourceFile;
         8: aload_0
         9: getstatic     #1155               // Field javax/tools/JavaFileObject$Kind.SOURCE:Ljavax/tools/JavaFileObject$Kind;
        12: invokespecial #1161               // Method ghidra/app/script/ResourceFileJavaFileObject."<init>":(Lgeneric/jar/ResourceFile;Lgeneric/jar/ResourceFile;Ljavax/tools/JavaFileObject$Kind;)V
        15: areturn

  private static java.util.stream.Stream lambda$writeErrorUnresolved$9(org.osgi.framework.wiring.BundleRequirement);
    Code:
         0: aload_0
         1: invokeinterface #1164,  1         // InterfaceMethod org/osgi/framework/wiring/BundleRequirement.toString:()Ljava/lang/String;
         6: invokestatic  #811                // Method ghidra/app/plugin/core/osgi/OSGiUtils.extractPackageNamesFromFailedResolution:(Ljava/lang/String;)Ljava/util/List;
         9: invokeinterface #465,  1          // InterfaceMethod java/util/List.stream:()Ljava/util/stream/Stream;
        14: areturn

  private static boolean lambda$correspondingBinaries$8(java.lang.String, generic.jar.ResourceFile);
    Code:
         0: aload_1
         1: invokevirtual #237                // Method generic/jar/ResourceFile.getName:()Ljava/lang/String;
         4: astore_2
         5: aload_2
         6: aload_0
         7: invokevirtual #707                // Method java/lang/String.startsWith:(Ljava/lang/String;)Z
        10: ifeq          36
        13: getstatic     #1165               // Field IS_CLASS_FILE:Ljava/util/function/Predicate;
        16: aload_2
        17: aload_0
        18: invokevirtual #144                // Method java/lang/String.length:()I
        21: invokevirtual #419                // Method java/lang/String.substring:(I)Ljava/lang/String;
        24: invokeinterface #1169,  2         // InterfaceMethod java/util/function/Predicate.test:(Ljava/lang/Object;)Z
        29: ifeq          36
        32: iconst_1
        33: goto          37
        36: iconst_0
        37: ireturn

  private static java.nio.file.Path lambda$addSourcesThatNowHaveMissingRequirements$7(generic.jar.ResourceFile);
    Code:
         0: aload_0
         1: iconst_0
         2: invokevirtual #1173               // Method generic/jar/ResourceFile.getFile:(Z)Ljava/io/File;
         5: invokevirtual #1176               // Method java/io/File.toPath:()Ljava/nio/file/Path;
         8: areturn

  private static boolean lambda$deleteOldBinaries$6(java.nio.file.Path);
    Code:
         0: aload_0
         1: iconst_0
         2: anewarray     #518                // class java/nio/file/LinkOption
         5: invokestatic  #529                // Method java/nio/file/Files.exists:(Ljava/nio/file/Path;[Ljava/nio/file/LinkOption;)Z
         8: ireturn

  private void lambda$updateFromFilesystem$5(generic.jar.ResourceFile, java.util.Collection) throws java.lang.Throwable;
    Code:
         0: aload_1
         1: ifnull        15
         4: aload_0
         5: getfield      #12                 // Field newSources:Ljava/util/List;
         8: aload_1
         9: invokeinterface #309,  2          // InterfaceMethod java/util/List.add:(Ljava/lang/Object;)Z
        14: pop
        15: aload_2
        16: ifnull        30
        19: aload_0
        20: getfield      #18                 // Field oldBinaries:Ljava/util/List;
        23: aload_2
        24: invokeinterface #1179,  2         // InterfaceMethod java/util/List.addAll:(Ljava/util/Collection;)Z
        29: pop
        30: return

  private static boolean lambda$findPackageDirs$4(generic.jar.ResourceFile);
    Code:
         0: aload_0
         1: invokevirtual #406                // Method generic/jar/ResourceFile.isDirectory:()Z
         4: ifne          19
         7: aload_0
         8: invokevirtual #237                // Method generic/jar/ResourceFile.getName:()Ljava/lang/String;
        11: ldc           #240                // String .java
        13: invokevirtual #242                // Method java/lang/String.endsWith:(Ljava/lang/String;)Z
        16: ifeq          23
        19: iconst_1
        20: goto          24
        23: iconst_0
        24: ireturn

  private static java.lang.Object lambda$createSourceManifestParser$3(java.util.Map$Entry);
    Code:
         0: aload_0
         1: invokeinterface #589,  1          // InterfaceMethod java/util/Map$Entry.getValue:()Ljava/lang/Object;
         6: invokevirtual #1180               // Method java/lang/Object.toString:()Ljava/lang/String;
         9: areturn

  private static java.lang.String lambda$createSourceManifestParser$2(java.util.Map$Entry);
    Code:
         0: aload_0
         1: invokeinterface #586,  1          // InterfaceMethod java/util/Map$Entry.getKey:()Ljava/lang/Object;
         6: invokevirtual #1180               // Method java/lang/Object.toString:()Ljava/lang/String;
         9: areturn

  private static void lambda$getComputedReqs$1(java.util.Map, org.osgi.framework.wiring.BundleRequirement);
    Code:
         0: aload_0
         1: aload_1
         2: invokeinterface #1181,  1         // InterfaceMethod org/osgi/framework/wiring/BundleRequirement.toString:()Ljava/lang/String;
         7: aload_1
         8: invokeinterface #1182,  3         // InterfaceMethod java/util/Map.putIfAbsent:(Ljava/lang/Object;Ljava/lang/Object;)Ljava/lang/Object;
        13: pop
        14: return

  private static java.util.List lambda$updateRequirementsFromMetadata$0(java.lang.String);
    Code:
         0: new           #7                  // class java/util/ArrayList
         3: dup
         4: invokespecial #9                  // Method java/util/ArrayList."<init>":()V
         7: areturn

  static {};
    Code:
         0: ldc_w         #1185               // String (\\$.*)?\\.class
         3: iconst_2
         4: invokestatic  #1189               // Method java/util/regex/Pattern.compile:(Ljava/lang/String;I)Ljava/util/regex/Pattern;
         7: invokevirtual #1193               // Method java/util/regex/Pattern.asMatchPredicate:()Ljava/util/function/Predicate;
        10: putstatic     #1165               // Field IS_CLASS_FILE:Ljava/util/function/Predicate;
        13: return
}
