Compiled from "HeadlessAnalyzer.java"
public class ghidra.app.util.headless.HeadlessAnalyzer {
  private static ghidra.app.util.headless.HeadlessAnalyzer instance;

  private ghidra.app.util.headless.HeadlessOptions options;

  private ghidra.app.util.headless.HeadlessAnalyzer$HeadlessGhidraProjectManager projectManager;

  private ghidra.framework.model.Project project;

  private boolean analysisTimedOut;

  private ghidra.framework.model.DomainFolder saveDomainFolder;

  private java.util.Map<java.lang.String, java.lang.Object> storage;

  private java.net.URLClassLoader classLoaderForDotClassScripts;

  private ghidra.formats.gfilesystem.FileSystemService fsService;

  public static ghidra.app.util.headless.HeadlessAnalyzer getLoggableInstance(java.io.File, java.io.File, boolean) throws java.lang.IllegalStateException, java.io.IOException;
    Code:
         0: getstatic     #1                  // Field instance:Lghidra/app/util/headless/HeadlessAnalyzer;
         3: ifnull        16
         6: new           #7                  // class java/lang/IllegalStateException
         9: dup
        10: ldc           #9                  // String A headless analzyer instance has already been retrieved.  Use HeadlessAnalyzer.getInstance() to get it.
        12: invokespecial #11                 // Method java/lang/IllegalStateException."<init>":(Ljava/lang/String;)V
        15: athrow
        16: invokestatic  #15                 // Method ghidra/framework/Application.isInitialized:()Z
        19: ifeq          32
        22: new           #7                  // class java/lang/IllegalStateException
        25: dup
        26: ldc           #21                 // String Logging cannot be set because the application has already been initialized.  Use HeadlessAnalyzer.getInstance() to get the headless analyzer.
        28: invokespecial #11                 // Method java/lang/IllegalStateException."<init>":(Ljava/lang/String;)V
        31: athrow
        32: new           #23                 // class ghidra/framework/HeadlessGhidraApplicationConfiguration
        35: dup
        36: invokespecial #25                 // Method ghidra/framework/HeadlessGhidraApplicationConfiguration."<init>":()V
        39: astore_3
        40: iload_2
        41: ifeq          65
        44: aload_0
        45: ifnull        53
        48: aload_3
        49: aload_0
        50: invokevirtual #28                 // Method ghidra/framework/ApplicationConfiguration.setApplicationLogFile:(Ljava/io/File;)V
        53: aload_1
        54: ifnull        81
        57: aload_3
        58: aload_1
        59: invokevirtual #34                 // Method ghidra/framework/ApplicationConfiguration.setScriptLogFile:(Ljava/io/File;)V
        62: goto          81
        65: aload_3
        66: iconst_0
        67: invokevirtual #37                 // Method ghidra/framework/ApplicationConfiguration.setInitializeLogging:(Z)V
        70: new           #41                 // class ghidra/app/util/headless/HeadlessErrorLogger
        73: dup
        74: aload_0
        75: invokespecial #43                 // Method ghidra/app/util/headless/HeadlessErrorLogger."<init>":(Ljava/io/File;)V
        78: invokestatic  #45                 // Method ghidra/util/Msg.setErrorLogger:(Lghidra/util/ErrorLogger;)V
        81: invokestatic  #51                 // Method getApplicationLayout:()Lghidra/GhidraApplicationLayout;
        84: aload_3
        85: invokestatic  #55                 // Method ghidra/framework/Application.initializeApplication:(Lutility/application/ApplicationLayout;Lghidra/framework/ApplicationConfiguration;)V
        88: new           #2                  // class ghidra/app/util/headless/HeadlessAnalyzer
        91: dup
        92: invokespecial #59                 // Method "<init>":()V
        95: putstatic     #1                  // Field instance:Lghidra/app/util/headless/HeadlessAnalyzer;
        98: getstatic     #1                  // Field instance:Lghidra/app/util/headless/HeadlessAnalyzer;
       101: areturn

  public static ghidra.app.util.headless.HeadlessAnalyzer getInstance() throws java.io.IOException;
    Code:
         0: getstatic     #1                  // Field instance:Lghidra/app/util/headless/HeadlessAnalyzer;
         3: ifnull        10
         6: getstatic     #1                  // Field instance:Lghidra/app/util/headless/HeadlessAnalyzer;
         9: areturn
        10: invokestatic  #15                 // Method ghidra/framework/Application.isInitialized:()Z
        13: ifne          47
        16: new           #23                 // class ghidra/framework/HeadlessGhidraApplicationConfiguration
        19: dup
        20: invokespecial #25                 // Method ghidra/framework/HeadlessGhidraApplicationConfiguration."<init>":()V
        23: astore_0
        24: aload_0
        25: iconst_0
        26: invokevirtual #37                 // Method ghidra/framework/ApplicationConfiguration.setInitializeLogging:(Z)V
        29: new           #41                 // class ghidra/app/util/headless/HeadlessErrorLogger
        32: dup
        33: aconst_null
        34: invokespecial #43                 // Method ghidra/app/util/headless/HeadlessErrorLogger."<init>":(Ljava/io/File;)V
        37: invokestatic  #45                 // Method ghidra/util/Msg.setErrorLogger:(Lghidra/util/ErrorLogger;)V
        40: invokestatic  #51                 // Method getApplicationLayout:()Lghidra/GhidraApplicationLayout;
        43: aload_0
        44: invokestatic  #55                 // Method ghidra/framework/Application.initializeApplication:(Lutility/application/ApplicationLayout;Lghidra/framework/ApplicationConfiguration;)V
        47: new           #2                  // class ghidra/app/util/headless/HeadlessAnalyzer
        50: dup
        51: invokespecial #59                 // Method "<init>":()V
        54: putstatic     #1                  // Field instance:Lghidra/app/util/headless/HeadlessAnalyzer;
        57: getstatic     #1                  // Field instance:Lghidra/app/util/headless/HeadlessAnalyzer;
        60: areturn

  private static ghidra.GhidraApplicationLayout getApplicationLayout() throws java.io.IOException;
    Code:
         0: new           #60                 // class ghidra/GhidraApplicationLayout
         3: dup
         4: invokespecial #62                 // Method ghidra/GhidraApplicationLayout."<init>":()V
         7: astore_0
         8: goto          34
        11: astore_1
        12: ldc           #2                  // class ghidra/app/util/headless/HeadlessAnalyzer
        14: aload_1
        15: invokevirtual #65                 // Method java/io/IOException.getMessage:()Ljava/lang/String;
        18: invokedynamic #69,  0             // InvokeDynamic #0:makeConcatWithConstants:(Ljava/lang/String;)Ljava/lang/String;
        23: invokestatic  #73                 // Method ghidra/util/Msg.debug:(Ljava/lang/Object;Ljava/lang/Object;)V
        26: new           #77                 // class ghidra/GhidraJarApplicationLayout
        29: dup
        30: invokespecial #79                 // Method ghidra/GhidraJarApplicationLayout."<init>":()V
        33: astore_0
        34: aload_0
        35: areturn
      Exception table:
         from    to  target type
             0     8    11   Class java/io/IOException

  private ghidra.app.util.headless.HeadlessAnalyzer();
    Code:
         0: aload_0
         1: invokespecial #80                 // Method java/lang/Object."<init>":()V
         4: aload_0
         5: new           #83                 // class ghidra/app/util/headless/HeadlessOptions
         8: dup
         9: invokespecial #85                 // Method ghidra/app/util/headless/HeadlessOptions."<init>":()V
        12: putfield      #86                 // Field options:Lghidra/app/util/headless/HeadlessOptions;
        15: invokestatic  #90                 // Method ghidra/framework/protocol/ghidra/Handler.registerHandler:()V
        18: ldc           #95                 // String java.awt.headless
        20: ldc           #97                 // String true
        22: invokestatic  #99                 // Method java/lang/System.setProperty:(Ljava/lang/String;Ljava/lang/String;)Ljava/lang/String;
        25: pop
        26: ldc           #107                // String SystemUtilities.isHeadless
        28: getstatic     #109                // Field java/lang/Boolean.TRUE:Ljava/lang/Boolean;
        31: invokevirtual #115                // Method java/lang/Boolean.toString:()Ljava/lang/String;
        34: invokestatic  #99                 // Method java/lang/System.setProperty:(Ljava/lang/String;Ljava/lang/String;)Ljava/lang/String;
        37: pop
        38: aload_0
        39: invokevirtual #118                // Method reset:()V
        42: aload_0
        43: invokestatic  #121                // Method ghidra/formats/gfilesystem/FileSystemService.getInstance:()Lghidra/formats/gfilesystem/FileSystemService;
        46: putfield      #127                // Field fsService:Lghidra/formats/gfilesystem/FileSystemService;
        49: return

  public void reset();
    Code:
         0: aload_0
         1: getfield      #86                 // Field options:Lghidra/app/util/headless/HeadlessOptions;
         4: invokevirtual #131                // Method ghidra/app/util/headless/HeadlessOptions.reset:()V
         7: aload_0
         8: aconst_null
         9: putfield      #132                // Field project:Lghidra/framework/model/Project;
        12: aload_0
        13: iconst_0
        14: putfield      #136                // Field analysisTimedOut:Z
        17: aload_0
        18: aconst_null
        19: putfield      #140                // Field saveDomainFolder:Lghidra/framework/model/DomainFolder;
        22: aload_0
        23: new           #144                // class java/util/HashMap
        26: dup
        27: invokespecial #146                // Method java/util/HashMap."<init>":()V
        30: putfield      #147                // Field storage:Ljava/util/Map;
        33: aload_0
        34: aconst_null
        35: putfield      #151                // Field classLoaderForDotClassScripts:Ljava/net/URLClassLoader;
        38: return

  public ghidra.app.util.headless.HeadlessOptions getOptions();
    Code:
         0: aload_0
         1: getfield      #86                 // Field options:Lghidra/app/util/headless/HeadlessOptions;
         4: areturn

  public void processURL(java.net.URL, java.util.List<java.io.File>) throws java.io.IOException, java.net.MalformedURLException, java.net.URISyntaxException;
    Code:
         0: aload_0
         1: getfield      #86                 // Field options:Lghidra/app/util/headless/HeadlessOptions;
         4: getfield      #155                // Field ghidra/app/util/headless/HeadlessOptions.readOnly:Z
         7: ifeq          27
        10: aload_0
        11: getfield      #86                 // Field options:Lghidra/app/util/headless/HeadlessOptions;
        14: getfield      #158                // Field ghidra/app/util/headless/HeadlessOptions.commit:Z
        17: ifeq          27
        20: aload_0
        21: ldc           #161                // String Abort due to Headless analyzer error: The requested readOnly option is in conflict with the commit option
        23: invokestatic  #163                // Method ghidra/util/Msg.error:(Ljava/lang/Object;Ljava/lang/Object;)V
        26: return
        27: ldc           #166                // String ghidra
        29: aload_1
        30: invokevirtual #168                // Method java/net/URL.getProtocol:()Ljava/lang/String;
        33: invokevirtual #173                // Method java/lang/String.equals:(Ljava/lang/Object;)Z
        36: ifne          56
        39: new           #179                // class java/net/MalformedURLException
        42: dup
        43: aload_1
        44: invokestatic  #181                // Method java/lang/String.valueOf:(Ljava/lang/Object;)Ljava/lang/String;
        47: invokedynamic #185,  0            // InvokeDynamic #1:makeConcatWithConstants:(Ljava/lang/String;)Ljava/lang/String;
        52: invokespecial #186                // Method java/net/MalformedURLException."<init>":(Ljava/lang/String;)V
        55: athrow
        56: aload_1
        57: invokestatic  #187                // Method ghidra/framework/protocol/ghidra/GhidraURL.isLocalURL:(Ljava/net/URL;)Z
        60: ifeq          70
        63: aload_0
        64: ldc           #193                // String Ghidra URL command form does not supported local project URLs (ghidra:/path...)
        66: invokestatic  #163                // Method ghidra/util/Msg.error:(Ljava/lang/Object;Ljava/lang/Object;)V
        69: return
        70: aload_1
        71: invokevirtual #195                // Method java/net/URL.getPath:()Ljava/lang/String;
        74: astore_3
        75: aload_3
        76: ifnonnull     96
        79: new           #179                // class java/net/MalformedURLException
        82: dup
        83: aload_1
        84: invokestatic  #181                // Method java/lang/String.valueOf:(Ljava/lang/Object;)Ljava/lang/String;
        87: invokedynamic #185,  0            // InvokeDynamic #1:makeConcatWithConstants:(Ljava/lang/String;)Ljava/lang/String;
        92: invokespecial #186                // Method java/net/MalformedURLException."<init>":(Ljava/lang/String;)V
        95: athrow
        96: aload_3
        97: invokevirtual #198                // Method java/lang/String.trim:()Ljava/lang/String;
       100: astore_3
       101: aload_3
       102: invokevirtual #201                // Method java/lang/String.length:()I
       105: ifne          125
       108: new           #179                // class java/net/MalformedURLException
       111: dup
       112: aload_1
       113: invokestatic  #181                // Method java/lang/String.valueOf:(Ljava/lang/Object;)Ljava/lang/String;
       116: invokedynamic #185,  0            // InvokeDynamic #1:makeConcatWithConstants:(Ljava/lang/String;)Ljava/lang/String;
       121: invokespecial #186                // Method java/net/MalformedURLException."<init>":(Ljava/lang/String;)V
       124: athrow
       125: aload_0
       126: getfield      #86                 // Field options:Lghidra/app/util/headless/HeadlessOptions;
       129: getfield      #205                // Field ghidra/app/util/headless/HeadlessOptions.runScriptsNoImport:Z
       132: ifne          227
       135: aload_2
       136: ifnull        148
       139: aload_2
       140: invokeinterface #208,  1          // InterfaceMethod java/util/List.size:()I
       145: ifne          185
       148: aload_0
       149: getfield      #86                 // Field options:Lghidra/app/util/headless/HeadlessOptions;
       152: getfield      #213                // Field ghidra/app/util/headless/HeadlessOptions.preScripts:Ljava/util/List;
       155: invokeinterface #217,  1          // InterfaceMethod java/util/List.isEmpty:()Z
       160: ifeq          185
       163: aload_0
       164: getfield      #86                 // Field options:Lghidra/app/util/headless/HeadlessOptions;
       167: getfield      #220                // Field ghidra/app/util/headless/HeadlessOptions.postScripts:Ljava/util/List;
       170: invokeinterface #217,  1          // InterfaceMethod java/util/List.isEmpty:()Z
       175: ifeq          185
       178: aload_0
       179: ldc           #223                // String REPORT: Nothing to do ... must specify files for import.
       181: invokestatic  #225                // Method ghidra/util/Msg.warn:(Ljava/lang/Object;Ljava/lang/Object;)V
       184: return
       185: aload_3
       186: ldc           #228                // String /
       188: invokevirtual #230                // Method java/lang/String.endsWith:(Ljava/lang/String;)Z
       191: ifne          279
       194: new           #234                // class java/net/URI
       197: dup
       198: ldc           #166                // String ghidra
       200: aconst_null
       201: aload_1
       202: invokevirtual #236                // Method java/net/URL.getHost:()Ljava/lang/String;
       205: aload_1
       206: invokevirtual #239                // Method java/net/URL.getPort:()I
       209: aload_3
       210: invokedynamic #242,  0            // InvokeDynamic #2:makeConcatWithConstants:(Ljava/lang/String;)Ljava/lang/String;
       215: aconst_null
       216: aconst_null
       217: invokespecial #243                // Method java/net/URI."<init>":(Ljava/lang/String;Ljava/lang/String;Ljava/lang/String;ILjava/lang/String;Ljava/lang/String;Ljava/lang/String;)V
       220: invokevirtual #246                // Method java/net/URI.toURL:()Ljava/net/URL;
       223: astore_1
       224: goto          279
       227: aload_3
       228: ldc           #228                // String /
       230: invokevirtual #230                // Method java/lang/String.endsWith:(Ljava/lang/String;)Z
       233: ifeq          279
       236: aload_3
       237: invokevirtual #201                // Method java/lang/String.length:()I
       240: iconst_1
       241: if_icmple     279
       244: new           #234                // class java/net/URI
       247: dup
       248: ldc           #166                // String ghidra
       250: aconst_null
       251: aload_1
       252: invokevirtual #236                // Method java/net/URL.getHost:()Ljava/lang/String;
       255: aload_1
       256: invokevirtual #239                // Method java/net/URL.getPort:()I
       259: aload_3
       260: iconst_0
       261: aload_3
       262: invokevirtual #201                // Method java/lang/String.length:()I
       265: iconst_1
       266: isub
       267: invokevirtual #250                // Method java/lang/String.substring:(II)Ljava/lang/String;
       270: aconst_null
       271: aconst_null
       272: invokespecial #243                // Method java/net/URI."<init>":(Ljava/lang/String;Ljava/lang/String;Ljava/lang/String;ILjava/lang/String;Ljava/lang/String;Ljava/lang/String;)V
       275: invokevirtual #246                // Method java/net/URI.toURL:()Ljava/net/URL;
       278: astore_1
       279: invokestatic  #254                // Method ghidra/app/script/GhidraScriptUtil.acquireBundleHostReference:()Lghidra/app/plugin/core/osgi/BundleHost;
       282: astore        4
       284: aload         4
       286: aload_0
       287: aload_0
       288: getfield      #86                 // Field options:Lghidra/app/util/headless/HeadlessOptions;
       291: getfield      #260                // Field ghidra/app/util/headless/HeadlessOptions.scriptPaths:Ljava/util/List;
       294: invokevirtual #263                // Method parseScriptPaths:(Ljava/util/List;)Ljava/util/List;
       297: iconst_1
       298: iconst_1
       299: invokevirtual #267                // Method ghidra/app/plugin/core/osgi/BundleHost.add:(Ljava/util/List;ZZ)Ljava/util/Collection;
       302: pop
       303: aload_0
       304: invokevirtual #273                // Method showConfiguredScriptPaths:()V
       307: aload_0
       308: invokevirtual #276                // Method compileScripts:()V
       311: ldc           #2                  // class ghidra/app/util/headless/HeadlessAnalyzer
       313: ldc_w         #279                // String HEADLESS: execution starts
       316: invokestatic  #281                // Method ghidra/util/Msg.info:(Ljava/lang/Object;Ljava/lang/Object;)V
       319: aload_1
       320: invokestatic  #284                // Method ghidra/framework/protocol/ghidra/GhidraURL.getFolderURL:(Ljava/net/URL;)Ljava/net/URL;
       323: astore_1
       324: aload_0
       325: aload_1
       326: invokestatic  #181                // Method java/lang/String.valueOf:(Ljava/lang/Object;)Ljava/lang/String;
       329: invokedynamic #288,  0            // InvokeDynamic #3:makeConcatWithConstants:(Ljava/lang/String;)Ljava/lang/String;
       334: invokestatic  #281                // Method ghidra/util/Msg.info:(Ljava/lang/Object;Ljava/lang/Object;)V
       337: aload_1
       338: aload_0
       339: getfield      #86                 // Field options:Lghidra/app/util/headless/HeadlessOptions;
       342: getfield      #155                // Field ghidra/app/util/headless/HeadlessOptions.readOnly:Z
       345: new           #289                // class ghidra/app/util/headless/HeadlessAnalyzer$1
       348: dup
       349: aload_0
       350: aload_2
       351: invokespecial #291                // Method ghidra/app/util/headless/HeadlessAnalyzer$1."<init>":(Lghidra/app/util/headless/HeadlessAnalyzer;Ljava/util/List;)V
       354: getstatic     #294                // Field ghidra/framework/protocol/ghidra/GhidraURLQuery$LinkFileControl.NO_FOLLOW:Lghidra/framework/protocol/ghidra/GhidraURLQuery$LinkFileControl;
       357: getstatic     #300                // Field ghidra/util/task/TaskMonitor.DUMMY:Lghidra/util/task/TaskMonitor;
       360: invokestatic  #306                // Method ghidra/framework/protocol/ghidra/GhidraURLQuery.queryRepositoryUrl:(Ljava/net/URL;ZLghidra/framework/protocol/ghidra/GhidraURLResultHandler;Lghidra/framework/protocol/ghidra/GhidraURLQuery$LinkFileControl;Lghidra/util/task/TaskMonitor;)V
       363: invokestatic  #312                // Method ghidra/app/script/GhidraScriptUtil.releaseBundleHostReference:()V
       366: goto          389
       369: astore        5
       371: new           #63                 // class java/io/IOException
       374: dup
       375: aload         5
       377: invokespecial #317                // Method java/io/IOException."<init>":(Ljava/lang/Throwable;)V
       380: athrow
       381: astore        6
       383: invokestatic  #312                // Method ghidra/app/script/GhidraScriptUtil.releaseBundleHostReference:()V
       386: aload         6
       388: athrow
       389: return
      Exception table:
         from    to  target type
           303   363   369   Class ghidra/util/exception/CancelledException
           303   363   381   any
           369   383   381   any

  public void processLocal(java.lang.String, java.lang.String, java.lang.String, java.util.List<java.io.File>) throws java.io.IOException;
    Code:
         0: aload_0
         1: getfield      #86                 // Field options:Lghidra/app/util/headless/HeadlessOptions;
         4: getfield      #155                // Field ghidra/app/util/headless/HeadlessOptions.readOnly:Z
         7: ifeq          27
        10: aload_0
        11: getfield      #86                 // Field options:Lghidra/app/util/headless/HeadlessOptions;
        14: getfield      #158                // Field ghidra/app/util/headless/HeadlessOptions.commit:Z
        17: ifeq          27
        20: aload_0
        21: ldc           #161                // String Abort due to Headless analyzer error: The requested readOnly option is in conflict with the commit option
        23: invokestatic  #163                // Method ghidra/util/Msg.error:(Ljava/lang/Object;Ljava/lang/Object;)V
        26: return
        27: aload_0
        28: getfield      #86                 // Field options:Lghidra/app/util/headless/HeadlessOptions;
        31: getfield      #205                // Field ghidra/app/util/headless/HeadlessOptions.runScriptsNoImport:Z
        34: ifeq          69
        37: aload_3
        38: ldc           #228                // String /
        40: invokevirtual #230                // Method java/lang/String.endsWith:(Ljava/lang/String;)Z
        43: ifeq          138
        46: aload_3
        47: invokevirtual #201                // Method java/lang/String.length:()I
        50: iconst_1
        51: if_icmple     138
        54: aload_3
        55: iconst_0
        56: aload_3
        57: invokevirtual #201                // Method java/lang/String.length:()I
        60: iconst_1
        61: isub
        62: invokevirtual #250                // Method java/lang/String.substring:(II)Ljava/lang/String;
        65: astore_3
        66: goto          138
        69: aload         4
        71: ifnull        84
        74: aload         4
        76: invokeinterface #208,  1          // InterfaceMethod java/util/List.size:()I
        81: ifne          122
        84: aload_0
        85: getfield      #86                 // Field options:Lghidra/app/util/headless/HeadlessOptions;
        88: getfield      #213                // Field ghidra/app/util/headless/HeadlessOptions.preScripts:Ljava/util/List;
        91: invokeinterface #217,  1          // InterfaceMethod java/util/List.isEmpty:()Z
        96: ifeq          122
        99: aload_0
       100: getfield      #86                 // Field options:Lghidra/app/util/headless/HeadlessOptions;
       103: getfield      #220                // Field ghidra/app/util/headless/HeadlessOptions.postScripts:Ljava/util/List;
       106: invokeinterface #217,  1          // InterfaceMethod java/util/List.isEmpty:()Z
       111: ifeq          122
       114: aload_0
       115: ldc_w         #320                // String REPORT: Nothing to do ... must specify file(s) for import.
       118: invokestatic  #225                // Method ghidra/util/Msg.warn:(Ljava/lang/Object;Ljava/lang/Object;)V
       121: return
       122: aload_3
       123: ldc           #228                // String /
       125: invokevirtual #230                // Method java/lang/String.endsWith:(Ljava/lang/String;)Z
       128: ifne          138
       131: aload_3
       132: invokedynamic #242,  0            // InvokeDynamic #2:makeConcatWithConstants:(Ljava/lang/String;)Ljava/lang/String;
       137: astore_3
       138: invokestatic  #254                // Method ghidra/app/script/GhidraScriptUtil.acquireBundleHostReference:()Lghidra/app/plugin/core/osgi/BundleHost;
       141: astore        5
       143: aload         5
       145: aload_0
       146: aload_0
       147: getfield      #86                 // Field options:Lghidra/app/util/headless/HeadlessOptions;
       150: getfield      #260                // Field ghidra/app/util/headless/HeadlessOptions.scriptPaths:Ljava/util/List;
       153: invokevirtual #263                // Method parseScriptPaths:(Ljava/util/List;)Ljava/util/List;
       156: iconst_1
       157: iconst_1
       158: invokevirtual #267                // Method ghidra/app/plugin/core/osgi/BundleHost.add:(Ljava/util/List;ZZ)Ljava/util/Collection;
       161: pop
       162: aload_0
       163: invokevirtual #273                // Method showConfiguredScriptPaths:()V
       166: aload_0
       167: invokevirtual #276                // Method compileScripts:()V
       170: ldc           #2                  // class ghidra/app/util/headless/HeadlessAnalyzer
       172: ldc_w         #279                // String HEADLESS: execution starts
       175: invokestatic  #281                // Method ghidra/util/Msg.info:(Ljava/lang/Object;Ljava/lang/Object;)V
       178: new           #322                // class java/io/File
       181: dup
       182: aload_1
       183: invokespecial #324                // Method java/io/File."<init>":(Ljava/lang/String;)V
       186: astore        6
       188: new           #325                // class ghidra/framework/model/ProjectLocator
       191: dup
       192: aload         6
       194: invokevirtual #327                // Method java/io/File.getAbsolutePath:()Ljava/lang/String;
       197: aload_2
       198: invokespecial #330                // Method ghidra/framework/model/ProjectLocator."<init>":(Ljava/lang/String;Ljava/lang/String;)V
       201: astore        7
       203: aload         7
       205: invokevirtual #333                // Method ghidra/framework/model/ProjectLocator.getProjectDir:()Ljava/io/File;
       208: invokevirtual #337                // Method java/io/File.exists:()Z
       211: ifeq          227
       214: aload_0
       215: aload_0
       216: aload         7
       218: invokevirtual #340                // Method openProject:(Lghidra/framework/model/ProjectLocator;)Lghidra/framework/model/Project;
       221: putfield      #132                // Field project:Lghidra/framework/model/Project;
       224: goto          345
       227: aload_0
       228: getfield      #86                 // Field options:Lghidra/app/util/headless/HeadlessOptions;
       231: getfield      #205                // Field ghidra/app/util/headless/HeadlessOptions.runScriptsNoImport:Z
       234: ifeq          269
       237: aload_0
       238: aload         7
       240: invokestatic  #181                // Method java/lang/String.valueOf:(Ljava/lang/Object;)Ljava/lang/String;
       243: invokedynamic #344,  0            // InvokeDynamic #4:makeConcatWithConstants:(Ljava/lang/String;)Ljava/lang/String;
       248: invokestatic  #163                // Method ghidra/util/Msg.error:(Ljava/lang/Object;Ljava/lang/Object;)V
       251: new           #63                 // class java/io/IOException
       254: dup
       255: aload         7
       257: invokestatic  #181                // Method java/lang/String.valueOf:(Ljava/lang/Object;)Ljava/lang/String;
       260: invokedynamic #345,  0            // InvokeDynamic #5:makeConcatWithConstants:(Ljava/lang/String;)Ljava/lang/String;
       265: invokespecial #346                // Method java/io/IOException."<init>":(Ljava/lang/String;)V
       268: athrow
       269: aload_0
       270: getfield      #86                 // Field options:Lghidra/app/util/headless/HeadlessOptions;
       273: getfield      #205                // Field ghidra/app/util/headless/HeadlessOptions.runScriptsNoImport:Z
       276: ifne          297
       279: aload_0
       280: getfield      #86                 // Field options:Lghidra/app/util/headless/HeadlessOptions;
       283: getfield      #155                // Field ghidra/app/util/headless/HeadlessOptions.readOnly:Z
       286: ifeq          297
       289: aload_0
       290: getfield      #86                 // Field options:Lghidra/app/util/headless/HeadlessOptions;
       293: iconst_1
       294: putfield      #347                // Field ghidra/app/util/headless/HeadlessOptions.deleteProject:Z
       297: aload_0
       298: aload_0
       299: getfield      #86                 // Field options:Lghidra/app/util/headless/HeadlessOptions;
       302: getfield      #347                // Field ghidra/app/util/headless/HeadlessOptions.deleteProject:Z
       305: ifeq          314
       308: ldc_w         #350                // String temporary
       311: goto          317
       314: ldc_w         #352                // String
       317: aload         7
       319: invokestatic  #181                // Method java/lang/String.valueOf:(Ljava/lang/Object;)Ljava/lang/String;
       322: invokedynamic #354,  0            // InvokeDynamic #6:makeConcatWithConstants:(Ljava/lang/String;Ljava/lang/String;)Ljava/lang/String;
       327: invokestatic  #281                // Method ghidra/util/Msg.info:(Ljava/lang/Object;Ljava/lang/Object;)V
       330: aload_0
       331: aload_0
       332: invokevirtual #356                // Method getProjectManager:()Lghidra/app/util/headless/HeadlessAnalyzer$HeadlessGhidraProjectManager;
       335: aload         7
       337: aconst_null
       338: iconst_0
       339: invokevirtual #360                // Method ghidra/app/util/headless/HeadlessAnalyzer$HeadlessGhidraProjectManager.createProject:(Lghidra/framework/model/ProjectLocator;Lghidra/framework/client/RepositoryAdapter;Z)Lghidra/framework/model/Project;
       342: putfield      #132                // Field project:Lghidra/framework/model/Project;
       345: aload_0
       346: invokevirtual #366                // Method checkUpdateOptions:()Z
       349: ifne          403
       352: aload_0
       353: getfield      #132                // Field project:Lghidra/framework/model/Project;
       356: invokeinterface #369,  1          // InterfaceMethod ghidra/framework/model/Project.close:()V
       361: aload_0
       362: getfield      #86                 // Field options:Lghidra/app/util/headless/HeadlessOptions;
       365: getfield      #205                // Field ghidra/app/util/headless/HeadlessOptions.runScriptsNoImport:Z
       368: ifne          399
       371: aload_0
       372: getfield      #86                 // Field options:Lghidra/app/util/headless/HeadlessOptions;
       375: getfield      #347                // Field ghidra/app/util/headless/HeadlessOptions.deleteProject:Z
       378: ifeq          399
       381: aload         7
       383: invokevirtual #333                // Method ghidra/framework/model/ProjectLocator.getProjectDir:()Ljava/io/File;
       386: invokestatic  #374                // Method utilities/util/FileUtilities.deleteDir:(Ljava/io/File;)Z
       389: pop
       390: aload         7
       392: invokevirtual #380                // Method ghidra/framework/model/ProjectLocator.getMarkerFile:()Ljava/io/File;
       395: invokevirtual #383                // Method java/io/File.delete:()Z
       398: pop
       399: invokestatic  #312                // Method ghidra/app/script/GhidraScriptUtil.releaseBundleHostReference:()V
       402: return
       403: aload_0
       404: getfield      #86                 // Field options:Lghidra/app/util/headless/HeadlessOptions;
       407: getfield      #205                // Field ghidra/app/util/headless/HeadlessOptions.runScriptsNoImport:Z
       410: ifeq          421
       413: aload_0
       414: aload_3
       415: invokevirtual #386                // Method processNoImport:(Ljava/lang/String;)V
       418: goto          428
       421: aload_0
       422: aload_3
       423: aload         4
       425: invokevirtual #389                // Method processWithImport:(Ljava/lang/String;Ljava/util/List;)V
       428: aload_0
       429: getfield      #132                // Field project:Lghidra/framework/model/Project;
       432: invokeinterface #369,  1          // InterfaceMethod ghidra/framework/model/Project.close:()V
       437: aload_0
       438: getfield      #86                 // Field options:Lghidra/app/util/headless/HeadlessOptions;
       441: getfield      #205                // Field ghidra/app/util/headless/HeadlessOptions.runScriptsNoImport:Z
       444: ifne          530
       447: aload_0
       448: getfield      #86                 // Field options:Lghidra/app/util/headless/HeadlessOptions;
       451: getfield      #347                // Field ghidra/app/util/headless/HeadlessOptions.deleteProject:Z
       454: ifeq          530
       457: aload         7
       459: invokevirtual #333                // Method ghidra/framework/model/ProjectLocator.getProjectDir:()Ljava/io/File;
       462: invokestatic  #374                // Method utilities/util/FileUtilities.deleteDir:(Ljava/io/File;)Z
       465: pop
       466: aload         7
       468: invokevirtual #380                // Method ghidra/framework/model/ProjectLocator.getMarkerFile:()Ljava/io/File;
       471: invokevirtual #383                // Method java/io/File.delete:()Z
       474: pop
       475: goto          530
       478: astore        8
       480: aload_0
       481: getfield      #132                // Field project:Lghidra/framework/model/Project;
       484: invokeinterface #369,  1          // InterfaceMethod ghidra/framework/model/Project.close:()V
       489: aload_0
       490: getfield      #86                 // Field options:Lghidra/app/util/headless/HeadlessOptions;
       493: getfield      #205                // Field ghidra/app/util/headless/HeadlessOptions.runScriptsNoImport:Z
       496: ifne          527
       499: aload_0
       500: getfield      #86                 // Field options:Lghidra/app/util/headless/HeadlessOptions;
       503: getfield      #347                // Field ghidra/app/util/headless/HeadlessOptions.deleteProject:Z
       506: ifeq          527
       509: aload         7
       511: invokevirtual #333                // Method ghidra/framework/model/ProjectLocator.getProjectDir:()Ljava/io/File;
       514: invokestatic  #374                // Method utilities/util/FileUtilities.deleteDir:(Ljava/io/File;)Z
       517: pop
       518: aload         7
       520: invokevirtual #380                // Method ghidra/framework/model/ProjectLocator.getMarkerFile:()Ljava/io/File;
       523: invokevirtual #383                // Method java/io/File.delete:()Z
       526: pop
       527: aload         8
       529: athrow
       530: invokestatic  #312                // Method ghidra/app/script/GhidraScriptUtil.releaseBundleHostReference:()V
       533: goto          544
       536: astore        9
       538: invokestatic  #312                // Method ghidra/app/script/GhidraScriptUtil.releaseBundleHostReference:()V
       541: aload         9
       543: athrow
       544: return
      Exception table:
         from    to  target type
           345   352   478   any
           403   428   478   any
           478   480   478   any
           162   399   536   any
           403   530   536   any
           536   538   536   any

  public boolean checkAnalysisTimedOut();
    Code:
         0: aload_0
         1: getfield      #136                // Field analysisTimedOut:Z
         4: ireturn

  void setSaveFolder(ghidra.framework.model.DomainFolder);
    Code:
         0: aload_0
         1: aload_1
         2: putfield      #140                // Field saveDomainFolder:Lghidra/framework/model/DomainFolder;
         5: aload_1
         6: ifnull        24
         9: aload_0
        10: aload_1
        11: invokeinterface #393,  1          // InterfaceMethod ghidra/framework/model/DomainFolder.getPathname:()Ljava/lang/String;
        16: invokedynamic #398,  0            // InvokeDynamic #7:makeConcatWithConstants:(Ljava/lang/String;)Ljava/lang/String;
        21: invokestatic  #281                // Method ghidra/util/Msg.info:(Ljava/lang/Object;Ljava/lang/Object;)V
        24: return

  void addVariableToStorage(java.lang.String, java.lang.Object);
    Code:
         0: aload_0
         1: getfield      #147                // Field storage:Ljava/util/Map;
         4: aload_1
         5: invokeinterface #399,  2          // InterfaceMethod java/util/Map.containsKey:(Ljava/lang/Object;)Z
        10: ifeq          23
        13: aload_0
        14: aload_1
        15: invokedynamic #404,  0            // InvokeDynamic #8:makeConcatWithConstants:(Ljava/lang/String;)Ljava/lang/String;
        20: invokestatic  #225                // Method ghidra/util/Msg.warn:(Ljava/lang/Object;Ljava/lang/Object;)V
        23: aload_0
        24: getfield      #147                // Field storage:Ljava/util/Map;
        27: aload_1
        28: aload_2
        29: invokeinterface #405,  3          // InterfaceMethod java/util/Map.put:(Ljava/lang/Object;Ljava/lang/Object;)Ljava/lang/Object;
        34: pop
        35: return

  java.util.Set<java.lang.String> getStorageKeys();
    Code:
         0: aload_0
         1: getfield      #147                // Field storage:Ljava/util/Map;
         4: invokeinterface #409,  1          // InterfaceMethod java/util/Map.keySet:()Ljava/util/Set;
         9: areturn

  java.lang.Object getVariableFromStorage(java.lang.String);
    Code:
         0: aload_0
         1: getfield      #147                // Field storage:Ljava/util/Map;
         4: aload_1
         5: invokeinterface #399,  2          // InterfaceMethod java/util/Map.containsKey:(Ljava/lang/Object;)Z
        10: ifne          25
        13: aload_0
        14: aload_1
        15: invokedynamic #413,  0            // InvokeDynamic #9:makeConcatWithConstants:(Ljava/lang/String;)Ljava/lang/String;
        20: invokestatic  #225                // Method ghidra/util/Msg.warn:(Ljava/lang/Object;Ljava/lang/Object;)V
        23: aconst_null
        24: areturn
        25: aload_0
        26: getfield      #147                // Field storage:Ljava/util/Map;
        29: aload_1
        30: invokeinterface #414,  2          // InterfaceMethod java/util/Map.get:(Ljava/lang/Object;)Ljava/lang/Object;
        35: areturn

  ghidra.framework.model.DomainFolder getDomainFolder(java.lang.String, boolean) throws java.io.IOException, ghidra.util.InvalidNameException;
    Code:
         0: aload_0
         1: getfield      #132                // Field project:Lghidra/framework/model/Project;
         4: invokeinterface #418,  1          // InterfaceMethod ghidra/framework/model/Project.getProjectData:()Lghidra/framework/model/ProjectData;
         9: aload_1
        10: invokeinterface #422,  2          // InterfaceMethod ghidra/framework/model/ProjectData.getFolder:(Ljava/lang/String;)Lghidra/framework/model/DomainFolder;
        15: astore_3
        16: iload_2
        17: ifeq          204
        20: aload_3
        21: ifnonnull     204
        24: aload_1
        25: ldc_w         #428                // String ^/+
        28: ldc_w         #352                // String
        31: invokevirtual #430                // Method java/lang/String.replaceAll:(Ljava/lang/String;Ljava/lang/String;)Ljava/lang/String;
        34: astore        4
        36: aload         4
        38: ldc_w         #433                // String /+$
        41: ldc_w         #352                // String
        44: invokevirtual #430                // Method java/lang/String.replaceAll:(Ljava/lang/String;Ljava/lang/String;)Ljava/lang/String;
        47: astore        4
        49: aload         4
        51: ldc_w         #435                // String /+
        54: invokevirtual #437                // Method java/lang/String.split:(Ljava/lang/String;)[Ljava/lang/String;
        57: astore        5
        59: iconst_0
        60: istore        6
        62: aload         5
        64: iload         6
        66: aaload
        67: invokedynamic #441,  0            // InvokeDynamic #10:makeConcatWithConstants:(Ljava/lang/String;)Ljava/lang/String;
        72: astore        7
        74: aload_0
        75: getfield      #132                // Field project:Lghidra/framework/model/Project;
        78: invokeinterface #418,  1          // InterfaceMethod ghidra/framework/model/Project.getProjectData:()Lghidra/framework/model/ProjectData;
        83: aload         7
        85: invokeinterface #422,  2          // InterfaceMethod ghidra/framework/model/ProjectData.getFolder:(Ljava/lang/String;)Lghidra/framework/model/DomainFolder;
        90: astore        8
        92: aconst_null
        93: astore        9
        95: aload         8
        97: ifnull        134
       100: iload         6
       102: aload         5
       104: arraylength
       105: iconst_1
       106: isub
       107: if_icmpge     134
       110: iinc          6, 1
       113: aload         8
       115: astore        9
       117: aload         9
       119: aload         5
       121: iload         6
       123: aaload
       124: invokeinterface #442,  2          // InterfaceMethod ghidra/framework/model/DomainFolder.getFolder:(Ljava/lang/String;)Lghidra/framework/model/DomainFolder;
       129: astore        8
       131: goto          95
       134: iload         6
       136: ifne          155
       139: aload_0
       140: getfield      #132                // Field project:Lghidra/framework/model/Project;
       143: invokeinterface #418,  1          // InterfaceMethod ghidra/framework/model/Project.getProjectData:()Lghidra/framework/model/ProjectData;
       148: invokeinterface #443,  1          // InterfaceMethod ghidra/framework/model/ProjectData.getRootFolder:()Lghidra/framework/model/DomainFolder;
       153: astore        9
       155: iload         6
       157: istore        10
       159: iload         10
       161: aload         5
       163: arraylength
       164: if_icmpge     201
       167: aload         9
       169: aload         5
       171: iload         10
       173: aaload
       174: invokeinterface #447,  2          // InterfaceMethod ghidra/framework/model/DomainFolder.createFolder:(Ljava/lang/String;)Lghidra/framework/model/DomainFolder;
       179: astore        9
       181: aload_0
       182: aload         5
       184: iload         10
       186: aaload
       187: invokedynamic #450,  0            // InvokeDynamic #11:makeConcatWithConstants:(Ljava/lang/String;)Ljava/lang/String;
       192: invokestatic  #281                // Method ghidra/util/Msg.info:(Ljava/lang/Object;Ljava/lang/Object;)V
       195: iinc          10, 1
       198: goto          159
       201: aload         9
       203: astore_3
       204: aload_3
       205: areturn

  boolean storageContainsKey(java.lang.String);
    Code:
         0: aload_0
         1: getfield      #147                // Field storage:Ljava/util/Map;
         4: aload_1
         5: invokeinterface #399,  2          // InterfaceMethod java/util/Map.containsKey:(Ljava/lang/Object;)Z
        10: ireturn

  private boolean runScript(ghidra.app.script.GhidraState, ghidra.app.script.GhidraScript);
    Code:
         0: aload_2
         1: instanceof    #451                // class ghidra/app/util/headless/HeadlessScript
         4: ifeq          15
         7: aload_2
         8: checkcast     #451                // class ghidra/app/util/headless/HeadlessScript
        11: aload_0
        12: invokevirtual #453                // Method ghidra/app/util/headless/HeadlessScript.setHeadlessInstance:(Lghidra/app/util/headless/HeadlessAnalyzer;)V
        15: aload_2
        16: invokevirtual #457                // Method ghidra/app/script/GhidraScript.getSourceFile:()Lgeneric/jar/ResourceFile;
        19: astore_3
        20: aload_3
        21: ifnull        31
        24: aload_3
        25: invokevirtual #463                // Method generic/jar/ResourceFile.getAbsolutePath:()Ljava/lang/String;
        28: goto          43
        31: aload_2
        32: invokevirtual #466                // Method java/lang/Object.getClass:()Ljava/lang/Class;
        35: invokevirtual #470                // Method java/lang/Class.getName:()Ljava/lang/String;
        38: invokedynamic #475,  0            // InvokeDynamic #12:makeConcatWithConstants:(Ljava/lang/String;)Ljava/lang/String;
        43: astore        4
        45: aload_0
        46: aload         4
        48: invokedynamic #476,  0            // InvokeDynamic #13:makeConcatWithConstants:(Ljava/lang/String;)Ljava/lang/String;
        53: invokestatic  #281                // Method ghidra/util/Msg.info:(Ljava/lang/Object;Ljava/lang/Object;)V
        56: aload_2
        57: aload_1
        58: getstatic     #477                // Field ghidra/app/script/ScriptControls.NONE:Lghidra/app/script/ScriptControls;
        61: invokevirtual #483                // Method ghidra/app/script/GhidraScript.execute:(Lghidra/app/script/GhidraState;Lghidra/app/script/ScriptControls;)V
        64: goto          84
        67: astore        5
        69: ldc_w         #489                // String REPORT SCRIPT ERROR:
        72: astore        6
        74: aload_0
        75: aload         6
        77: aload         5
        79: invokestatic  #491                // Method ghidra/util/Msg.error:(Ljava/lang/Object;Ljava/lang/Object;Ljava/lang/Throwable;)V
        82: iconst_0
        83: ireturn
        84: iconst_1
        85: ireturn
      Exception table:
         from    to  target type
            45    64    67   Class java/lang/Exception

  private boolean checkUpdateOptions();
    Code:
         0: aload_0
         1: getfield      #86                 // Field options:Lghidra/app/util/headless/HeadlessOptions;
         4: getfield      #155                // Field ghidra/app/util/headless/HeadlessOptions.readOnly:Z
         7: ifeq          61
        10: ldc_w         #494                // String Abort due to Headless analyzer error: The requested -readOnly option is in conflict with the
        13: astore_1
        14: aload_0
        15: getfield      #86                 // Field options:Lghidra/app/util/headless/HeadlessOptions;
        18: getfield      #158                // Field ghidra/app/util/headless/HeadlessOptions.commit:Z
        21: ifeq          36
        24: aload_0
        25: aload_1
        26: invokedynamic #496,  0            // InvokeDynamic #14:makeConcatWithConstants:(Ljava/lang/String;)Ljava/lang/String;
        31: invokestatic  #163                // Method ghidra/util/Msg.error:(Ljava/lang/Object;Ljava/lang/Object;)V
        34: iconst_0
        35: ireturn
        36: aload_0
        37: getfield      #86                 // Field options:Lghidra/app/util/headless/HeadlessOptions;
        40: getfield      #497                // Field ghidra/app/util/headless/HeadlessOptions.okToDelete:Z
        43: ifeq          58
        46: aload_0
        47: aload_1
        48: invokedynamic #500,  0            // InvokeDynamic #15:makeConcatWithConstants:(Ljava/lang/String;)Ljava/lang/String;
        53: invokestatic  #163                // Method ghidra/util/Msg.error:(Ljava/lang/Object;Ljava/lang/Object;)V
        56: iconst_0
        57: ireturn
        58: goto          77
        61: aload_0
        62: invokevirtual #501                // Method isInWritableProject:()Z
        65: ifne          77
        68: aload_0
        69: ldc_w         #504                // String Processing files within read-only project/repository - the -readOnly option is required.
        72: invokestatic  #163                // Method ghidra/util/Msg.error:(Ljava/lang/Object;Ljava/lang/Object;)V
        75: iconst_0
        76: ireturn
        77: aload_0
        78: invokevirtual #506                // Method isCommitAllowed:()Z
        81: istore_1
        82: aload_0
        83: getfield      #86                 // Field options:Lghidra/app/util/headless/HeadlessOptions;
        86: getfield      #158                // Field ghidra/app/util/headless/HeadlessOptions.commit:Z
        89: ifeq          105
        92: iload_1
        93: ifne          105
        96: aload_0
        97: ldc_w         #509                // String Commit to repository not possible (due to permission or connection issue)
       100: invokestatic  #163                // Method ghidra/util/Msg.error:(Ljava/lang/Object;Ljava/lang/Object;)V
       103: iconst_0
       104: ireturn
       105: aload_0
       106: getfield      #132                // Field project:Lghidra/framework/model/Project;
       109: invokeinterface #511,  1          // InterfaceMethod ghidra/framework/model/Project.getProjectLocator:()Lghidra/framework/model/ProjectLocator;
       114: invokevirtual #515                // Method ghidra/framework/model/ProjectLocator.isTransient:()Z
       117: ifeq          159
       120: aload_0
       121: getfield      #86                 // Field options:Lghidra/app/util/headless/HeadlessOptions;
       124: getfield      #158                // Field ghidra/app/util/headless/HeadlessOptions.commit:Z
       127: ifne          159
       130: iload_1
       131: ifeq          159
       134: aload_0
       135: getfield      #86                 // Field options:Lghidra/app/util/headless/HeadlessOptions;
       138: getfield      #155                // Field ghidra/app/util/headless/HeadlessOptions.readOnly:Z
       141: ifne          159
       144: aload_0
       145: ldc_w         #518                // String When processing a URL, -commit is automatically enabled unless -readOnly mode is specified.  Enabling -commit and continuing.
       148: invokestatic  #281                // Method ghidra/util/Msg.info:(Ljava/lang/Object;Ljava/lang/Object;)V
       151: aload_0
       152: getfield      #86                 // Field options:Lghidra/app/util/headless/HeadlessOptions;
       155: iconst_1
       156: putfield      #158                // Field ghidra/app/util/headless/HeadlessOptions.commit:Z
       159: aload_0
       160: getfield      #86                 // Field options:Lghidra/app/util/headless/HeadlessOptions;
       163: getfield      #520                // Field ghidra/app/util/headless/HeadlessOptions.overwrite:Z
       166: ifeq          224
       169: aload_0
       170: getfield      #86                 // Field options:Lghidra/app/util/headless/HeadlessOptions;
       173: getfield      #205                // Field ghidra/app/util/headless/HeadlessOptions.runScriptsNoImport:Z
       176: ifne          183
       179: iconst_1
       180: goto          184
       183: iconst_0
       184: istore_2
       185: iload_2
       186: ifne          199
       189: aload_0
       190: ldc_w         #523                // String Ignoring -overwrite because it is not applicable to -process mode.
       193: invokestatic  #281                // Method ghidra/util/Msg.info:(Ljava/lang/Object;Ljava/lang/Object;)V
       196: goto          224
       199: aload_0
       200: getfield      #86                 // Field options:Lghidra/app/util/headless/HeadlessOptions;
       203: getfield      #155                // Field ghidra/app/util/headless/HeadlessOptions.readOnly:Z
       206: ifeq          224
       209: aload_0
       210: ldc_w         #525                // String Ignoring -overwrite because it is not applicable to -readOnly import mode.
       213: invokestatic  #281                // Method ghidra/util/Msg.info:(Ljava/lang/Object;Ljava/lang/Object;)V
       216: aload_0
       217: getfield      #86                 // Field options:Lghidra/app/util/headless/HeadlessOptions;
       220: iconst_0
       221: putfield      #520                // Field ghidra/app/util/headless/HeadlessOptions.overwrite:Z
       224: iconst_1
       225: ireturn

  private boolean isInWritableProject();
    Code:
         0: aload_0
         1: getfield      #132                // Field project:Lghidra/framework/model/Project;
         4: invokeinterface #418,  1          // InterfaceMethod ghidra/framework/model/Project.getProjectData:()Lghidra/framework/model/ProjectData;
         9: invokeinterface #443,  1          // InterfaceMethod ghidra/framework/model/ProjectData.getRootFolder:()Lghidra/framework/model/DomainFolder;
        14: invokeinterface #527,  1          // InterfaceMethod ghidra/framework/model/DomainFolder.isInWritableProject:()Z
        19: ireturn

  private boolean isCommitAllowed();
    Code:
         0: aload_0
         1: getfield      #132                // Field project:Lghidra/framework/model/Project;
         4: invokeinterface #528,  1          // InterfaceMethod ghidra/framework/model/Project.getRepository:()Lghidra/framework/client/RepositoryAdapter;
         9: astore_1
        10: aload_1
        11: ifnonnull     16
        14: iconst_1
        15: ireturn
        16: aload_1
        17: invokevirtual #532                // Method ghidra/framework/client/RepositoryAdapter.connect:()V
        20: aload_1
        21: invokevirtual #537                // Method ghidra/framework/client/RepositoryAdapter.isConnected:()Z
        24: ifne          29
        27: iconst_0
        28: ireturn
        29: aload_1
        30: invokevirtual #540                // Method ghidra/framework/client/RepositoryAdapter.getUser:()Lghidra/framework/remote/User;
        33: astore_2
        34: aload_2
        35: invokevirtual #544                // Method ghidra/framework/remote/User.hasWritePermission:()Z
        38: ifne          56
        41: aload_0
        42: aload_2
        43: invokevirtual #549                // Method ghidra/framework/remote/User.getName:()Ljava/lang/String;
        46: invokedynamic #550,  0            // InvokeDynamic #16:makeConcatWithConstants:(Ljava/lang/String;)Ljava/lang/String;
        51: invokestatic  #163                // Method ghidra/util/Msg.error:(Ljava/lang/Object;Ljava/lang/Object;)V
        54: iconst_0
        55: ireturn
        56: iconst_1
        57: ireturn
        58: astore_2
        59: aload_0
        60: aload_1
        61: invokevirtual #551                // Method ghidra/framework/client/RepositoryAdapter.getServerInfo:()Lghidra/framework/model/ServerInfo;
        64: invokestatic  #181                // Method java/lang/String.valueOf:(Ljava/lang/Object;)Ljava/lang/String;
        67: invokedynamic #555,  0            // InvokeDynamic #17:makeConcatWithConstants:(Ljava/lang/String;)Ljava/lang/String;
        72: invokestatic  #163                // Method ghidra/util/Msg.error:(Ljava/lang/Object;Ljava/lang/Object;)V
        75: iconst_0
        76: ireturn
      Exception table:
         from    to  target type
            16    28    58   Class java/io/IOException
            29    55    58   Class java/io/IOException
            56    57    58   Class java/io/IOException

  private java.util.List<generic.jar.ResourceFile> parseScriptPaths(java.util.List<java.lang.String>);
    Code:
         0: aload_1
         1: ifnonnull     8
         4: invokestatic  #556                // InterfaceMethod java/util/List.of:()Ljava/util/List;
         7: areturn
         8: new           #560                // class java/util/ArrayList
        11: dup
        12: invokespecial #562                // Method java/util/ArrayList."<init>":()V
        15: astore_2
        16: aload_1
        17: invokeinterface #563,  1          // InterfaceMethod java/util/List.iterator:()Ljava/util/Iterator;
        22: astore_3
        23: aload_3
        24: invokeinterface #567,  1          // InterfaceMethod java/util/Iterator.hasNext:()Z
        29: ifeq          87
        32: aload_3
        33: invokeinterface #572,  1          // InterfaceMethod java/util/Iterator.next:()Ljava/lang/Object;
        38: checkcast     #174                // class java/lang/String
        41: astore        4
        43: aload         4
        45: invokestatic  #576                // Method generic/util/Path.fromPathString:(Ljava/lang/String;)Lgeneric/jar/ResourceFile;
        48: astore        5
        50: aload         5
        52: invokevirtual #582                // Method generic/jar/ResourceFile.exists:()Z
        55: ifeq          70
        58: aload_2
        59: aload         5
        61: invokeinterface #583,  2          // InterfaceMethod java/util/List.add:(Ljava/lang/Object;)Z
        66: pop
        67: goto          84
        70: aload_0
        71: aload         5
        73: invokestatic  #181                // Method java/lang/String.valueOf:(Ljava/lang/Object;)Ljava/lang/String;
        76: invokedynamic #585,  0            // InvokeDynamic #18:makeConcatWithConstants:(Ljava/lang/String;)Ljava/lang/String;
        81: invokestatic  #225                // Method ghidra/util/Msg.warn:(Ljava/lang/Object;Ljava/lang/Object;)V
        84: goto          23
        87: aload_2
        88: areturn

  private void showConfiguredScriptPaths();
    Code:
         0: new           #586                // class java/lang/StringBuffer
         3: dup
         4: ldc_w         #588                // String HEADLESS Script Paths:
         7: invokespecial #590                // Method java/lang/StringBuffer."<init>":(Ljava/lang/String;)V
        10: astore_1
        11: invokestatic  #591                // Method ghidra/app/script/GhidraScriptUtil.getScriptSourceDirectories:()Ljava/util/List;
        14: invokeinterface #563,  1          // InterfaceMethod java/util/List.iterator:()Ljava/util/Iterator;
        19: astore_2
        20: aload_2
        21: invokeinterface #567,  1          // InterfaceMethod java/util/Iterator.hasNext:()Z
        26: ifeq          59
        29: aload_2
        30: invokeinterface #572,  1          // InterfaceMethod java/util/Iterator.next:()Ljava/lang/Object;
        35: checkcast     #464                // class generic/jar/ResourceFile
        38: astore_3
        39: aload_1
        40: ldc_w         #594                // String \n
        43: invokevirtual #596                // Method java/lang/StringBuffer.append:(Ljava/lang/String;)Ljava/lang/StringBuffer;
        46: pop
        47: aload_1
        48: aload_3
        49: invokevirtual #463                // Method generic/jar/ResourceFile.getAbsolutePath:()Ljava/lang/String;
        52: invokevirtual #596                // Method java/lang/StringBuffer.append:(Ljava/lang/String;)Ljava/lang/StringBuffer;
        55: pop
        56: goto          20
        59: ldc           #2                  // class ghidra/app/util/headless/HeadlessAnalyzer
        61: aload_1
        62: invokevirtual #600                // Method java/lang/StringBuffer.toString:()Ljava/lang/String;
        65: invokestatic  #281                // Method ghidra/util/Msg.info:(Ljava/lang/Object;Ljava/lang/Object;)V
        68: return

  private generic.jar.ResourceFile findScript(java.lang.String);
    Code:
         0: new           #464                // class generic/jar/ResourceFile
         3: dup
         4: aload_1
         5: invokespecial #601                // Method generic/jar/ResourceFile."<init>":(Ljava/lang/String;)V
         8: astore_2
         9: aload_2
        10: invokevirtual #602                // Method generic/jar/ResourceFile.getCanonicalFile:()Lgeneric/jar/ResourceFile;
        13: astore_2
        14: aload_2
        15: invokevirtual #582                // Method generic/jar/ResourceFile.exists:()Z
        18: ifeq          23
        21: aload_2
        22: areturn
        23: aload_1
        24: invokestatic  #605                // Method ghidra/app/script/GhidraScriptUtil.findScriptByName:(Ljava/lang/String;)Lgeneric/jar/ResourceFile;
        27: astore_2
        28: aload_2
        29: ifnull        34
        32: aload_2
        33: areturn
        34: new           #608                // class java/lang/IllegalArgumentException
        37: dup
        38: aload_1
        39: invokedynamic #610,  0            // InvokeDynamic #19:makeConcatWithConstants:(Ljava/lang/String;)Ljava/lang/String;
        44: invokespecial #611                // Method java/lang/IllegalArgumentException."<init>":(Ljava/lang/String;)V
        47: athrow

  private generic.jar.ResourceFile checkScript(java.lang.String);
    Code:
         0: ldc_w         #612                // String .class
         3: astore_2
         4: aload_1
         5: aload_2
         6: invokevirtual #230                // Method java/lang/String.endsWith:(Ljava/lang/String;)Z
         9: ifeq          169
        12: aload_1
        13: iconst_0
        14: aload_1
        15: invokevirtual #201                // Method java/lang/String.length:()I
        18: aload_2
        19: invokevirtual #201                // Method java/lang/String.length:()I
        22: isub
        23: invokevirtual #250                // Method java/lang/String.substring:(II)Ljava/lang/String;
        26: astore_3
        27: invokestatic  #591                // Method ghidra/app/script/GhidraScriptUtil.getScriptSourceDirectories:()Ljava/util/List;
        30: astore        4
        32: new           #560                // class java/util/ArrayList
        35: dup
        36: invokespecial #562                // Method java/util/ArrayList."<init>":()V
        39: astore        5
        41: aload         4
        43: invokeinterface #563,  1          // InterfaceMethod java/util/List.iterator:()Ljava/util/Iterator;
        48: astore        6
        50: aload         6
        52: invokeinterface #567,  1          // InterfaceMethod java/util/Iterator.hasNext:()Z
        57: ifeq          93
        60: aload         6
        62: invokeinterface #572,  1          // InterfaceMethod java/util/Iterator.next:()Ljava/lang/Object;
        67: checkcast     #464                // class generic/jar/ResourceFile
        70: astore        7
        72: aload         5
        74: aload         7
        76: invokevirtual #614                // Method generic/jar/ResourceFile.toURL:()Ljava/net/URL;
        79: invokeinterface #583,  2          // InterfaceMethod java/util/List.add:(Ljava/lang/Object;)Z
        84: pop
        85: goto          90
        88: astore        8
        90: goto          50
        93: aload_0
        94: aload         5
        96: iconst_0
        97: anewarray     #169                // class java/net/URL
       100: invokeinterface #615,  2          // InterfaceMethod java/util/List.toArray:([Ljava/lang/Object;)[Ljava/lang/Object;
       105: checkcast     #619                // class "[Ljava/net/URL;"
       108: invokestatic  #621                // Method java/net/URLClassLoader.newInstance:([Ljava/net/URL;)Ljava/net/URLClassLoader;
       111: putfield      #151                // Field classLoaderForDotClassScripts:Ljava/net/URLClassLoader;
       114: aload_3
       115: ldc_w         #458                // class ghidra/app/script/GhidraScript
       118: aload_0
       119: getfield      #151                // Field classLoaderForDotClassScripts:Ljava/net/URLClassLoader;
       122: invokestatic  #627                // Method ghidra/util/classfinder/ClassSearcher.forNameSafe:(Ljava/lang/String;Ljava/lang/Class;Ljava/lang/ClassLoader;)Ljava/lang/Class;
       125: pop
       126: aconst_null
       127: areturn
       128: astore        4
       130: aload_0
       131: aload_3
       132: invokedynamic #635,  0            // InvokeDynamic #20:makeConcatWithConstants:(Ljava/lang/String;)Ljava/lang/String;
       137: invokestatic  #163                // Method ghidra/util/Msg.error:(Ljava/lang/Object;Ljava/lang/Object;)V
       140: goto          155
       143: astore        4
       145: aload_0
       146: aload_3
       147: invokedynamic #638,  0            // InvokeDynamic #21:makeConcatWithConstants:(Ljava/lang/String;)Ljava/lang/String;
       152: invokestatic  #163                // Method ghidra/util/Msg.error:(Ljava/lang/Object;Ljava/lang/Object;)V
       155: new           #608                // class java/lang/IllegalArgumentException
       158: dup
       159: aload_1
       160: invokedynamic #639,  0            // InvokeDynamic #22:makeConcatWithConstants:(Ljava/lang/String;)Ljava/lang/String;
       165: invokespecial #611                // Method java/lang/IllegalArgumentException."<init>":(Ljava/lang/String;)V
       168: athrow
       169: aload_0
       170: aload_1
       171: invokevirtual #640                // Method findScript:(Ljava/lang/String;)Lgeneric/jar/ResourceFile;
       174: astore_3
       175: aload_3
       176: invokestatic  #643                // Method ghidra/app/script/GhidraScriptUtil.getProvider:(Lgeneric/jar/ResourceFile;)Lghidra/app/script/GhidraScriptProvider;
       179: astore        4
       181: aload         4
       183: ifnonnull     197
       186: new           #63                 // class java/io/IOException
       189: dup
       190: ldc_w         #647                // String Missing plugin needed to run scripts of this type. Please ensure you have installed the necessary plugin.
       193: invokespecial #346                // Method java/io/IOException."<init>":(Ljava/lang/String;)V
       196: athrow
       197: aload_3
       198: areturn
       199: astore_3
       200: aload_1
       201: aload_3
       202: invokevirtual #651                // Method java/lang/Throwable.getMessage:()Ljava/lang/String;
       205: invokedynamic #654,  0            // InvokeDynamic #23:makeConcatWithConstants:(Ljava/lang/String;Ljava/lang/String;)Ljava/lang/String;
       210: astore        4
       212: aload_0
       213: aload         4
       215: invokestatic  #163                // Method ghidra/util/Msg.error:(Ljava/lang/Object;Ljava/lang/Object;)V
       218: new           #608                // class java/lang/IllegalArgumentException
       221: dup
       222: aload_1
       223: invokedynamic #639,  0            // InvokeDynamic #22:makeConcatWithConstants:(Ljava/lang/String;)Ljava/lang/String;
       228: invokespecial #611                // Method java/lang/IllegalArgumentException."<init>":(Ljava/lang/String;)V
       231: athrow
      Exception table:
         from    to  target type
            72    85    88   Class java/net/MalformedURLException
            27   127   128   Class java/lang/ClassNotFoundException
            27   127   143   Class java/lang/ClassCastException
           169   198   199   Class java/lang/Exception
           169   198   199   Class java/lang/NoClassDefFoundError

  private java.util.Map<java.lang.String, generic.jar.ResourceFile> checkScriptsList(java.util.List<generic.stl.Pair<java.lang.String, java.lang.String[]>>);
    Code:
         0: new           #144                // class java/util/HashMap
         3: dup
         4: invokespecial #146                // Method java/util/HashMap."<init>":()V
         7: astore_2
         8: aload_1
         9: invokeinterface #563,  1          // InterfaceMethod java/util/List.iterator:()Ljava/util/Iterator;
        14: astore_3
        15: aload_3
        16: invokeinterface #567,  1          // InterfaceMethod java/util/Iterator.hasNext:()Z
        21: ifeq          67
        24: aload_3
        25: invokeinterface #572,  1          // InterfaceMethod java/util/Iterator.next:()Ljava/lang/Object;
        30: checkcast     #655                // class generic/stl/Pair
        33: astore        4
        35: aload         4
        37: getfield      #657                // Field generic/stl/Pair.first:Ljava/lang/Object;
        40: checkcast     #174                // class java/lang/String
        43: astore        5
        45: aload_0
        46: aload         5
        48: invokevirtual #661                // Method checkScript:(Ljava/lang/String;)Lgeneric/jar/ResourceFile;
        51: astore        6
        53: aload_2
        54: aload         5
        56: aload         6
        58: invokeinterface #405,  3          // InterfaceMethod java/util/Map.put:(Ljava/lang/Object;Ljava/lang/Object;)Ljava/lang/Object;
        63: pop
        64: goto          15
        67: aload_2
        68: areturn

  private void compileScripts() throws java.io.IOException;
    Code:
         0: aload_0
         1: getfield      #86                 // Field options:Lghidra/app/util/headless/HeadlessOptions;
         4: getfield      #664                // Field ghidra/app/util/headless/HeadlessOptions.propertiesFileStrPaths:Ljava/util/List;
         7: invokeinterface #208,  1          // InterfaceMethod java/util/List.size:()I
        12: ifle          141
        15: aload_0
        16: getfield      #86                 // Field options:Lghidra/app/util/headless/HeadlessOptions;
        19: getfield      #667                // Field ghidra/app/util/headless/HeadlessOptions.propertiesFilePaths:Ljava/util/List;
        22: invokeinterface #670,  1          // InterfaceMethod java/util/List.clear:()V
        27: aload_0
        28: getfield      #86                 // Field options:Lghidra/app/util/headless/HeadlessOptions;
        31: getfield      #664                // Field ghidra/app/util/headless/HeadlessOptions.propertiesFileStrPaths:Ljava/util/List;
        34: invokeinterface #563,  1          // InterfaceMethod java/util/List.iterator:()Ljava/util/Iterator;
        39: astore_1
        40: aload_1
        41: invokeinterface #567,  1          // InterfaceMethod java/util/Iterator.hasNext:()Z
        46: ifeq          141
        49: aload_1
        50: invokeinterface #572,  1          // InterfaceMethod java/util/Iterator.next:()Ljava/lang/Object;
        55: checkcast     #174                // class java/lang/String
        58: astore_2
        59: new           #577                // class generic/util/Path
        62: dup
        63: aload_2
        64: iconst_1
        65: iconst_0
        66: iconst_1
        67: invokespecial #673                // Method generic/util/Path."<init>":(Ljava/lang/String;ZZZ)V
        70: astore_3
        71: aload_3
        72: invokevirtual #676                // Method generic/util/Path.getPath:()Lgeneric/jar/ResourceFile;
        75: astore        4
        77: aload         4
        79: invokevirtual #678                // Method generic/jar/ResourceFile.isDirectory:()Z
        82: ifne          99
        85: new           #63                 // class java/io/IOException
        88: dup
        89: aload_2
        90: invokedynamic #681,  0            // InvokeDynamic #24:makeConcatWithConstants:(Ljava/lang/String;)Ljava/lang/String;
        95: invokespecial #346                // Method java/io/IOException."<init>":(Ljava/lang/String;)V
        98: athrow
        99: aload_3
       100: invokevirtual #682                // Method generic/util/Path.isEnabled:()Z
       103: ifeq          138
       106: aload_0
       107: getfield      #86                 // Field options:Lghidra/app/util/headless/HeadlessOptions;
       110: getfield      #667                // Field ghidra/app/util/headless/HeadlessOptions.propertiesFilePaths:Ljava/util/List;
       113: aload         4
       115: invokeinterface #685,  2          // InterfaceMethod java/util/List.contains:(Ljava/lang/Object;)Z
       120: ifne          138
       123: aload_0
       124: getfield      #86                 // Field options:Lghidra/app/util/headless/HeadlessOptions;
       127: getfield      #667                // Field ghidra/app/util/headless/HeadlessOptions.propertiesFilePaths:Ljava/util/List;
       130: aload         4
       132: invokeinterface #583,  2          // InterfaceMethod java/util/List.add:(Ljava/lang/Object;)Z
       137: pop
       138: goto          40
       141: aload_0
       142: getfield      #86                 // Field options:Lghidra/app/util/headless/HeadlessOptions;
       145: getfield      #688                // Field ghidra/app/util/headless/HeadlessOptions.preScriptFileMap:Ljava/util/Map;
       148: ifnonnull     169
       151: aload_0
       152: getfield      #86                 // Field options:Lghidra/app/util/headless/HeadlessOptions;
       155: aload_0
       156: aload_0
       157: getfield      #86                 // Field options:Lghidra/app/util/headless/HeadlessOptions;
       160: getfield      #213                // Field ghidra/app/util/headless/HeadlessOptions.preScripts:Ljava/util/List;
       163: invokevirtual #691                // Method checkScriptsList:(Ljava/util/List;)Ljava/util/Map;
       166: putfield      #688                // Field ghidra/app/util/headless/HeadlessOptions.preScriptFileMap:Ljava/util/Map;
       169: aload_0
       170: getfield      #86                 // Field options:Lghidra/app/util/headless/HeadlessOptions;
       173: getfield      #695                // Field ghidra/app/util/headless/HeadlessOptions.postScriptFileMap:Ljava/util/Map;
       176: ifnonnull     197
       179: aload_0
       180: getfield      #86                 // Field options:Lghidra/app/util/headless/HeadlessOptions;
       183: aload_0
       184: aload_0
       185: getfield      #86                 // Field options:Lghidra/app/util/headless/HeadlessOptions;
       188: getfield      #220                // Field ghidra/app/util/headless/HeadlessOptions.postScripts:Ljava/util/List;
       191: invokevirtual #691                // Method checkScriptsList:(Ljava/util/List;)Ljava/util/Map;
       194: putfield      #695                // Field ghidra/app/util/headless/HeadlessOptions.postScriptFileMap:Ljava/util/Map;
       197: return

  private ghidra.app.util.headless.HeadlessScript$HeadlessContinuationOption runScriptsList(java.util.List<generic.stl.Pair<java.lang.String, java.lang.String[]>>, java.util.Map<java.lang.String, generic.jar.ResourceFile>, ghidra.app.script.GhidraState, ghidra.app.util.headless.HeadlessScript$HeadlessContinuationOption);
    Code:
         0: aload         4
         2: astore        6
         4: iconst_0
         5: istore        8
         7: ldc_w         #352                // String
        10: astore        9
        12: aload_1
        13: invokeinterface #563,  1          // InterfaceMethod java/util/List.iterator:()Ljava/util/Iterator;
        18: astore        11
        20: aload         11
        22: invokeinterface #567,  1          // InterfaceMethod java/util/Iterator.hasNext:()Z
        27: ifeq          477
        30: aload         11
        32: invokeinterface #572,  1          // InterfaceMethod java/util/Iterator.next:()Ljava/lang/Object;
        37: checkcast     #655                // class generic/stl/Pair
        40: astore        12
        42: aload         12
        44: getfield      #657                // Field generic/stl/Pair.first:Ljava/lang/Object;
        47: checkcast     #174                // class java/lang/String
        50: astore        9
        52: aload         12
        54: getfield      #698                // Field generic/stl/Pair.second:Ljava/lang/Object;
        57: checkcast     #701                // class "[Ljava/lang/String;"
        60: astore        13
        62: new           #703                // class java/lang/StringBuilder
        65: dup
        66: invokespecial #705                // Method java/lang/StringBuilder."<init>":()V
        69: astore        14
        71: aload         13
        73: astore        15
        75: aload         15
        77: arraylength
        78: istore        16
        80: iconst_0
        81: istore        17
        83: iload         17
        85: iload         16
        87: if_icmpge     129
        90: aload         15
        92: iload         17
        94: aaload
        95: astore        18
        97: aload         14
        99: ldc_w         #706                // String \'
       102: invokevirtual #708                // Method java/lang/StringBuilder.append:(Ljava/lang/String;)Ljava/lang/StringBuilder;
       105: pop
       106: aload         14
       108: aload         18
       110: invokevirtual #708                // Method java/lang/StringBuilder.append:(Ljava/lang/String;)Ljava/lang/StringBuilder;
       113: pop
       114: aload         14
       116: ldc_w         #711                // String \'
       119: invokevirtual #708                // Method java/lang/StringBuilder.append:(Ljava/lang/String;)Ljava/lang/StringBuilder;
       122: pop
       123: iinc          17, 1
       126: goto          83
       129: aload_0
       130: aload         9
       132: aload         14
       134: invokevirtual #713                // Method java/lang/StringBuilder.toString:()Ljava/lang/String;
       137: invokedynamic #714,  0            // InvokeDynamic #25:makeConcatWithConstants:(Ljava/lang/String;Ljava/lang/String;)Ljava/lang/String;
       142: invokestatic  #281                // Method ghidra/util/Msg.info:(Ljava/lang/Object;Ljava/lang/Object;)V
       145: aload         9
       147: ldc_w         #612                // String .class
       150: invokevirtual #230                // Method java/lang/String.endsWith:(Ljava/lang/String;)Z
       153: ifeq          308
       156: aload_0
       157: getfield      #151                // Field classLoaderForDotClassScripts:Ljava/net/URLClassLoader;
       160: ifnonnull     178
       163: new           #608                // class java/lang/IllegalArgumentException
       166: dup
       167: aload         9
       169: invokedynamic #639,  0            // InvokeDynamic #22:makeConcatWithConstants:(Ljava/lang/String;)Ljava/lang/String;
       174: invokespecial #611                // Method java/lang/IllegalArgumentException."<init>":(Ljava/lang/String;)V
       177: athrow
       178: aload         9
       180: iconst_0
       181: aload         9
       183: invokevirtual #201                // Method java/lang/String.length:()I
       186: bipush        6
       188: isub
       189: invokevirtual #250                // Method java/lang/String.substring:(II)Ljava/lang/String;
       192: astore        15
       194: aload         15
       196: ldc_w         #458                // class ghidra/app/script/GhidraScript
       199: aload_0
       200: getfield      #151                // Field classLoaderForDotClassScripts:Ljava/net/URLClassLoader;
       203: invokestatic  #627                // Method ghidra/util/classfinder/ClassSearcher.forNameSafe:(Ljava/lang/String;Ljava/lang/Class;Ljava/lang/ClassLoader;)Ljava/lang/Class;
       206: astore        16
       208: new           #322                // class java/io/File
       211: dup
       212: aload         16
       214: aload         16
       216: invokevirtual #715                // Method java/lang/Class.getSimpleName:()Ljava/lang/String;
       219: invokedynamic #475,  0            // InvokeDynamic #12:makeConcatWithConstants:(Ljava/lang/String;)Ljava/lang/String;
       224: invokevirtual #718                // Method java/lang/Class.getResource:(Ljava/lang/String;)Ljava/net/URL;
       227: invokevirtual #722                // Method java/net/URL.toURI:()Ljava/net/URI;
       230: invokespecial #726                // Method java/io/File."<init>":(Ljava/net/URI;)V
       233: invokevirtual #729                // Method java/io/File.getParentFile:()Ljava/io/File;
       236: astore        17
       238: aload         16
       240: iconst_0
       241: anewarray     #471                // class java/lang/Class
       244: invokevirtual #732                // Method java/lang/Class.getConstructor:([Ljava/lang/Class;)Ljava/lang/reflect/Constructor;
       247: iconst_0
       248: anewarray     #81                 // class java/lang/Object
       251: invokevirtual #736                // Method java/lang/reflect/Constructor.newInstance:([Ljava/lang/Object;)Ljava/lang/Object;
       254: checkcast     #458                // class ghidra/app/script/GhidraScript
       257: astore        10
       259: aload         10
       261: aload         13
       263: invokevirtual #741                // Method ghidra/app/script/GhidraScript.setScriptArgs:([Ljava/lang/String;)V
       266: aload_0
       267: getfield      #86                 // Field options:Lghidra/app/util/headless/HeadlessOptions;
       270: getfield      #667                // Field ghidra/app/util/headless/HeadlessOptions.propertiesFilePaths:Ljava/util/List;
       273: invokeinterface #208,  1          // InterfaceMethod java/util/List.size:()I
       278: ifle          293
       281: aload         10
       283: aload_0
       284: getfield      #86                 // Field options:Lghidra/app/util/headless/HeadlessOptions;
       287: getfield      #667                // Field ghidra/app/util/headless/HeadlessOptions.propertiesFilePaths:Ljava/util/List;
       290: invokevirtual #745                // Method ghidra/app/script/GhidraScript.setPotentialPropertiesFileLocations:(Ljava/util/List;)V
       293: aload         10
       295: aload         17
       297: invokevirtual #327                // Method java/io/File.getAbsolutePath:()Ljava/lang/String;
       300: aload         15
       302: invokevirtual #749                // Method ghidra/app/script/GhidraScript.setPropertiesFileLocation:(Ljava/lang/String;Ljava/lang/String;)V
       305: goto          385
       308: aload_2
       309: aload         9
       311: invokeinterface #414,  2          // InterfaceMethod java/util/Map.get:(Ljava/lang/Object;)Ljava/lang/Object;
       316: checkcast     #464                // class generic/jar/ResourceFile
       319: astore        5
       321: aload         5
       323: invokestatic  #643                // Method ghidra/app/script/GhidraScriptUtil.getProvider:(Lgeneric/jar/ResourceFile;)Lghidra/app/script/GhidraScriptProvider;
       326: astore        15
       328: new           #752                // class java/io/PrintWriter
       331: dup
       332: getstatic     #754                // Field java/lang/System.err:Ljava/io/PrintStream;
       335: invokespecial #758                // Method java/io/PrintWriter."<init>":(Ljava/io/OutputStream;)V
       338: astore        16
       340: aload         15
       342: aload         5
       344: aload         16
       346: invokevirtual #761                // Method ghidra/app/script/GhidraScriptProvider.getScriptInstance:(Lgeneric/jar/ResourceFile;Ljava/io/PrintWriter;)Lghidra/app/script/GhidraScript;
       349: astore        10
       351: aload         10
       353: aload         13
       355: invokevirtual #741                // Method ghidra/app/script/GhidraScript.setScriptArgs:([Ljava/lang/String;)V
       358: aload_0
       359: getfield      #86                 // Field options:Lghidra/app/util/headless/HeadlessOptions;
       362: getfield      #667                // Field ghidra/app/util/headless/HeadlessOptions.propertiesFilePaths:Ljava/util/List;
       365: invokeinterface #208,  1          // InterfaceMethod java/util/List.size:()I
       370: ifle          385
       373: aload         10
       375: aload_0
       376: getfield      #86                 // Field options:Lghidra/app/util/headless/HeadlessOptions;
       379: getfield      #667                // Field ghidra/app/util/headless/HeadlessOptions.propertiesFilePaths:Ljava/util/List;
       382: invokevirtual #745                // Method ghidra/app/script/GhidraScript.setPotentialPropertiesFileLocations:(Ljava/util/List;)V
       385: aload         10
       387: instanceof    #451                // class ghidra/app/util/headless/HeadlessScript
       390: ifeq          397
       393: iconst_1
       394: goto          398
       397: iconst_0
       398: istore        8
       400: iload         8
       402: ifeq          415
       405: aload         10
       407: checkcast     #451                // class ghidra/app/util/headless/HeadlessScript
       410: aload         6
       412: invokevirtual #767                // Method ghidra/app/util/headless/HeadlessScript.setInitialContinuationOption:(Lghidra/app/util/headless/HeadlessScript$HeadlessContinuationOption;)V
       415: aload_0
       416: aload_3
       417: aload         10
       419: invokevirtual #771                // Method runScript:(Lghidra/app/script/GhidraState;Lghidra/app/script/GhidraScript;)Z
       422: istore        7
       424: iload         8
       426: ifeq          474
       429: iload         7
       431: ifeq          463
       434: aload         10
       436: checkcast     #451                // class ghidra/app/util/headless/HeadlessScript
       439: invokevirtual #775                // Method ghidra/app/util/headless/HeadlessScript.getContinuationOption:()Lghidra/app/util/headless/HeadlessScript$HeadlessContinuationOption;
       442: astore        6
       444: aload         6
       446: getstatic     #779                // Field ghidra/app/util/headless/HeadlessScript$HeadlessContinuationOption.ABORT:Lghidra/app/util/headless/HeadlessScript$HeadlessContinuationOption;
       449: if_acmpeq     460
       452: aload         6
       454: getstatic     #785                // Field ghidra/app/util/headless/HeadlessScript$HeadlessContinuationOption.ABORT_AND_DELETE:Lghidra/app/util/headless/HeadlessScript$HeadlessContinuationOption;
       457: if_acmpne     474
       460: aload         6
       462: areturn
       463: aload_0
       464: ldc_w         #788                // String Script does not exist or encountered problems; further processing is aborted.
       467: invokestatic  #225                // Method ghidra/util/Msg.warn:(Ljava/lang/Object;Ljava/lang/Object;)V
       470: getstatic     #779                // Field ghidra/app/util/headless/HeadlessScript$HeadlessContinuationOption.ABORT:Lghidra/app/util/headless/HeadlessScript$HeadlessContinuationOption;
       473: areturn
       474: goto          20
       477: goto          516
       480: astore        11
       482: new           #792                // class java/lang/Error
       485: dup
       486: aload         11
       488: invokespecial #794                // Method java/lang/Error."<init>":(Ljava/lang/Throwable;)V
       491: athrow
       492: astore        11
       494: aload         9
       496: aload         11
       498: invokevirtual #795                // Method java/lang/Exception.getMessage:()Ljava/lang/String;
       501: invokedynamic #654,  0            // InvokeDynamic #23:makeConcatWithConstants:(Ljava/lang/String;Ljava/lang/String;)Ljava/lang/String;
       506: astore        12
       508: aload_0
       509: aload         12
       511: aload         11
       513: invokestatic  #491                // Method ghidra/util/Msg.error:(Ljava/lang/Object;Ljava/lang/Object;Ljava/lang/Throwable;)V
       516: aload         6
       518: areturn
      Exception table:
         from    to  target type
            12   462   480   Class ghidra/app/script/JythonStubScriptProvider$JythonStubException
           463   473   480   Class ghidra/app/script/JythonStubScriptProvider$JythonStubException
           474   477   480   Class ghidra/app/script/JythonStubScriptProvider$JythonStubException
            12   462   492   Class java/lang/Exception
           463   473   492   Class java/lang/Exception
           474   477   492   Class java/lang/Exception

  private ghidra.app.script.GhidraState getInitialProgramState(ghidra.program.model.listing.Program);
    Code:
         0: aconst_null
         1: astore_2
         2: aload_1
         3: invokeinterface #796,  1          // InterfaceMethod ghidra/program/model/listing/Program.getMemory:()Lghidra/program/model/mem/Memory;
         8: invokeinterface #802,  1          // InterfaceMethod ghidra/program/model/mem/Memory.getLoadedAndInitializedAddressSet:()Lghidra/program/model/address/AddressSetView;
        13: astore_3
        14: aload_3
        15: invokeinterface #808,  1          // InterfaceMethod ghidra/program/model/address/AddressSetView.isEmpty:()Z
        20: ifne          38
        23: new           #811                // class ghidra/program/util/ProgramLocation
        26: dup
        27: aload_1
        28: aload_3
        29: invokeinterface #813,  1          // InterfaceMethod ghidra/program/model/address/AddressSetView.getMinAddress:()Lghidra/program/model/address/Address;
        34: invokespecial #817                // Method ghidra/program/util/ProgramLocation."<init>":(Lghidra/program/model/listing/Program;Lghidra/program/model/address/Address;)V
        37: astore_2
        38: new           #820                // class ghidra/app/script/GhidraState
        41: dup
        42: aconst_null
        43: aload_0
        44: getfield      #132                // Field project:Lghidra/framework/model/Project;
        47: aload_1
        48: aload_2
        49: aconst_null
        50: aconst_null
        51: invokespecial #822                // Method ghidra/app/script/GhidraState."<init>":(Lghidra/framework/plugintool/PluginTool;Lghidra/framework/model/Project;Lghidra/program/model/listing/Program;Lghidra/program/util/ProgramLocation;Lghidra/program/util/ProgramSelection;Lghidra/program/util/ProgramSelection;)V
        54: areturn

  private boolean analyzeProgram(java.lang.String, ghidra.program.model.listing.Program);
    Code:
         0: aload_0
         1: iconst_0
         2: putfield      #136                // Field analysisTimedOut:Z
         5: aload_2
         6: invokestatic  #825                // Method ghidra/app/plugin/core/analysis/AutoAnalysisManager.getAnalysisManager:(Lghidra/program/model/listing/Program;)Lghidra/app/plugin/core/analysis/AutoAnalysisManager;
         9: astore_3
        10: aload_3
        11: invokevirtual #831                // Method ghidra/app/plugin/core/analysis/AutoAnalysisManager.initializeOptions:()V
        14: aconst_null
        15: astore        4
        17: getstatic     #834                // Field ghidra/app/util/headless/HeadlessScript$HeadlessContinuationOption.CONTINUE:Lghidra/app/util/headless/HeadlessScript$HeadlessContinuationOption;
        20: astore        5
        22: iconst_0
        23: istore        6
        25: iconst_0
        26: istore        7
        28: aload_0
        29: getfield      #86                 // Field options:Lghidra/app/util/headless/HeadlessOptions;
        32: getfield      #213                // Field ghidra/app/util/headless/HeadlessOptions.preScripts:Ljava/util/List;
        35: invokeinterface #217,  1          // InterfaceMethod java/util/List.isEmpty:()Z
        40: ifne          74
        43: aload_0
        44: aload_2
        45: invokevirtual #837                // Method getInitialProgramState:(Lghidra/program/model/listing/Program;)Lghidra/app/script/GhidraState;
        48: astore        4
        50: aload_0
        51: aload_0
        52: getfield      #86                 // Field options:Lghidra/app/util/headless/HeadlessOptions;
        55: getfield      #213                // Field ghidra/app/util/headless/HeadlessOptions.preScripts:Ljava/util/List;
        58: aload_0
        59: getfield      #86                 // Field options:Lghidra/app/util/headless/HeadlessOptions;
        62: getfield      #688                // Field ghidra/app/util/headless/HeadlessOptions.preScriptFileMap:Ljava/util/Map;
        65: aload         4
        67: aload         5
        69: invokevirtual #841                // Method runScriptsList:(Ljava/util/List;Ljava/util/Map;Lghidra/app/script/GhidraState;Lghidra/app/util/headless/HeadlessScript$HeadlessContinuationOption;)Lghidra/app/util/headless/HeadlessScript$HeadlessContinuationOption;
        72: astore        5
        74: getstatic     #845                // Field ghidra/app/util/headless/HeadlessAnalyzer$3.$SwitchMap$ghidra$app$util$headless$HeadlessScript$HeadlessContinuationOption:[I
        77: aload         5
        79: invokevirtual #851                // Method ghidra/app/util/headless/HeadlessScript$HeadlessContinuationOption.ordinal:()I
        82: iaload
        83: tableswitch   { // 1 to 3
                       1: 108
                       2: 117
                       3: 126
                 default: 135
            }
       108: iconst_1
       109: istore        6
       111: iconst_1
       112: istore        7
       114: goto          135
       117: iconst_0
       118: istore        6
       120: iconst_1
       121: istore        7
       123: goto          135
       126: iconst_1
       127: istore        6
       129: iconst_0
       130: istore        7
       132: goto          135
       135: iload         6
       137: ifeq          158
       140: aload_0
       141: ldc_w         #854                // String Processing aborted as a result of pre-script.
       144: invokestatic  #281                // Method ghidra/util/Msg.info:(Ljava/lang/Object;Ljava/lang/Object;)V
       147: iload         7
       149: ifne          156
       152: iconst_1
       153: goto          157
       156: iconst_0
       157: ireturn
       158: aload_2
       159: ldc_w         #856                // String Analysis
       162: invokeinterface #858,  2          // InterfaceMethod ghidra/program/model/listing/Program.startTransaction:(Ljava/lang/String;)I
       167: istore        8
       169: aload_0
       170: getfield      #86                 // Field options:Lghidra/app/util/headless/HeadlessOptions;
       173: getfield      #862                // Field ghidra/app/util/headless/HeadlessOptions.analyze:Z
       176: ifeq          347
       179: aload_0
       180: aload_1
       181: invokedynamic #865,  0            // InvokeDynamic #26:makeConcatWithConstants:(Ljava/lang/String;)Ljava/lang/String;
       186: invokestatic  #281                // Method ghidra/util/Msg.info:(Ljava/lang/Object;Ljava/lang/Object;)V
       189: aload_3
       190: invokevirtual #831                // Method ghidra/app/plugin/core/analysis/AutoAnalysisManager.initializeOptions:()V
       193: aload_3
       194: aconst_null
       195: invokevirtual #866                // Method ghidra/app/plugin/core/analysis/AutoAnalysisManager.reAnalyzeAll:(Lghidra/program/model/address/AddressSetView;)V
       198: aload_0
       199: getfield      #86                 // Field options:Lghidra/app/util/headless/HeadlessOptions;
       202: getfield      #870                // Field ghidra/app/util/headless/HeadlessOptions.perFileTimeout:I
       205: iconst_m1
       206: if_icmpne     233
       209: aload_3
       210: getstatic     #300                // Field ghidra/util/task/TaskMonitor.DUMMY:Lghidra/util/task/TaskMonitor;
       213: invokevirtual #874                // Method ghidra/app/plugin/core/analysis/AutoAnalysisManager.startAnalysis:(Lghidra/util/task/TaskMonitor;)V
       216: aload_0
       217: aload_1
       218: invokedynamic #878,  0            // InvokeDynamic #27:makeConcatWithConstants:(Ljava/lang/String;)Ljava/lang/String;
       223: invokestatic  #281                // Method ghidra/util/Msg.info:(Ljava/lang/Object;Ljava/lang/Object;)V
       226: aload_2
       227: invokestatic  #879                // Method ghidra/program/util/GhidraProgramUtilities.markProgramAnalyzed:(Lghidra/program/model/listing/Program;)V
       230: goto          347
       233: new           #885                // class ghidra/app/util/headless/HeadlessTimedTaskMonitor
       236: dup
       237: aload_0
       238: getfield      #86                 // Field options:Lghidra/app/util/headless/HeadlessOptions;
       241: getfield      #870                // Field ghidra/app/util/headless/HeadlessOptions.perFileTimeout:I
       244: invokespecial #887                // Method ghidra/app/util/headless/HeadlessTimedTaskMonitor."<init>":(I)V
       247: astore        9
       249: aload_3
       250: aload         9
       252: invokevirtual #874                // Method ghidra/app/plugin/core/analysis/AutoAnalysisManager.startAnalysis:(Lghidra/util/task/TaskMonitor;)V
       255: aload         9
       257: invokevirtual #890                // Method ghidra/app/util/headless/HeadlessTimedTaskMonitor.isCancelled:()Z
       260: ifeq          328
       263: aload_0
       264: aload_0
       265: getfield      #86                 // Field options:Lghidra/app/util/headless/HeadlessOptions;
       268: getfield      #870                // Field ghidra/app/util/headless/HeadlessOptions.perFileTimeout:I
       271: aload_1
       272: invokedynamic #893,  0            // InvokeDynamic #28:makeConcatWithConstants:(ILjava/lang/String;)Ljava/lang/String;
       277: invokestatic  #163                // Method ghidra/util/Msg.error:(Ljava/lang/Object;Ljava/lang/Object;)V
       280: aload_0
       281: getfield      #86                 // Field options:Lghidra/app/util/headless/HeadlessOptions;
       284: getfield      #220                // Field ghidra/app/util/headless/HeadlessOptions.postScripts:Ljava/util/List;
       287: invokeinterface #217,  1          // InterfaceMethod java/util/List.isEmpty:()Z
       292: ifeq          320
       295: iload         7
       297: ifne          304
       300: iconst_1
       301: goto          305
       304: iconst_0
       305: istore        10
       307: aload_2
       308: iload         8
       310: iconst_1
       311: invokeinterface #896,  3          // InterfaceMethod ghidra/program/model/listing/Program.endTransaction:(IZ)Z
       316: pop
       317: iload         10
       319: ireturn
       320: aload_0
       321: iconst_1
       322: putfield      #136                // Field analysisTimedOut:Z
       325: goto          347
       328: aload         9
       330: invokevirtual #900                // Method ghidra/app/util/headless/HeadlessTimedTaskMonitor.cancel:()V
       333: aload_0
       334: aload_1
       335: invokedynamic #878,  0            // InvokeDynamic #27:makeConcatWithConstants:(Ljava/lang/String;)Ljava/lang/String;
       340: invokestatic  #281                // Method ghidra/util/Msg.info:(Ljava/lang/Object;Ljava/lang/Object;)V
       343: aload_2
       344: invokestatic  #879                // Method ghidra/program/util/GhidraProgramUtilities.markProgramAnalyzed:(Lghidra/program/model/listing/Program;)V
       347: aload_2
       348: iload         8
       350: iconst_1
       351: invokeinterface #896,  3          // InterfaceMethod ghidra/program/model/listing/Program.endTransaction:(IZ)Z
       356: pop
       357: goto          375
       360: astore        11
       362: aload_2
       363: iload         8
       365: iconst_1
       366: invokeinterface #896,  3          // InterfaceMethod ghidra/program/model/listing/Program.endTransaction:(IZ)Z
       371: pop
       372: aload         11
       374: athrow
       375: aload_0
       376: getfield      #86                 // Field options:Lghidra/app/util/headless/HeadlessOptions;
       379: getfield      #220                // Field ghidra/app/util/headless/HeadlessOptions.postScripts:Ljava/util/List;
       382: invokeinterface #217,  1          // InterfaceMethod java/util/List.isEmpty:()Z
       387: ifne          590
       390: aload         4
       392: ifnonnull     402
       395: aload_0
       396: aload_2
       397: invokevirtual #837                // Method getInitialProgramState:(Lghidra/program/model/listing/Program;)Lghidra/app/script/GhidraState;
       400: astore        4
       402: aload_0
       403: aload_0
       404: getfield      #86                 // Field options:Lghidra/app/util/headless/HeadlessOptions;
       407: getfield      #220                // Field ghidra/app/util/headless/HeadlessOptions.postScripts:Ljava/util/List;
       410: aload_0
       411: getfield      #86                 // Field options:Lghidra/app/util/headless/HeadlessOptions;
       414: getfield      #695                // Field ghidra/app/util/headless/HeadlessOptions.postScriptFileMap:Ljava/util/Map;
       417: aload         4
       419: aload         5
       421: invokevirtual #841                // Method runScriptsList:(Ljava/util/List;Ljava/util/Map;Lghidra/app/script/GhidraState;Lghidra/app/util/headless/HeadlessScript$HeadlessContinuationOption;)Lghidra/app/util/headless/HeadlessScript$HeadlessContinuationOption;
       424: astore        5
       426: getstatic     #845                // Field ghidra/app/util/headless/HeadlessAnalyzer$3.$SwitchMap$ghidra$app$util$headless$HeadlessScript$HeadlessContinuationOption:[I
       429: aload         5
       431: invokevirtual #851                // Method ghidra/app/util/headless/HeadlessScript$HeadlessContinuationOption.ordinal:()I
       434: iaload
       435: tableswitch   { // 1 to 3
                       1: 460
                       2: 469
                       3: 478
                 default: 484
            }
       460: iconst_1
       461: istore        6
       463: iconst_1
       464: istore        7
       466: goto          484
       469: iconst_0
       470: istore        6
       472: iconst_1
       473: istore        7
       475: goto          484
       478: iconst_1
       479: istore        6
       481: goto          484
       484: iload         6
       486: ifeq          499
       489: aload_0
       490: ldc_w         #903                // String Processing aborted as a result of post-script.
       493: invokestatic  #281                // Method ghidra/util/Msg.info:(Ljava/lang/Object;Ljava/lang/Object;)V
       496: goto          590
       499: aload_0
       500: getfield      #86                 // Field options:Lghidra/app/util/headless/HeadlessOptions;
       503: getfield      #862                // Field ghidra/app/util/headless/HeadlessOptions.analyze:Z
       506: ifeq          590
       509: aload_0
       510: getfield      #86                 // Field options:Lghidra/app/util/headless/HeadlessOptions;
       513: getfield      #220                // Field ghidra/app/util/headless/HeadlessOptions.postScripts:Ljava/util/List;
       516: invokeinterface #217,  1          // InterfaceMethod java/util/List.isEmpty:()Z
       521: ifne          590
       524: aload_0
       525: aload_1
       526: invokedynamic #905,  0            // InvokeDynamic #29:makeConcatWithConstants:(Ljava/lang/String;)Ljava/lang/String;
       531: invokestatic  #281                // Method ghidra/util/Msg.info:(Ljava/lang/Object;Ljava/lang/Object;)V
       534: aload_2
       535: ldc_w         #906                // String Post-Analysis
       538: invokeinterface #858,  2          // InterfaceMethod ghidra/program/model/listing/Program.startTransaction:(Ljava/lang/String;)I
       543: istore        8
       545: aload_3
       546: getstatic     #300                // Field ghidra/util/task/TaskMonitor.DUMMY:Lghidra/util/task/TaskMonitor;
       549: invokevirtual #874                // Method ghidra/app/plugin/core/analysis/AutoAnalysisManager.startAnalysis:(Lghidra/util/task/TaskMonitor;)V
       552: aload_2
       553: iload         8
       555: iconst_1
       556: invokeinterface #896,  3          // InterfaceMethod ghidra/program/model/listing/Program.endTransaction:(IZ)Z
       561: pop
       562: goto          580
       565: astore        12
       567: aload_2
       568: iload         8
       570: iconst_1
       571: invokeinterface #896,  3          // InterfaceMethod ghidra/program/model/listing/Program.endTransaction:(IZ)Z
       576: pop
       577: aload         12
       579: athrow
       580: aload_0
       581: aload_1
       582: invokedynamic #908,  0            // InvokeDynamic #30:makeConcatWithConstants:(Ljava/lang/String;)Ljava/lang/String;
       587: invokestatic  #281                // Method ghidra/util/Msg.info:(Ljava/lang/Object;Ljava/lang/Object;)V
       590: iload         7
       592: ifne          599
       595: iconst_1
       596: goto          600
       599: iconst_0
       600: ireturn
      Exception table:
         from    to  target type
           169   307   360   any
           320   347   360   any
           360   362   360   any
           545   552   565   any
           565   567   565   any

  private void processFileNoImport(ghidra.framework.model.DomainFile) throws java.io.IOException;
    Code:
         0: aload_1
         1: invokeinterface #909,  1          // InterfaceMethod ghidra/framework/model/DomainFile.isHijacked:()Z
         6: ifeq          25
         9: aload_0
        10: aload_1
        11: invokeinterface #914,  1          // InterfaceMethod ghidra/framework/model/DomainFile.getPathname:()Ljava/lang/String;
        16: invokedynamic #915,  0            // InvokeDynamic #31:makeConcatWithConstants:(Ljava/lang/String;)Ljava/lang/String;
        21: invokestatic  #163                // Method ghidra/util/Msg.error:(Ljava/lang/Object;Ljava/lang/Object;)V
        24: return
        25: ldc_w         #918                // String Program
        28: aload_1
        29: invokeinterface #920,  1          // InterfaceMethod ghidra/framework/model/DomainFile.getContentType:()Ljava/lang/String;
        34: invokevirtual #173                // Method java/lang/String.equals:(Ljava/lang/Object;)Z
        37: ifne          41
        40: return
        41: aconst_null
        42: astore_2
        43: iconst_1
        44: istore_3
        45: iconst_0
        46: istore        4
        48: aload_0
        49: getfield      #86                 // Field options:Lghidra/app/util/headless/HeadlessOptions;
        52: getfield      #155                // Field ghidra/app/util/headless/HeadlessOptions.readOnly:Z
        55: ifne          76
        58: aload_1
        59: invokeinterface #923,  1          // InterfaceMethod ghidra/framework/model/DomainFile.isReadOnly:()Z
        64: ifne          76
        67: aload_1
        68: invokeinterface #926,  1          // InterfaceMethod ghidra/framework/model/DomainFile.isInWritableProject:()Z
        73: ifne          80
        76: iconst_1
        77: goto          81
        80: iconst_0
        81: istore        5
        83: iload         5
        85: ifne          411
        88: aload_1
        89: invokeinterface #927,  1          // InterfaceMethod ghidra/framework/model/DomainFile.isVersioned:()Z
        94: ifeq          411
        97: aload_1
        98: invokeinterface #930,  1          // InterfaceMethod ghidra/framework/model/DomainFile.isCheckedOut:()Z
       103: ifne          308
       106: aload_1
       107: invokeinterface #933,  1          // InterfaceMethod ghidra/framework/model/DomainFile.canCheckout:()Z
       112: ifne          199
       115: aload_0
       116: aload_1
       117: invokeinterface #914,  1          // InterfaceMethod ghidra/framework/model/DomainFile.getPathname:()Ljava/lang/String;
       122: invokedynamic #936,  0            // InvokeDynamic #32:makeConcatWithConstants:(Ljava/lang/String;)Ljava/lang/String;
       127: invokestatic  #225                // Method ghidra/util/Msg.warn:(Ljava/lang/Object;Ljava/lang/Object;)V
       130: aload_2
       131: ifnull        150
       134: aload_2
       135: invokestatic  #825                // Method ghidra/app/plugin/core/analysis/AutoAnalysisManager.getAnalysisManager:(Lghidra/program/model/listing/Program;)Lghidra/app/plugin/core/analysis/AutoAnalysisManager;
       138: invokevirtual #937                // Method ghidra/app/plugin/core/analysis/AutoAnalysisManager.dispose:()V
       141: aload_2
       142: aload_0
       143: invokeinterface #940,  2          // InterfaceMethod ghidra/program/model/listing/Program.release:(Ljava/lang/Object;)V
       148: aconst_null
       149: astore_2
       150: iload         5
       152: ifne          198
       155: aload_1
       156: invokeinterface #930,  1          // InterfaceMethod ghidra/framework/model/DomainFile.isCheckedOut:()Z
       161: ifeq          189
       164: iload_3
       165: ifeq          182
       168: iload         4
       170: ifeq          189
       173: aload_1
       174: invokeinterface #944,  1          // InterfaceMethod ghidra/framework/model/DomainFile.modifiedSinceCheckout:()Z
       179: ifne          189
       182: aload_1
       183: iconst_0
       184: invokeinterface #947,  2          // InterfaceMethod ghidra/framework/model/DomainFile.undoCheckout:(Z)V
       189: iload_3
       190: ifne          198
       193: aload_0
       194: aload_1
       195: invokevirtual #950                // Method deleteDomainFile:(Lghidra/framework/model/DomainFile;)V
       198: return
       199: aload_1
       200: aload_0
       201: getfield      #86                 // Field options:Lghidra/app/util/headless/HeadlessOptions;
       204: getfield      #158                // Field ghidra/app/util/headless/HeadlessOptions.commit:Z
       207: getstatic     #300                // Field ghidra/util/task/TaskMonitor.DUMMY:Lghidra/util/task/TaskMonitor;
       210: invokeinterface #954,  3          // InterfaceMethod ghidra/framework/model/DomainFile.checkout:(ZLghidra/util/task/TaskMonitor;)Z
       215: ifne          302
       218: aload_0
       219: aload_1
       220: invokeinterface #914,  1          // InterfaceMethod ghidra/framework/model/DomainFile.getPathname:()Ljava/lang/String;
       225: invokedynamic #958,  0            // InvokeDynamic #33:makeConcatWithConstants:(Ljava/lang/String;)Ljava/lang/String;
       230: invokestatic  #225                // Method ghidra/util/Msg.warn:(Ljava/lang/Object;Ljava/lang/Object;)V
       233: aload_2
       234: ifnull        253
       237: aload_2
       238: invokestatic  #825                // Method ghidra/app/plugin/core/analysis/AutoAnalysisManager.getAnalysisManager:(Lghidra/program/model/listing/Program;)Lghidra/app/plugin/core/analysis/AutoAnalysisManager;
       241: invokevirtual #937                // Method ghidra/app/plugin/core/analysis/AutoAnalysisManager.dispose:()V
       244: aload_2
       245: aload_0
       246: invokeinterface #940,  2          // InterfaceMethod ghidra/program/model/listing/Program.release:(Ljava/lang/Object;)V
       251: aconst_null
       252: astore_2
       253: iload         5
       255: ifne          301
       258: aload_1
       259: invokeinterface #930,  1          // InterfaceMethod ghidra/framework/model/DomainFile.isCheckedOut:()Z
       264: ifeq          292
       267: iload_3
       268: ifeq          285
       271: iload         4
       273: ifeq          292
       276: aload_1
       277: invokeinterface #944,  1          // InterfaceMethod ghidra/framework/model/DomainFile.modifiedSinceCheckout:()Z
       282: ifne          292
       285: aload_1
       286: iconst_0
       287: invokeinterface #947,  2          // InterfaceMethod ghidra/framework/model/DomainFile.undoCheckout:(Z)V
       292: iload_3
       293: ifne          301
       296: aload_0
       297: aload_1
       298: invokevirtual #950                // Method deleteDomainFile:(Lghidra/framework/model/DomainFile;)V
       301: return
       302: iconst_1
       303: istore        4
       305: goto          411
       308: aload_0
       309: getfield      #86                 // Field options:Lghidra/app/util/headless/HeadlessOptions;
       312: getfield      #158                // Field ghidra/app/util/headless/HeadlessOptions.commit:Z
       315: ifeq          411
       318: aload_1
       319: invokeinterface #959,  1          // InterfaceMethod ghidra/framework/model/DomainFile.isCheckedOutExclusive:()Z
       324: ifne          411
       327: aload_0
       328: aload_1
       329: invokeinterface #914,  1          // InterfaceMethod ghidra/framework/model/DomainFile.getPathname:()Ljava/lang/String;
       334: invokedynamic #962,  0            // InvokeDynamic #34:makeConcatWithConstants:(Ljava/lang/String;)Ljava/lang/String;
       339: invokestatic  #163                // Method ghidra/util/Msg.error:(Ljava/lang/Object;Ljava/lang/Object;)V
       342: aload_2
       343: ifnull        362
       346: aload_2
       347: invokestatic  #825                // Method ghidra/app/plugin/core/analysis/AutoAnalysisManager.getAnalysisManager:(Lghidra/program/model/listing/Program;)Lghidra/app/plugin/core/analysis/AutoAnalysisManager;
       350: invokevirtual #937                // Method ghidra/app/plugin/core/analysis/AutoAnalysisManager.dispose:()V
       353: aload_2
       354: aload_0
       355: invokeinterface #940,  2          // InterfaceMethod ghidra/program/model/listing/Program.release:(Ljava/lang/Object;)V
       360: aconst_null
       361: astore_2
       362: iload         5
       364: ifne          410
       367: aload_1
       368: invokeinterface #930,  1          // InterfaceMethod ghidra/framework/model/DomainFile.isCheckedOut:()Z
       373: ifeq          401
       376: iload_3
       377: ifeq          394
       380: iload         4
       382: ifeq          401
       385: aload_1
       386: invokeinterface #944,  1          // InterfaceMethod ghidra/framework/model/DomainFile.modifiedSinceCheckout:()Z
       391: ifne          401
       394: aload_1
       395: iconst_0
       396: invokeinterface #947,  2          // InterfaceMethod ghidra/framework/model/DomainFile.undoCheckout:(Z)V
       401: iload_3
       402: ifne          410
       405: aload_0
       406: aload_1
       407: invokevirtual #950                // Method deleteDomainFile:(Lghidra/framework/model/DomainFile;)V
       410: return
       411: aload_1
       412: aload_0
       413: iconst_1
       414: iconst_0
       415: getstatic     #300                // Field ghidra/util/task/TaskMonitor.DUMMY:Lghidra/util/task/TaskMonitor;
       418: invokeinterface #963,  5          // InterfaceMethod ghidra/framework/model/DomainFile.getDomainObject:(Ljava/lang/Object;ZZLghidra/util/task/TaskMonitor;)Lghidra/framework/model/DomainObject;
       423: checkcast     #797                // class ghidra/program/model/listing/Program
       426: astore_2
       427: iload         5
       429: ifeq          438
       432: ldc_w         #967                // String read-only
       435: goto          441
       438: ldc_w         #352                // String
       441: astore        6
       443: aload_0
       444: aload         6
       446: aload_1
       447: invokeinterface #914,  1          // InterfaceMethod ghidra/framework/model/DomainFile.getPathname:()Ljava/lang/String;
       452: invokedynamic #969,  0            // InvokeDynamic #35:makeConcatWithConstants:(Ljava/lang/String;Ljava/lang/String;)Ljava/lang/String;
       457: invokestatic  #281                // Method ghidra/util/Msg.info:(Ljava/lang/Object;Ljava/lang/Object;)V
       460: aload_0
       461: aload_1
       462: invokeinterface #914,  1          // InterfaceMethod ghidra/framework/model/DomainFile.getPathname:()Ljava/lang/String;
       467: aload_2
       468: invokevirtual #970                // Method analyzeProgram:(Ljava/lang/String;Lghidra/program/model/listing/Program;)Z
       471: ifne          479
       474: iload         5
       476: ifeq          483
       479: iconst_1
       480: goto          484
       483: iconst_0
       484: istore_3
       485: iload_3
       486: ifne          523
       489: aload_2
       490: iconst_1
       491: invokeinterface #974,  2          // InterfaceMethod ghidra/program/model/listing/Program.setTemporary:(Z)V
       496: aload_0
       497: getfield      #86                 // Field options:Lghidra/app/util/headless/HeadlessOptions;
       500: getfield      #497                // Field ghidra/app/util/headless/HeadlessOptions.okToDelete:Z
       503: ifne          523
       506: aload_0
       507: aload_1
       508: invokeinterface #914,  1          // InterfaceMethod ghidra/framework/model/DomainFile.getPathname:()Ljava/lang/String;
       513: invokedynamic #977,  0            // InvokeDynamic #36:makeConcatWithConstants:(Ljava/lang/String;)Ljava/lang/String;
       518: invokestatic  #225                // Method ghidra/util/Msg.warn:(Ljava/lang/Object;Ljava/lang/Object;)V
       521: iconst_1
       522: istore_3
       523: iload         5
       525: ifeq          621
       528: aload_2
       529: invokeinterface #978,  1          // InterfaceMethod ghidra/program/model/listing/Program.isChanged:()Z
       534: ifeq          552
       537: aload_0
       538: aload_1
       539: invokeinterface #914,  1          // InterfaceMethod ghidra/framework/model/DomainFile.getPathname:()Ljava/lang/String;
       544: invokedynamic #981,  0            // InvokeDynamic #37:makeConcatWithConstants:(Ljava/lang/String;)Ljava/lang/String;
       549: invokestatic  #281                // Method ghidra/util/Msg.info:(Ljava/lang/Object;Ljava/lang/Object;)V
       552: aload_2
       553: ifnull        572
       556: aload_2
       557: invokestatic  #825                // Method ghidra/app/plugin/core/analysis/AutoAnalysisManager.getAnalysisManager:(Lghidra/program/model/listing/Program;)Lghidra/app/plugin/core/analysis/AutoAnalysisManager;
       560: invokevirtual #937                // Method ghidra/app/plugin/core/analysis/AutoAnalysisManager.dispose:()V
       563: aload_2
       564: aload_0
       565: invokeinterface #940,  2          // InterfaceMethod ghidra/program/model/listing/Program.release:(Ljava/lang/Object;)V
       570: aconst_null
       571: astore_2
       572: iload         5
       574: ifne          620
       577: aload_1
       578: invokeinterface #930,  1          // InterfaceMethod ghidra/framework/model/DomainFile.isCheckedOut:()Z
       583: ifeq          611
       586: iload_3
       587: ifeq          604
       590: iload         4
       592: ifeq          611
       595: aload_1
       596: invokeinterface #944,  1          // InterfaceMethod ghidra/framework/model/DomainFile.modifiedSinceCheckout:()Z
       601: ifne          611
       604: aload_1
       605: iconst_0
       606: invokeinterface #947,  2          // InterfaceMethod ghidra/framework/model/DomainFile.undoCheckout:(Z)V
       611: iload_3
       612: ifne          620
       615: aload_0
       616: aload_1
       617: invokevirtual #950                // Method deleteDomainFile:(Lghidra/framework/model/DomainFile;)V
       620: return
       621: aload_2
       622: invokeinterface #982,  1          // InterfaceMethod ghidra/program/model/listing/Program.isTemporary:()Z
       627: ifeq          723
       630: aload_2
       631: invokeinterface #978,  1          // InterfaceMethod ghidra/program/model/listing/Program.isChanged:()Z
       636: ifeq          654
       639: aload_0
       640: aload_1
       641: invokeinterface #914,  1          // InterfaceMethod ghidra/framework/model/DomainFile.getPathname:()Ljava/lang/String;
       646: invokedynamic #985,  0            // InvokeDynamic #38:makeConcatWithConstants:(Ljava/lang/String;)Ljava/lang/String;
       651: invokestatic  #281                // Method ghidra/util/Msg.info:(Ljava/lang/Object;Ljava/lang/Object;)V
       654: aload_2
       655: ifnull        674
       658: aload_2
       659: invokestatic  #825                // Method ghidra/app/plugin/core/analysis/AutoAnalysisManager.getAnalysisManager:(Lghidra/program/model/listing/Program;)Lghidra/app/plugin/core/analysis/AutoAnalysisManager;
       662: invokevirtual #937                // Method ghidra/app/plugin/core/analysis/AutoAnalysisManager.dispose:()V
       665: aload_2
       666: aload_0
       667: invokeinterface #940,  2          // InterfaceMethod ghidra/program/model/listing/Program.release:(Ljava/lang/Object;)V
       672: aconst_null
       673: astore_2
       674: iload         5
       676: ifne          722
       679: aload_1
       680: invokeinterface #930,  1          // InterfaceMethod ghidra/framework/model/DomainFile.isCheckedOut:()Z
       685: ifeq          713
       688: iload_3
       689: ifeq          706
       692: iload         4
       694: ifeq          713
       697: aload_1
       698: invokeinterface #944,  1          // InterfaceMethod ghidra/framework/model/DomainFile.modifiedSinceCheckout:()Z
       703: ifne          713
       706: aload_1
       707: iconst_0
       708: invokeinterface #947,  2          // InterfaceMethod ghidra/framework/model/DomainFile.undoCheckout:(Z)V
       713: iload_3
       714: ifne          722
       717: aload_0
       718: aload_1
       719: invokevirtual #950                // Method deleteDomainFile:(Lghidra/framework/model/DomainFile;)V
       722: return
       723: aload_1
       724: invokeinterface #986,  1          // InterfaceMethod ghidra/framework/model/DomainFile.canSave:()Z
       729: ifeq          756
       732: aload_1
       733: getstatic     #300                // Field ghidra/util/task/TaskMonitor.DUMMY:Lghidra/util/task/TaskMonitor;
       736: invokeinterface #989,  2          // InterfaceMethod ghidra/framework/model/DomainFile.save:(Lghidra/util/task/TaskMonitor;)V
       741: aload_0
       742: aload_1
       743: invokeinterface #914,  1          // InterfaceMethod ghidra/framework/model/DomainFile.getPathname:()Ljava/lang/String;
       748: invokedynamic #992,  0            // InvokeDynamic #39:makeConcatWithConstants:(Ljava/lang/String;)Ljava/lang/String;
       753: invokestatic  #281                // Method ghidra/util/Msg.info:(Ljava/lang/Object;Ljava/lang/Object;)V
       756: aload_2
       757: invokeinterface #978,  1          // InterfaceMethod ghidra/program/model/listing/Program.isChanged:()Z
       762: ifeq          780
       765: aload_0
       766: aload_1
       767: invokeinterface #914,  1          // InterfaceMethod ghidra/framework/model/DomainFile.getPathname:()Ljava/lang/String;
       772: invokedynamic #993,  0            // InvokeDynamic #40:makeConcatWithConstants:(Ljava/lang/String;)Ljava/lang/String;
       777: invokestatic  #163                // Method ghidra/util/Msg.error:(Ljava/lang/Object;Ljava/lang/Object;)V
       780: aload_0
       781: getfield      #86                 // Field options:Lghidra/app/util/headless/HeadlessOptions;
       784: getfield      #158                // Field ghidra/app/util/headless/HeadlessOptions.commit:Z
       787: ifeq          811
       790: aload_2
       791: invokestatic  #825                // Method ghidra/app/plugin/core/analysis/AutoAnalysisManager.getAnalysisManager:(Lghidra/program/model/listing/Program;)Lghidra/app/plugin/core/analysis/AutoAnalysisManager;
       794: invokevirtual #937                // Method ghidra/app/plugin/core/analysis/AutoAnalysisManager.dispose:()V
       797: aload_2
       798: aload_0
       799: invokeinterface #940,  2          // InterfaceMethod ghidra/program/model/listing/Program.release:(Ljava/lang/Object;)V
       804: aconst_null
       805: astore_2
       806: aload_0
       807: aload_1
       808: invokevirtual #994                // Method commitProgram:(Lghidra/framework/model/DomainFile;)V
       811: aload_2
       812: ifnull        831
       815: aload_2
       816: invokestatic  #825                // Method ghidra/app/plugin/core/analysis/AutoAnalysisManager.getAnalysisManager:(Lghidra/program/model/listing/Program;)Lghidra/app/plugin/core/analysis/AutoAnalysisManager;
       819: invokevirtual #937                // Method ghidra/app/plugin/core/analysis/AutoAnalysisManager.dispose:()V
       822: aload_2
       823: aload_0
       824: invokeinterface #940,  2          // InterfaceMethod ghidra/program/model/listing/Program.release:(Ljava/lang/Object;)V
       829: aconst_null
       830: astore_2
       831: iload         5
       833: ifne          1237
       836: aload_1
       837: invokeinterface #930,  1          // InterfaceMethod ghidra/framework/model/DomainFile.isCheckedOut:()Z
       842: ifeq          870
       845: iload_3
       846: ifeq          863
       849: iload         4
       851: ifeq          870
       854: aload_1
       855: invokeinterface #944,  1          // InterfaceMethod ghidra/framework/model/DomainFile.modifiedSinceCheckout:()Z
       860: ifne          870
       863: aload_1
       864: iconst_0
       865: invokeinterface #947,  2          // InterfaceMethod ghidra/framework/model/DomainFile.undoCheckout:(Z)V
       870: iload_3
       871: ifne          1237
       874: aload_0
       875: aload_1
       876: invokevirtual #950                // Method deleteDomainFile:(Lghidra/framework/model/DomainFile;)V
       879: goto          1237
       882: astore        6
       884: aload         6
       886: invokevirtual #999                // Method ghidra/util/exception/VersionException.isUpgradable:()Z
       889: ifeq          910
       892: aload_0
       893: aload_1
       894: invokeinterface #914,  1          // InterfaceMethod ghidra/framework/model/DomainFile.getPathname:()Ljava/lang/String;
       899: invokedynamic #1002,  0           // InvokeDynamic #41:makeConcatWithConstants:(Ljava/lang/String;)Ljava/lang/String;
       904: invokestatic  #163                // Method ghidra/util/Msg.error:(Ljava/lang/Object;Ljava/lang/Object;)V
       907: goto          925
       910: aload_0
       911: aload_1
       912: invokeinterface #914,  1          // InterfaceMethod ghidra/framework/model/DomainFile.getPathname:()Ljava/lang/String;
       917: invokedynamic #1003,  0           // InvokeDynamic #42:makeConcatWithConstants:(Ljava/lang/String;)Ljava/lang/String;
       922: invokestatic  #163                // Method ghidra/util/Msg.error:(Ljava/lang/Object;Ljava/lang/Object;)V
       925: aload_2
       926: ifnull        945
       929: aload_2
       930: invokestatic  #825                // Method ghidra/app/plugin/core/analysis/AutoAnalysisManager.getAnalysisManager:(Lghidra/program/model/listing/Program;)Lghidra/app/plugin/core/analysis/AutoAnalysisManager;
       933: invokevirtual #937                // Method ghidra/app/plugin/core/analysis/AutoAnalysisManager.dispose:()V
       936: aload_2
       937: aload_0
       938: invokeinterface #940,  2          // InterfaceMethod ghidra/program/model/listing/Program.release:(Ljava/lang/Object;)V
       943: aconst_null
       944: astore_2
       945: iload         5
       947: ifne          1237
       950: aload_1
       951: invokeinterface #930,  1          // InterfaceMethod ghidra/framework/model/DomainFile.isCheckedOut:()Z
       956: ifeq          984
       959: iload_3
       960: ifeq          977
       963: iload         4
       965: ifeq          984
       968: aload_1
       969: invokeinterface #944,  1          // InterfaceMethod ghidra/framework/model/DomainFile.modifiedSinceCheckout:()Z
       974: ifne          984
       977: aload_1
       978: iconst_0
       979: invokeinterface #947,  2          // InterfaceMethod ghidra/framework/model/DomainFile.undoCheckout:(Z)V
       984: iload_3
       985: ifne          1237
       988: aload_0
       989: aload_1
       990: invokevirtual #950                // Method deleteDomainFile:(Lghidra/framework/model/DomainFile;)V
       993: goto          1237
       996: astore        6
       998: aload_2
       999: ifnull        1018
      1002: aload_2
      1003: invokestatic  #825                // Method ghidra/app/plugin/core/analysis/AutoAnalysisManager.getAnalysisManager:(Lghidra/program/model/listing/Program;)Lghidra/app/plugin/core/analysis/AutoAnalysisManager;
      1006: invokevirtual #937                // Method ghidra/app/plugin/core/analysis/AutoAnalysisManager.dispose:()V
      1009: aload_2
      1010: aload_0
      1011: invokeinterface #940,  2          // InterfaceMethod ghidra/program/model/listing/Program.release:(Ljava/lang/Object;)V
      1016: aconst_null
      1017: astore_2
      1018: iload         5
      1020: ifne          1237
      1023: aload_1
      1024: invokeinterface #930,  1          // InterfaceMethod ghidra/framework/model/DomainFile.isCheckedOut:()Z
      1029: ifeq          1057
      1032: iload_3
      1033: ifeq          1050
      1036: iload         4
      1038: ifeq          1057
      1041: aload_1
      1042: invokeinterface #944,  1          // InterfaceMethod ghidra/framework/model/DomainFile.modifiedSinceCheckout:()Z
      1047: ifne          1057
      1050: aload_1
      1051: iconst_0
      1052: invokeinterface #947,  2          // InterfaceMethod ghidra/framework/model/DomainFile.undoCheckout:(Z)V
      1057: iload_3
      1058: ifne          1237
      1061: aload_0
      1062: aload_1
      1063: invokevirtual #950                // Method deleteDomainFile:(Lghidra/framework/model/DomainFile;)V
      1066: goto          1237
      1069: astore        6
      1071: aload_0
      1072: aload_1
      1073: invokeinterface #914,  1          // InterfaceMethod ghidra/framework/model/DomainFile.getPathname:()Ljava/lang/String;
      1078: aload         6
      1080: invokevirtual #795                // Method java/lang/Exception.getMessage:()Ljava/lang/String;
      1083: invokedynamic #1004,  0           // InvokeDynamic #43:makeConcatWithConstants:(Ljava/lang/String;Ljava/lang/String;)Ljava/lang/String;
      1088: aload         6
      1090: invokestatic  #491                // Method ghidra/util/Msg.error:(Ljava/lang/Object;Ljava/lang/Object;Ljava/lang/Throwable;)V
      1093: aload_2
      1094: ifnull        1113
      1097: aload_2
      1098: invokestatic  #825                // Method ghidra/app/plugin/core/analysis/AutoAnalysisManager.getAnalysisManager:(Lghidra/program/model/listing/Program;)Lghidra/app/plugin/core/analysis/AutoAnalysisManager;
      1101: invokevirtual #937                // Method ghidra/app/plugin/core/analysis/AutoAnalysisManager.dispose:()V
      1104: aload_2
      1105: aload_0
      1106: invokeinterface #940,  2          // InterfaceMethod ghidra/program/model/listing/Program.release:(Ljava/lang/Object;)V
      1111: aconst_null
      1112: astore_2
      1113: iload         5
      1115: ifne          1237
      1118: aload_1
      1119: invokeinterface #930,  1          // InterfaceMethod ghidra/framework/model/DomainFile.isCheckedOut:()Z
      1124: ifeq          1152
      1127: iload_3
      1128: ifeq          1145
      1131: iload         4
      1133: ifeq          1152
      1136: aload_1
      1137: invokeinterface #944,  1          // InterfaceMethod ghidra/framework/model/DomainFile.modifiedSinceCheckout:()Z
      1142: ifne          1152
      1145: aload_1
      1146: iconst_0
      1147: invokeinterface #947,  2          // InterfaceMethod ghidra/framework/model/DomainFile.undoCheckout:(Z)V
      1152: iload_3
      1153: ifne          1237
      1156: aload_0
      1157: aload_1
      1158: invokevirtual #950                // Method deleteDomainFile:(Lghidra/framework/model/DomainFile;)V
      1161: goto          1237
      1164: astore        7
      1166: aload_2
      1167: ifnull        1186
      1170: aload_2
      1171: invokestatic  #825                // Method ghidra/app/plugin/core/analysis/AutoAnalysisManager.getAnalysisManager:(Lghidra/program/model/listing/Program;)Lghidra/app/plugin/core/analysis/AutoAnalysisManager;
      1174: invokevirtual #937                // Method ghidra/app/plugin/core/analysis/AutoAnalysisManager.dispose:()V
      1177: aload_2
      1178: aload_0
      1179: invokeinterface #940,  2          // InterfaceMethod ghidra/program/model/listing/Program.release:(Ljava/lang/Object;)V
      1184: aconst_null
      1185: astore_2
      1186: iload         5
      1188: ifne          1234
      1191: aload_1
      1192: invokeinterface #930,  1          // InterfaceMethod ghidra/framework/model/DomainFile.isCheckedOut:()Z
      1197: ifeq          1225
      1200: iload_3
      1201: ifeq          1218
      1204: iload         4
      1206: ifeq          1225
      1209: aload_1
      1210: invokeinterface #944,  1          // InterfaceMethod ghidra/framework/model/DomainFile.modifiedSinceCheckout:()Z
      1215: ifne          1225
      1218: aload_1
      1219: iconst_0
      1220: invokeinterface #947,  2          // InterfaceMethod ghidra/framework/model/DomainFile.undoCheckout:(Z)V
      1225: iload_3
      1226: ifne          1234
      1229: aload_0
      1230: aload_1
      1231: invokevirtual #950                // Method deleteDomainFile:(Lghidra/framework/model/DomainFile;)V
      1234: aload         7
      1236: athrow
      1237: return
      Exception table:
         from    to  target type
            83   130   882   Class ghidra/util/exception/VersionException
           199   233   882   Class ghidra/util/exception/VersionException
           302   342   882   Class ghidra/util/exception/VersionException
           411   552   882   Class ghidra/util/exception/VersionException
           621   654   882   Class ghidra/util/exception/VersionException
           723   811   882   Class ghidra/util/exception/VersionException
            83   130   996   Class ghidra/util/exception/CancelledException
           199   233   996   Class ghidra/util/exception/CancelledException
           302   342   996   Class ghidra/util/exception/CancelledException
           411   552   996   Class ghidra/util/exception/CancelledException
           621   654   996   Class ghidra/util/exception/CancelledException
           723   811   996   Class ghidra/util/exception/CancelledException
            83   130  1069   Class java/lang/Exception
           199   233  1069   Class java/lang/Exception
           302   342  1069   Class java/lang/Exception
           411   552  1069   Class java/lang/Exception
           621   654  1069   Class java/lang/Exception
           723   811  1069   Class java/lang/Exception
            83   130  1164   any
           199   233  1164   any
           302   342  1164   any
           411   552  1164   any
           621   654  1164   any
           723   811  1164   any
           882   925  1164   any
           996   998  1164   any
          1069  1093  1164   any
          1164  1166  1164   any

  private void deleteDomainFile(ghidra.framework.model.DomainFile);
    Code:
         0: aload_1
         1: invokeinterface #930,  1          // InterfaceMethod ghidra/framework/model/DomainFile.isCheckedOut:()Z
         6: ifeq          25
         9: aload_0
        10: aload_1
        11: invokeinterface #914,  1          // InterfaceMethod ghidra/framework/model/DomainFile.getPathname:()Ljava/lang/String;
        16: invokedynamic #1005,  0           // InvokeDynamic #44:makeConcatWithConstants:(Ljava/lang/String;)Ljava/lang/String;
        21: invokestatic  #163                // Method ghidra/util/Msg.error:(Ljava/lang/Object;Ljava/lang/Object;)V
        24: return
        25: aload_1
        26: invokeinterface #1006,  1         // InterfaceMethod ghidra/framework/model/DomainFile.delete:()V
        31: goto          54
        34: astore_2
        35: aload_0
        36: aload_2
        37: invokevirtual #65                 // Method java/io/IOException.getMessage:()Ljava/lang/String;
        40: aload_1
        41: invokeinterface #914,  1          // InterfaceMethod ghidra/framework/model/DomainFile.getPathname:()Ljava/lang/String;
        46: invokedynamic #1008,  0           // InvokeDynamic #45:makeConcatWithConstants:(Ljava/lang/String;Ljava/lang/String;)Ljava/lang/String;
        51: invokestatic  #163                // Method ghidra/util/Msg.error:(Ljava/lang/Object;Ljava/lang/Object;)V
        54: return
      Exception table:
         from    to  target type
            25    31    34   Class java/io/IOException

  private boolean processFolderNoImport(ghidra.framework.model.DomainFolder, java.util.regex.Pattern) throws java.io.IOException;
    Code:
         0: aload_1
         1: invokeinterface #1009,  1         // InterfaceMethod ghidra/framework/model/DomainFolder.isEmpty:()Z
         6: ifeq          11
         9: iconst_0
        10: ireturn
        11: iconst_0
        12: istore_3
        13: aload_1
        14: invokeinterface #1010,  1         // InterfaceMethod ghidra/framework/model/DomainFolder.getFiles:()[Lghidra/framework/model/DomainFile;
        19: astore        4
        21: aload         4
        23: arraylength
        24: istore        5
        26: iconst_0
        27: istore        6
        29: iload         6
        31: iload         5
        33: if_icmpge     94
        36: aload         4
        38: iload         6
        40: aaload
        41: astore        7
        43: aload_2
        44: ifnull        64
        47: aload_2
        48: aload         7
        50: invokeinterface #1014,  1         // InterfaceMethod ghidra/framework/model/DomainFile.getName:()Ljava/lang/String;
        55: invokevirtual #1015               // Method java/util/regex/Pattern.matcher:(Ljava/lang/CharSequence;)Ljava/util/regex/Matcher;
        58: invokevirtual #1021               // Method java/util/regex/Matcher.matches:()Z
        61: ifeq          88
        64: ldc_w         #918                // String Program
        67: aload         7
        69: invokeinterface #920,  1          // InterfaceMethod ghidra/framework/model/DomainFile.getContentType:()Ljava/lang/String;
        74: invokevirtual #173                // Method java/lang/String.equals:(Ljava/lang/Object;)Z
        77: ifeq          88
        80: iconst_1
        81: istore_3
        82: aload_0
        83: aload         7
        85: invokevirtual #1026               // Method processFileNoImport:(Lghidra/framework/model/DomainFile;)V
        88: iinc          6, 1
        91: goto          29
        94: aload_0
        95: getfield      #86                 // Field options:Lghidra/app/util/headless/HeadlessOptions;
        98: getfield      #1029               // Field ghidra/app/util/headless/HeadlessOptions.recursive:Z
       101: ifeq          150
       104: aload_1
       105: invokeinterface #1032,  1         // InterfaceMethod ghidra/framework/model/DomainFolder.getFolders:()[Lghidra/framework/model/DomainFolder;
       110: astore        4
       112: aload         4
       114: arraylength
       115: istore        5
       117: iconst_0
       118: istore        6
       120: iload         6
       122: iload         5
       124: if_icmpge     150
       127: aload         4
       129: iload         6
       131: aaload
       132: astore        7
       134: iload_3
       135: aload_0
       136: aload         7
       138: aload_2
       139: invokevirtual #1036               // Method processFolderNoImport:(Lghidra/framework/model/DomainFolder;Ljava/util/regex/Pattern;)Z
       142: ior
       143: istore_3
       144: iinc          6, 1
       147: goto          120
       150: iload_3
       151: ireturn

  private boolean processFolderNoImport(ghidra.framework.model.DomainFolder, java.lang.String) throws java.io.IOException;
    Code:
         0: aload_1
         1: invokeinterface #1009,  1         // InterfaceMethod ghidra/framework/model/DomainFolder.isEmpty:()Z
         6: ifeq          11
         9: iconst_0
        10: ireturn
        11: iconst_0
        12: istore_3
        13: aload_1
        14: aload_2
        15: invokeinterface #1040,  2         // InterfaceMethod ghidra/framework/model/DomainFolder.getFile:(Ljava/lang/String;)Lghidra/framework/model/DomainFile;
        20: astore        4
        22: aload         4
        24: ifnull        51
        27: ldc_w         #918                // String Program
        30: aload         4
        32: invokeinterface #920,  1          // InterfaceMethod ghidra/framework/model/DomainFile.getContentType:()Ljava/lang/String;
        37: invokevirtual #173                // Method java/lang/String.equals:(Ljava/lang/Object;)Z
        40: ifeq          51
        43: iconst_1
        44: istore_3
        45: aload_0
        46: aload         4
        48: invokevirtual #1026               // Method processFileNoImport:(Lghidra/framework/model/DomainFile;)V
        51: aload_0
        52: getfield      #86                 // Field options:Lghidra/app/util/headless/HeadlessOptions;
        55: getfield      #1029               // Field ghidra/app/util/headless/HeadlessOptions.recursive:Z
        58: ifeq          107
        61: aload_1
        62: invokeinterface #1032,  1         // InterfaceMethod ghidra/framework/model/DomainFolder.getFolders:()[Lghidra/framework/model/DomainFolder;
        67: astore        5
        69: aload         5
        71: arraylength
        72: istore        6
        74: iconst_0
        75: istore        7
        77: iload         7
        79: iload         6
        81: if_icmpge     107
        84: aload         5
        86: iload         7
        88: aaload
        89: astore        8
        91: iload_3
        92: aload_0
        93: aload         8
        95: aload_2
        96: invokevirtual #1044               // Method processFolderNoImport:(Lghidra/framework/model/DomainFolder;Ljava/lang/String;)Z
        99: ior
       100: istore_3
       101: iinc          7, 1
       104: goto          77
       107: iload_3
       108: ireturn

  private void processNoImport(java.lang.String) throws java.io.IOException;
    Code:
         0: aload_0
         1: getfield      #147                // Field storage:Ljava/util/Map;
         4: invokeinterface #1047,  1         // InterfaceMethod java/util/Map.clear:()V
         9: aload_0
        10: getfield      #132                // Field project:Lghidra/framework/model/Project;
        13: invokeinterface #418,  1          // InterfaceMethod ghidra/framework/model/Project.getProjectData:()Lghidra/framework/model/ProjectData;
        18: aload_1
        19: invokeinterface #422,  2          // InterfaceMethod ghidra/framework/model/ProjectData.getFolder:(Ljava/lang/String;)Lghidra/framework/model/DomainFolder;
        24: astore_2
        25: aload_2
        26: ifnonnull     43
        29: new           #63                 // class java/io/IOException
        32: dup
        33: aload_1
        34: invokedynamic #1048,  0           // InvokeDynamic #46:makeConcatWithConstants:(Ljava/lang/String;)Ljava/lang/String;
        39: invokespecial #346                // Method java/io/IOException."<init>":(Ljava/lang/String;)V
        42: athrow
        43: aconst_null
        44: astore_3
        45: aload_0
        46: getfield      #86                 // Field options:Lghidra/app/util/headless/HeadlessOptions;
        49: getfield      #1049               // Field ghidra/app/util/headless/HeadlessOptions.domainFileNameToProcess:Ljava/lang/String;
        52: ifnull        67
        55: aload_0
        56: aload_0
        57: getfield      #86                 // Field options:Lghidra/app/util/headless/HeadlessOptions;
        60: getfield      #1049               // Field ghidra/app/util/headless/HeadlessOptions.domainFileNameToProcess:Ljava/lang/String;
        63: invokevirtual #1053               // Method createFilenamePattern:(Ljava/lang/String;)Ljava/util/regex/Pattern;
        66: astore_3
        67: iconst_0
        68: istore        4
        70: aload_3
        71: ifnonnull     101
        74: aload_0
        75: getfield      #86                 // Field options:Lghidra/app/util/headless/HeadlessOptions;
        78: getfield      #1049               // Field ghidra/app/util/headless/HeadlessOptions.domainFileNameToProcess:Ljava/lang/String;
        81: ifnull        101
        84: aload_0
        85: aload_2
        86: aload_0
        87: getfield      #86                 // Field options:Lghidra/app/util/headless/HeadlessOptions;
        90: getfield      #1049               // Field ghidra/app/util/headless/HeadlessOptions.domainFileNameToProcess:Ljava/lang/String;
        93: invokevirtual #1044               // Method processFolderNoImport:(Lghidra/framework/model/DomainFolder;Ljava/lang/String;)Z
        96: istore        4
        98: goto          109
       101: aload_0
       102: aload_2
       103: aload_3
       104: invokevirtual #1036               // Method processFolderNoImport:(Lghidra/framework/model/DomainFolder;Ljava/util/regex/Pattern;)Z
       107: istore        4
       109: iload         4
       111: ifne          163
       114: aload_0
       115: getfield      #86                 // Field options:Lghidra/app/util/headless/HeadlessOptions;
       118: getfield      #1049               // Field ghidra/app/util/headless/HeadlessOptions.domainFileNameToProcess:Ljava/lang/String;
       121: ifnull        144
       124: new           #63                 // class java/io/IOException
       127: dup
       128: aload_0
       129: getfield      #86                 // Field options:Lghidra/app/util/headless/HeadlessOptions;
       132: getfield      #1049               // Field ghidra/app/util/headless/HeadlessOptions.domainFileNameToProcess:Ljava/lang/String;
       135: invokedynamic #1057,  0           // InvokeDynamic #47:makeConcatWithConstants:(Ljava/lang/String;)Ljava/lang/String;
       140: invokespecial #346                // Method java/io/IOException."<init>":(Ljava/lang/String;)V
       143: athrow
       144: new           #63                 // class java/io/IOException
       147: dup
       148: aload_2
       149: invokeinterface #393,  1          // InterfaceMethod ghidra/framework/model/DomainFolder.getPathname:()Ljava/lang/String;
       154: invokedynamic #1058,  0           // InvokeDynamic #48:makeConcatWithConstants:(Ljava/lang/String;)Ljava/lang/String;
       159: invokespecial #346                // Method java/io/IOException."<init>":(Ljava/lang/String;)V
       162: athrow
       163: return

  private java.util.regex.Pattern createFilenamePattern(java.lang.String);
    Code:
         0: aload_1
         1: bipush        42
         3: invokevirtual #1059               // Method java/lang/String.indexOf:(I)I
         6: iconst_m1
         7: if_icmpne     22
        10: aload_1
        11: bipush        63
        13: invokevirtual #1059               // Method java/lang/String.indexOf:(I)I
        16: iconst_m1
        17: if_icmpne     22
        20: aconst_null
        21: areturn
        22: aload_1
        23: ldc_w         #706                // String \'
        26: invokevirtual #1063               // Method java/lang/String.startsWith:(Ljava/lang/String;)Z
        29: ifeq          54
        32: aload_1
        33: ldc_w         #706                // String \'
        36: invokevirtual #230                // Method java/lang/String.endsWith:(Ljava/lang/String;)Z
        39: ifeq          54
        42: aload_1
        43: iconst_1
        44: aload_1
        45: invokevirtual #201                // Method java/lang/String.length:()I
        48: iconst_1
        49: isub
        50: invokevirtual #250                // Method java/lang/String.substring:(II)Ljava/lang/String;
        53: astore_1
        54: aload_1
        55: iconst_1
        56: invokestatic  #1066               // Method ghidra/util/UserSearchUtils.createSearchPattern:(Ljava/lang/String;Z)Ljava/util/regex/Pattern;
        59: astore_2
        60: aload_2
        61: areturn

  private boolean checkOverwrite(ghidra.app.util.opinion.Loaded<ghidra.program.model.listing.Program>) throws java.io.IOException;
    Code:
         0: aload_0
         1: getfield      #132                // Field project:Lghidra/framework/model/Project;
         4: invokeinterface #418,  1          // InterfaceMethod ghidra/framework/model/Project.getProjectData:()Lghidra/framework/model/ProjectData;
         9: aload_1
        10: invokevirtual #1072               // Method ghidra/app/util/opinion/Loaded.getProjectFolderPath:()Ljava/lang/String;
        13: invokeinterface #422,  2          // InterfaceMethod ghidra/framework/model/ProjectData.getFolder:(Ljava/lang/String;)Lghidra/framework/model/DomainFolder;
        18: astore_2
        19: aload_2
        20: ifnonnull     25
        23: iconst_1
        24: ireturn
        25: aload_2
        26: aload_1
        27: invokevirtual #1077               // Method ghidra/app/util/opinion/Loaded.getName:()Ljava/lang/String;
        30: invokeinterface #1040,  2         // InterfaceMethod ghidra/framework/model/DomainFolder.getFile:(Ljava/lang/String;)Lghidra/framework/model/DomainFile;
        35: astore_3
        36: aload_3
        37: ifnonnull     42
        40: iconst_1
        41: ireturn
        42: aload_0
        43: getfield      #86                 // Field options:Lghidra/app/util/headless/HeadlessOptions;
        46: getfield      #520                // Field ghidra/app/util/headless/HeadlessOptions.overwrite:Z
        49: ifeq          203
        52: aload_3
        53: invokeinterface #909,  1          // InterfaceMethod ghidra/framework/model/DomainFile.isHijacked:()Z
        58: ifeq          78
        61: aload_0
        62: aload_3
        63: invokeinterface #914,  1          // InterfaceMethod ghidra/framework/model/DomainFile.getPathname:()Ljava/lang/String;
        68: invokedynamic #1078,  0           // InvokeDynamic #49:makeConcatWithConstants:(Ljava/lang/String;)Ljava/lang/String;
        73: invokestatic  #163                // Method ghidra/util/Msg.error:(Ljava/lang/Object;Ljava/lang/Object;)V
        76: iconst_0
        77: ireturn
        78: aload_3
        79: invokeinterface #927,  1          // InterfaceMethod ghidra/framework/model/DomainFile.isVersioned:()Z
        84: ifeq          130
        87: aload_0
        88: getfield      #86                 // Field options:Lghidra/app/util/headless/HeadlessOptions;
        91: getfield      #158                // Field ghidra/app/util/headless/HeadlessOptions.commit:Z
        94: ifne          114
        97: aload_0
        98: aload_3
        99: invokeinterface #914,  1          // InterfaceMethod ghidra/framework/model/DomainFile.getPathname:()Ljava/lang/String;
       104: invokedynamic #1079,  0           // InvokeDynamic #50:makeConcatWithConstants:(Ljava/lang/String;)Ljava/lang/String;
       109: invokestatic  #163                // Method ghidra/util/Msg.error:(Ljava/lang/Object;Ljava/lang/Object;)V
       112: iconst_0
       113: ireturn
       114: aload_3
       115: invokeinterface #930,  1          // InterfaceMethod ghidra/framework/model/DomainFile.isCheckedOut:()Z
       120: ifeq          130
       123: aload_3
       124: iconst_0
       125: invokeinterface #947,  2          // InterfaceMethod ghidra/framework/model/DomainFile.undoCheckout:(Z)V
       130: aload_3
       131: invokeinterface #1006,  1         // InterfaceMethod ghidra/framework/model/DomainFile.delete:()V
       136: goto          163
       139: astore        4
       141: aload_0
       142: aload         4
       144: invokevirtual #65                 // Method java/io/IOException.getMessage:()Ljava/lang/String;
       147: aload_3
       148: invokeinterface #914,  1          // InterfaceMethod ghidra/framework/model/DomainFile.getPathname:()Ljava/lang/String;
       153: invokedynamic #1080,  0           // InvokeDynamic #51:makeConcatWithConstants:(Ljava/lang/String;Ljava/lang/String;)Ljava/lang/String;
       158: invokestatic  #163                // Method ghidra/util/Msg.error:(Ljava/lang/Object;Ljava/lang/Object;)V
       161: iconst_0
       162: ireturn
       163: goto          185
       166: astore        4
       168: aload_0
       169: aload_3
       170: invokeinterface #914,  1          // InterfaceMethod ghidra/framework/model/DomainFile.getPathname:()Ljava/lang/String;
       175: invokedynamic #1083,  0           // InvokeDynamic #52:makeConcatWithConstants:(Ljava/lang/String;)Ljava/lang/String;
       180: invokestatic  #163                // Method ghidra/util/Msg.error:(Ljava/lang/Object;Ljava/lang/Object;)V
       183: iconst_0
       184: ireturn
       185: aload_0
       186: aload_3
       187: invokeinterface #914,  1          // InterfaceMethod ghidra/framework/model/DomainFile.getPathname:()Ljava/lang/String;
       192: invokedynamic #1084,  0           // InvokeDynamic #53:makeConcatWithConstants:(Ljava/lang/String;)Ljava/lang/String;
       197: invokestatic  #225                // Method ghidra/util/Msg.warn:(Ljava/lang/Object;Ljava/lang/Object;)V
       200: goto          220
       203: aload_0
       204: aload_3
       205: invokeinterface #914,  1          // InterfaceMethod ghidra/framework/model/DomainFile.getPathname:()Ljava/lang/String;
       210: invokedynamic #1085,  0           // InvokeDynamic #54:makeConcatWithConstants:(Ljava/lang/String;)Ljava/lang/String;
       215: invokestatic  #163                // Method ghidra/util/Msg.error:(Ljava/lang/Object;Ljava/lang/Object;)V
       218: iconst_0
       219: ireturn
       220: iconst_1
       221: ireturn
      Exception table:
         from    to  target type
           130   136   139   Class java/io/IOException
            52    77   166   Class ghidra/util/exception/UserAccessException
            78   113   166   Class ghidra/util/exception/UserAccessException
           114   162   166   Class ghidra/util/exception/UserAccessException

  private void commitProgram(ghidra.framework.model.DomainFile) throws java.io.IOException;
    Code:
         0: aload_0
         1: getfield      #132                // Field project:Lghidra/framework/model/Project;
         4: invokeinterface #528,  1          // InterfaceMethod ghidra/framework/model/Project.getRepository:()Lghidra/framework/client/RepositoryAdapter;
         9: astore_2
        10: aload_2
        11: ifnull        72
        14: aload_2
        15: invokevirtual #532                // Method ghidra/framework/client/RepositoryAdapter.connect:()V
        18: goto          31
        21: astore_3
        22: aload_2
        23: aload_3
        24: ldc_w         #1086               // String Connect
        27: aconst_null
        28: invokestatic  #1088               // Method ghidra/framework/client/ClientUtil.handleException:(Lghidra/framework/client/RepositoryAdapter;Ljava/lang/Exception;Ljava/lang/String;Ljava/awt/Component;)V
        31: aload_2
        32: invokevirtual #537                // Method ghidra/framework/client/RepositoryAdapter.isConnected:()Z
        35: ifne          72
        38: aload_0
        39: aload_1
        40: invokeinterface #914,  1          // InterfaceMethod ghidra/framework/model/DomainFile.getPathname:()Ljava/lang/String;
        45: invokedynamic #1094,  0           // InvokeDynamic #55:makeConcatWithConstants:(Ljava/lang/String;)Ljava/lang/String;
        50: invokestatic  #163                // Method ghidra/util/Msg.error:(Ljava/lang/Object;Ljava/lang/Object;)V
        53: new           #63                 // class java/io/IOException
        56: dup
        57: aload_1
        58: invokeinterface #914,  1          // InterfaceMethod ghidra/framework/model/DomainFile.getPathname:()Ljava/lang/String;
        63: invokedynamic #1094,  0           // InvokeDynamic #55:makeConcatWithConstants:(Ljava/lang/String;)Ljava/lang/String;
        68: invokespecial #346                // Method java/io/IOException."<init>":(Ljava/lang/String;)V
        71: athrow
        72: aload_1
        73: invokeinterface #1095,  1         // InterfaceMethod ghidra/framework/model/DomainFile.canAddToRepository:()Z
        78: ifeq          142
        81: aload_1
        82: aload_0
        83: getfield      #86                 // Field options:Lghidra/app/util/headless/HeadlessOptions;
        86: getfield      #1098               // Field ghidra/app/util/headless/HeadlessOptions.commitComment:Ljava/lang/String;
        89: iconst_0
        90: getstatic     #300                // Field ghidra/util/task/TaskMonitor.DUMMY:Lghidra/util/task/TaskMonitor;
        93: invokeinterface #1101,  4         // InterfaceMethod ghidra/framework/model/DomainFile.addToVersionControl:(Ljava/lang/String;ZLghidra/util/task/TaskMonitor;)V
        98: aload_0
        99: aload_1
       100: invokeinterface #914,  1          // InterfaceMethod ghidra/framework/model/DomainFile.getPathname:()Ljava/lang/String;
       105: invokedynamic #1105,  0           // InvokeDynamic #56:makeConcatWithConstants:(Ljava/lang/String;)Ljava/lang/String;
       110: invokestatic  #281                // Method ghidra/util/Msg.info:(Ljava/lang/Object;Ljava/lang/Object;)V
       113: goto          246
       116: astore_3
       117: aload_0
       118: aload_1
       119: invokeinterface #914,  1          // InterfaceMethod ghidra/framework/model/DomainFile.getPathname:()Ljava/lang/String;
       124: aload_3
       125: invokevirtual #65                 // Method java/io/IOException.getMessage:()Ljava/lang/String;
       128: invokedynamic #1106,  0           // InvokeDynamic #57:makeConcatWithConstants:(Ljava/lang/String;Ljava/lang/String;)Ljava/lang/String;
       133: invokestatic  #163                // Method ghidra/util/Msg.error:(Ljava/lang/Object;Ljava/lang/Object;)V
       136: aload_3
       137: athrow
       138: astore_3
       139: goto          246
       142: aload_1
       143: invokeinterface #1107,  1         // InterfaceMethod ghidra/framework/model/DomainFile.canCheckin:()Z
       148: ifeq          231
       151: aload_1
       152: new           #1110               // class ghidra/app/util/headless/HeadlessAnalyzer$2
       155: dup
       156: aload_0
       157: invokespecial #1112               // Method ghidra/app/util/headless/HeadlessAnalyzer$2."<init>":(Lghidra/app/util/headless/HeadlessAnalyzer;)V
       160: getstatic     #300                // Field ghidra/util/task/TaskMonitor.DUMMY:Lghidra/util/task/TaskMonitor;
       163: invokeinterface #1114,  3         // InterfaceMethod ghidra/framework/model/DomainFile.checkin:(Lghidra/framework/data/CheckinHandler;Lghidra/util/task/TaskMonitor;)V
       168: aload_0
       169: aload_1
       170: invokeinterface #914,  1          // InterfaceMethod ghidra/framework/model/DomainFile.getPathname:()Ljava/lang/String;
       175: invokedynamic #1118,  0           // InvokeDynamic #58:makeConcatWithConstants:(Ljava/lang/String;)Ljava/lang/String;
       180: invokestatic  #281                // Method ghidra/util/Msg.info:(Ljava/lang/Object;Ljava/lang/Object;)V
       183: goto          246
       186: astore_3
       187: aload_0
       188: aload_1
       189: invokeinterface #914,  1          // InterfaceMethod ghidra/framework/model/DomainFile.getPathname:()Ljava/lang/String;
       194: aload_3
       195: invokevirtual #65                 // Method java/io/IOException.getMessage:()Ljava/lang/String;
       198: invokedynamic #1106,  0           // InvokeDynamic #57:makeConcatWithConstants:(Ljava/lang/String;Ljava/lang/String;)Ljava/lang/String;
       203: invokestatic  #163                // Method ghidra/util/Msg.error:(Ljava/lang/Object;Ljava/lang/Object;)V
       206: aload_3
       207: athrow
       208: astore_3
       209: aload_0
       210: aload_1
       211: invokeinterface #914,  1          // InterfaceMethod ghidra/framework/model/DomainFile.getPathname:()Ljava/lang/String;
       216: invokedynamic #1119,  0           // InvokeDynamic #59:makeConcatWithConstants:(Ljava/lang/String;)Ljava/lang/String;
       221: invokestatic  #163                // Method ghidra/util/Msg.error:(Ljava/lang/Object;Ljava/lang/Object;)V
       224: goto          246
       227: astore_3
       228: goto          246
       231: aload_0
       232: aload_1
       233: invokeinterface #914,  1          // InterfaceMethod ghidra/framework/model/DomainFile.getPathname:()Ljava/lang/String;
       238: invokedynamic #1120,  0           // InvokeDynamic #60:makeConcatWithConstants:(Ljava/lang/String;)Ljava/lang/String;
       243: invokestatic  #163                // Method ghidra/util/Msg.error:(Ljava/lang/Object;Ljava/lang/Object;)V
       246: return
      Exception table:
         from    to  target type
            14    18    21   Class java/io/IOException
            81   113   116   Class java/io/IOException
            81   113   138   Class ghidra/util/exception/CancelledException
           151   183   186   Class java/io/IOException
           151   183   208   Class ghidra/util/exception/VersionException
           151   183   227   Class ghidra/util/exception/CancelledException

  private boolean processFileWithImport(ghidra.formats.gfilesystem.FSRL, java.lang.String);
    Code:
         0: aload_0
         1: aload_1
         2: invokestatic  #181                // Method java/lang/String.valueOf:(Ljava/lang/Object;)Ljava/lang/String;
         5: invokedynamic #1121,  0           // InvokeDynamic #61:makeConcatWithConstants:(Ljava/lang/String;)Ljava/lang/String;
        10: invokestatic  #281                // Method ghidra/util/Msg.info:(Ljava/lang/Object;Ljava/lang/Object;)V
        13: aconst_null
        14: astore_3
        15: invokestatic  #1122               // Method ghidra/app/util/importer/ProgramLoader.builder:()Lghidra/app/util/importer/ProgramLoader$Builder;
        18: aload_1
        19: invokevirtual #1128               // Method ghidra/app/util/importer/ProgramLoader$Builder.source:(Lghidra/formats/gfilesystem/FSRL;)Lghidra/app/util/importer/ProgramLoader$Builder;
        22: aload_0
        23: getfield      #132                // Field project:Lghidra/framework/model/Project;
        26: invokevirtual #1134               // Method ghidra/app/util/importer/ProgramLoader$Builder.project:(Lghidra/framework/model/Project;)Lghidra/app/util/importer/ProgramLoader$Builder;
        29: aload_2
        30: invokevirtual #1137               // Method ghidra/app/util/importer/ProgramLoader$Builder.projectFolderPath:(Ljava/lang/String;)Lghidra/app/util/importer/ProgramLoader$Builder;
        33: aload_0
        34: getfield      #86                 // Field options:Lghidra/app/util/headless/HeadlessOptions;
        37: getfield      #1141               // Field ghidra/app/util/headless/HeadlessOptions.mirror:Z
        40: invokevirtual #1144               // Method ghidra/app/util/importer/ProgramLoader$Builder.mirror:(Z)Lghidra/app/util/importer/ProgramLoader$Builder;
        43: aload_0
        44: getfield      #86                 // Field options:Lghidra/app/util/headless/HeadlessOptions;
        47: getfield      #1147               // Field ghidra/app/util/headless/HeadlessOptions.language:Lghidra/program/model/lang/Language;
        50: invokevirtual #1151               // Method ghidra/app/util/importer/ProgramLoader$Builder.language:(Lghidra/program/model/lang/Language;)Lghidra/app/util/importer/ProgramLoader$Builder;
        53: aload_0
        54: getfield      #86                 // Field options:Lghidra/app/util/headless/HeadlessOptions;
        57: getfield      #1154               // Field ghidra/app/util/headless/HeadlessOptions.compilerSpec:Lghidra/program/model/lang/CompilerSpec;
        60: invokevirtual #1158               // Method ghidra/app/util/importer/ProgramLoader$Builder.compiler:(Lghidra/program/model/lang/CompilerSpec;)Lghidra/app/util/importer/ProgramLoader$Builder;
        63: aload_0
        64: getfield      #86                 // Field options:Lghidra/app/util/headless/HeadlessOptions;
        67: getfield      #1162               // Field ghidra/app/util/headless/HeadlessOptions.loaderClass:Ljava/lang/Class;
        70: invokevirtual #1166               // Method ghidra/app/util/importer/ProgramLoader$Builder.loaders:(Ljava/lang/Class;)Lghidra/app/util/importer/ProgramLoader$Builder;
        73: aload_0
        74: getfield      #86                 // Field options:Lghidra/app/util/headless/HeadlessOptions;
        77: getfield      #1170               // Field ghidra/app/util/headless/HeadlessOptions.loaderArgs:Ljava/util/List;
        80: invokevirtual #1173               // Method ghidra/app/util/importer/ProgramLoader$Builder.loaderArgs:(Ljava/util/List;)Lghidra/app/util/importer/ProgramLoader$Builder;
        83: invokevirtual #1176               // Method ghidra/app/util/importer/ProgramLoader$Builder.load:()Lghidra/app/util/opinion/LoadResults;
        86: astore_3
        87: aload_0
        88: aload_3
        89: invokevirtual #1180               // Method ghidra/app/util/opinion/LoadResults.size:()I
        92: iconst_1
        93: isub
        94: invokedynamic #1183,  0           // InvokeDynamic #62:makeConcatWithConstants:(I)Ljava/lang/String;
        99: invokestatic  #281                // Method ghidra/util/Msg.info:(Ljava/lang/Object;Ljava/lang/Object;)V
       102: aload_0
       103: getfield      #86                 // Field options:Lghidra/app/util/headless/HeadlessOptions;
       106: getfield      #155                // Field ghidra/app/util/headless/HeadlessOptions.readOnly:Z
       109: ifne          166
       112: aload_3
       113: invokevirtual #1186               // Method ghidra/app/util/opinion/LoadResults.iterator:()Ljava/util/Iterator;
       116: astore        4
       118: aload         4
       120: invokeinterface #567,  1          // InterfaceMethod java/util/Iterator.hasNext:()Z
       125: ifeq          166
       128: aload         4
       130: invokeinterface #572,  1          // InterfaceMethod java/util/Iterator.next:()Ljava/lang/Object;
       135: checkcast     #1073               // class ghidra/app/util/opinion/Loaded
       138: astore        5
       140: aload_0
       141: aload         5
       143: invokevirtual #1187               // Method checkOverwrite:(Lghidra/app/util/opinion/Loaded;)Z
       146: ifne          163
       149: iconst_0
       150: istore        6
       152: aload_3
       153: ifnull        160
       156: aload_3
       157: invokevirtual #1191               // Method ghidra/app/util/opinion/LoadResults.close:()V
       160: iload         6
       162: ireturn
       163: goto          118
       166: aload_3
       167: invokevirtual #1192               // Method ghidra/app/util/opinion/LoadResults.getPrimary:()Lghidra/app/util/opinion/Loaded;
       170: astore        4
       172: aload         4
       174: invokedynamic #1196,  0           // InvokeDynamic #63:test:()Ljava/util/function/Predicate;
       179: invokevirtual #1200               // Method ghidra/app/util/opinion/Loaded.check:(Ljava/util/function/Predicate;)Z
       182: ifeq          212
       185: aload_0
       186: aload_1
       187: invokestatic  #181                // Method java/lang/String.valueOf:(Ljava/lang/Object;)Ljava/lang/String;
       190: invokedynamic #1204,  0           // InvokeDynamic #64:makeConcatWithConstants:(Ljava/lang/String;)Ljava/lang/String;
       195: invokestatic  #163                // Method ghidra/util/Msg.error:(Ljava/lang/Object;Ljava/lang/Object;)V
       198: iconst_0
       199: istore        5
       201: aload_3
       202: ifnull        209
       205: aload_3
       206: invokevirtual #1191               // Method ghidra/app/util/opinion/LoadResults.close:()V
       209: iload         5
       211: ireturn
       212: aload         4
       214: aload_0
       215: invokevirtual #1205               // Method ghidra/app/util/opinion/Loaded.getDomainObject:(Ljava/lang/Object;)Lghidra/framework/model/DomainObject;
       218: checkcast     #797                // class ghidra/program/model/listing/Program
       221: astore        5
       223: aload_0
       224: aload_1
       225: invokevirtual #1208               // Method ghidra/formats/gfilesystem/FSRL.toString:()Ljava/lang/String;
       228: aload         5
       230: invokevirtual #970                // Method analyzeProgram:(Ljava/lang/String;Lghidra/program/model/listing/Program;)Z
       233: ifeq          250
       236: aload_0
       237: getfield      #86                 // Field options:Lghidra/app/util/headless/HeadlessOptions;
       240: getfield      #155                // Field ghidra/app/util/headless/HeadlessOptions.readOnly:Z
       243: ifne          250
       246: iconst_1
       247: goto          251
       250: iconst_0
       251: istore        6
       253: aload         5
       255: aload_0
       256: invokeinterface #940,  2          // InterfaceMethod ghidra/program/model/listing/Program.release:(Ljava/lang/Object;)V
       261: goto          277
       264: astore        7
       266: aload         5
       268: aload_0
       269: invokeinterface #940,  2          // InterfaceMethod ghidra/program/model/listing/Program.release:(Ljava/lang/Object;)V
       274: aload         7
       276: athrow
       277: iload         6
       279: ifne          291
       282: aload_3
       283: invokedynamic #1211,  0           // InvokeDynamic #65:accept:()Ljava/util/function/Consumer;
       288: invokevirtual #1215               // Method ghidra/app/util/opinion/LoadResults.forEach:(Ljava/util/function/Consumer;)V
       291: aload_0
       292: getfield      #140                // Field saveDomainFolder:Lghidra/framework/model/DomainFolder;
       295: ifnull        335
       298: aload         4
       300: aload_0
       301: getfield      #140                // Field saveDomainFolder:Lghidra/framework/model/DomainFolder;
       304: invokeinterface #393,  1          // InterfaceMethod ghidra/framework/model/DomainFolder.getPathname:()Ljava/lang/String;
       309: invokevirtual #1219               // Method ghidra/app/util/opinion/Loaded.setProjectFolderPath:(Ljava/lang/String;)V
       312: aload_0
       313: aload         4
       315: invokevirtual #1187               // Method checkOverwrite:(Lghidra/app/util/opinion/Loaded;)Z
       318: ifne          335
       321: iconst_0
       322: istore        7
       324: aload_3
       325: ifnull        332
       328: aload_3
       329: invokevirtual #1191               // Method ghidra/app/util/opinion/LoadResults.close:()V
       332: iload         7
       334: ireturn
       335: aload_3
       336: invokevirtual #1186               // Method ghidra/app/util/opinion/LoadResults.iterator:()Ljava/util/Iterator;
       339: astore        7
       341: aload         7
       343: invokeinterface #567,  1          // InterfaceMethod java/util/Iterator.hasNext:()Z
       348: ifeq          476
       351: aload         7
       353: invokeinterface #572,  1          // InterfaceMethod java/util/Iterator.next:()Ljava/lang/Object;
       358: checkcast     #1073               // class ghidra/app/util/opinion/Loaded
       361: astore        8
       363: aload         8
       365: invokedynamic #1222,  0           // InvokeDynamic #66:test:()Ljava/util/function/Predicate;
       370: invokevirtual #1200               // Method ghidra/app/util/opinion/Loaded.check:(Ljava/util/function/Predicate;)Z
       373: ifne          432
       376: aload         8
       378: getstatic     #300                // Field ghidra/util/task/TaskMonitor.DUMMY:Lghidra/util/task/TaskMonitor;
       381: invokevirtual #1223               // Method ghidra/app/util/opinion/Loaded.save:(Lghidra/util/task/TaskMonitor;)Lghidra/framework/model/DomainFile;
       384: astore        9
       386: aload_0
       387: ldc_w         #1226               // String REPORT: Save succeeded for: %s (%s)
       390: iconst_2
       391: anewarray     #81                 // class java/lang/Object
       394: dup
       395: iconst_0
       396: aload         8
       398: aastore
       399: dup
       400: iconst_1
       401: aload         9
       403: aastore
       404: invokestatic  #1228               // Method java/lang/String.format:(Ljava/lang/String;[Ljava/lang/Object;)Ljava/lang/String;
       407: invokestatic  #281                // Method ghidra/util/Msg.info:(Ljava/lang/Object;Ljava/lang/Object;)V
       410: goto          473
       413: astore        9
       415: aload_0
       416: aload         8
       418: invokestatic  #181                // Method java/lang/String.valueOf:(Ljava/lang/Object;)Ljava/lang/String;
       421: invokedynamic #1232,  0           // InvokeDynamic #67:makeConcatWithConstants:(Ljava/lang/String;)Ljava/lang/String;
       426: invokestatic  #281                // Method ghidra/util/Msg.info:(Ljava/lang/Object;Ljava/lang/Object;)V
       429: goto          473
       432: aload_0
       433: getfield      #86                 // Field options:Lghidra/app/util/headless/HeadlessOptions;
       436: getfield      #155                // Field ghidra/app/util/headless/HeadlessOptions.readOnly:Z
       439: ifeq          459
       442: aload_0
       443: aload         8
       445: invokestatic  #181                // Method java/lang/String.valueOf:(Ljava/lang/Object;)Ljava/lang/String;
       448: invokedynamic #1233,  0           // InvokeDynamic #68:makeConcatWithConstants:(Ljava/lang/String;)Ljava/lang/String;
       453: invokestatic  #281                // Method ghidra/util/Msg.info:(Ljava/lang/Object;Ljava/lang/Object;)V
       456: goto          473
       459: aload_0
       460: aload         8
       462: invokestatic  #181                // Method java/lang/String.valueOf:(Ljava/lang/Object;)Ljava/lang/String;
       465: invokedynamic #1234,  0           // InvokeDynamic #69:makeConcatWithConstants:(Ljava/lang/String;)Ljava/lang/String;
       470: invokestatic  #281                // Method ghidra/util/Msg.info:(Ljava/lang/Object;Ljava/lang/Object;)V
       473: goto          341
       476: aload_0
       477: getfield      #86                 // Field options:Lghidra/app/util/headless/HeadlessOptions;
       480: getfield      #158                // Field ghidra/app/util/headless/HeadlessOptions.commit:Z
       483: ifeq          559
       486: aload_3
       487: invokevirtual #1186               // Method ghidra/app/util/opinion/LoadResults.iterator:()Ljava/util/Iterator;
       490: astore        7
       492: aload         7
       494: invokeinterface #567,  1          // InterfaceMethod java/util/Iterator.hasNext:()Z
       499: ifeq          559
       502: aload         7
       504: invokeinterface #572,  1          // InterfaceMethod java/util/Iterator.next:()Ljava/lang/Object;
       509: checkcast     #1073               // class ghidra/app/util/opinion/Loaded
       512: astore        8
       514: aload         8
       516: invokedynamic #1222,  0           // InvokeDynamic #66:test:()Ljava/util/function/Predicate;
       521: invokevirtual #1200               // Method ghidra/app/util/opinion/Loaded.check:(Ljava/util/function/Predicate;)Z
       524: ifne          556
       527: aload         8
       529: aload         4
       531: if_acmpne     542
       534: aload         5
       536: invokestatic  #825                // Method ghidra/app/plugin/core/analysis/AutoAnalysisManager.getAnalysisManager:(Lghidra/program/model/listing/Program;)Lghidra/app/plugin/core/analysis/AutoAnalysisManager;
       539: invokevirtual #937                // Method ghidra/app/plugin/core/analysis/AutoAnalysisManager.dispose:()V
       542: aload         8
       544: invokevirtual #1235               // Method ghidra/app/util/opinion/Loaded.close:()V
       547: aload_0
       548: aload         8
       550: invokevirtual #1236               // Method ghidra/app/util/opinion/Loaded.getSavedDomainFile:()Lghidra/framework/model/DomainFile;
       553: invokevirtual #994                // Method commitProgram:(Lghidra/framework/model/DomainFile;)V
       556: goto          492
       559: aload_0
       560: ldc_w         #1240               // String REPORT: Import succeeded
       563: invokestatic  #281                // Method ghidra/util/Msg.info:(Ljava/lang/Object;Ljava/lang/Object;)V
       566: iconst_1
       567: istore        7
       569: aload_3
       570: ifnull        577
       573: aload_3
       574: invokevirtual #1191               // Method ghidra/app/util/opinion/LoadResults.close:()V
       577: iload         7
       579: ireturn
       580: astore        4
       582: aload_0
       583: aload_1
       584: invokestatic  #181                // Method java/lang/String.valueOf:(Ljava/lang/Object;)Ljava/lang/String;
       587: invokedynamic #1244,  0           // InvokeDynamic #70:makeConcatWithConstants:(Ljava/lang/String;)Ljava/lang/String;
       592: invokestatic  #163                // Method ghidra/util/Msg.error:(Ljava/lang/Object;Ljava/lang/Object;)V
       595: aload_0
       596: getfield      #86                 // Field options:Lghidra/app/util/headless/HeadlessOptions;
       599: getfield      #1162               // Field ghidra/app/util/headless/HeadlessOptions.loaderClass:Ljava/lang/Class;
       602: ifnull        637
       605: aload_0
       606: getfield      #86                 // Field options:Lghidra/app/util/headless/HeadlessOptions;
       609: getfield      #1162               // Field ghidra/app/util/headless/HeadlessOptions.loaderClass:Ljava/lang/Class;
       612: ldc_w         #1245               // class ghidra/app/util/opinion/BinaryLoader
       615: if_acmpeq     637
       618: aload_0
       619: aload_0
       620: getfield      #86                 // Field options:Lghidra/app/util/headless/HeadlessOptions;
       623: getfield      #1162               // Field ghidra/app/util/headless/HeadlessOptions.loaderClass:Ljava/lang/Class;
       626: invokevirtual #715                // Method java/lang/Class.getSimpleName:()Ljava/lang/String;
       629: invokedynamic #1247,  0           // InvokeDynamic #71:makeConcatWithConstants:(Ljava/lang/String;)Ljava/lang/String;
       634: invokestatic  #163                // Method ghidra/util/Msg.error:(Ljava/lang/Object;Ljava/lang/Object;)V
       637: iconst_0
       638: istore        5
       640: aload_3
       641: ifnull        648
       644: aload_3
       645: invokevirtual #1191               // Method ghidra/app/util/opinion/LoadResults.close:()V
       648: iload         5
       650: ireturn
       651: astore        4
       653: aload_0
       654: aload         4
       656: invokevirtual #795                // Method java/lang/Exception.getMessage:()Ljava/lang/String;
       659: invokedynamic #1248,  0           // InvokeDynamic #72:makeConcatWithConstants:(Ljava/lang/String;)Ljava/lang/String;
       664: aload         4
       666: invokestatic  #491                // Method ghidra/util/Msg.error:(Ljava/lang/Object;Ljava/lang/Object;Ljava/lang/Throwable;)V
       669: iconst_0
       670: istore        5
       672: aload_3
       673: ifnull        680
       676: aload_3
       677: invokevirtual #1191               // Method ghidra/app/util/opinion/LoadResults.close:()V
       680: iload         5
       682: ireturn
       683: astore        10
       685: aload_3
       686: ifnull        693
       689: aload_3
       690: invokevirtual #1191               // Method ghidra/app/util/opinion/LoadResults.close:()V
       693: aload         10
       695: athrow
      Exception table:
         from    to  target type
           223   253   264   any
           264   266   264   any
           376   410   413   Class java/io/IOException
            15   152   580   Class ghidra/app/util/opinion/LoadException
           163   201   580   Class ghidra/app/util/opinion/LoadException
           212   324   580   Class ghidra/app/util/opinion/LoadException
           335   569   580   Class ghidra/app/util/opinion/LoadException
            15   152   651   Class java/lang/Exception
           163   201   651   Class java/lang/Exception
           212   324   651   Class java/lang/Exception
           335   569   651   Class java/lang/Exception
            15   152   683   any
           163   201   683   any
           212   324   683   any
           335   569   683   any
           580   640   683   any
           651   672   683   any
           683   685   683   any

  private void processWithImport(ghidra.formats.gfilesystem.FSRL, java.lang.String, java.lang.Integer, boolean) throws java.io.IOException;
    Code:
         0: aload_0
         1: getfield      #127                // Field fsService:Lghidra/formats/gfilesystem/FileSystemService;
         4: aload_1
         5: getstatic     #300                // Field ghidra/util/task/TaskMonitor.DUMMY:Lghidra/util/task/TaskMonitor;
         8: invokevirtual #1249               // Method ghidra/formats/gfilesystem/FileSystemService.getRefdFile:(Lghidra/formats/gfilesystem/FSRL;Lghidra/util/task/TaskMonitor;)Lghidra/formats/gfilesystem/RefdFile;
        11: astore        5
        13: aload         5
        15: getfield      #1253               // Field ghidra/formats/gfilesystem/RefdFile.file:Lghidra/formats/gfilesystem/GFile;
        18: astore        6
        20: aload_3
        21: ifnonnull     48
        24: iload         4
        26: ifeq          48
        29: aload         6
        31: invokeinterface #1259,  1         // InterfaceMethod ghidra/formats/gfilesystem/GFile.isDirectory:()Z
        36: ifeq          43
        39: iconst_0
        40: goto          44
        43: iconst_1
        44: invokestatic  #1262               // Method java/lang/Integer.valueOf:(I)Ljava/lang/Integer;
        47: astore_3
        48: aload_0
        49: getfield      #86                 // Field options:Lghidra/app/util/headless/HeadlessOptions;
        52: getfield      #1029               // Field ghidra/app/util/headless/HeadlessOptions.recursive:Z
        55: ifne          63
        58: iload         4
        60: ifeq          102
        63: aload         6
        65: invokeinterface #1259,  1         // InterfaceMethod ghidra/formats/gfilesystem/GFile.isDirectory:()Z
        70: ifeq          102
        73: aload_0
        74: aload         6
        76: invokeinterface #1267,  1         // InterfaceMethod ghidra/formats/gfilesystem/GFile.getFilesystem:()Lghidra/formats/gfilesystem/GFileSystem;
        81: aload         6
        83: aload_2
        84: aload_3
        85: invokevirtual #1271               // Method java/lang/Integer.intValue:()I
        88: invokevirtual #1274               // Method processFS:(Lghidra/formats/gfilesystem/GFileSystem;Lghidra/formats/gfilesystem/GFile;Ljava/lang/String;I)V
        91: aload         5
        93: ifnull        101
        96: aload         5
        98: invokevirtual #1278               // Method ghidra/formats/gfilesystem/RefdFile.close:()V
       101: return
       102: aload_0
       103: getfield      #86                 // Field options:Lghidra/app/util/headless/HeadlessOptions;
       106: getfield      #1029               // Field ghidra/app/util/headless/HeadlessOptions.recursive:Z
       109: ifeq          143
       112: aload_3
       113: invokevirtual #1271               // Method java/lang/Integer.intValue:()I
       116: ifle          143
       119: aload_0
       120: aload_1
       121: aload_2
       122: aload_3
       123: invokevirtual #1271               // Method java/lang/Integer.intValue:()I
       126: invokevirtual #1279               // Method processAsFS:(Lghidra/formats/gfilesystem/FSRL;Ljava/lang/String;I)Z
       129: ifeq          143
       132: aload         5
       134: ifnull        142
       137: aload         5
       139: invokevirtual #1278               // Method ghidra/formats/gfilesystem/RefdFile.close:()V
       142: return
       143: aload         6
       145: invokeinterface #1259,  1         // InterfaceMethod ghidra/formats/gfilesystem/GFile.isDirectory:()Z
       150: ifne          173
       153: aload_0
       154: aload_1
       155: aload_2
       156: invokevirtual #1283               // Method processWithLoader:(Lghidra/formats/gfilesystem/FSRL;Ljava/lang/String;)Z
       159: ifeq          173
       162: aload         5
       164: ifnull        172
       167: aload         5
       169: invokevirtual #1278               // Method ghidra/formats/gfilesystem/RefdFile.close:()V
       172: return
       173: aload         5
       175: ifnull        213
       178: aload         5
       180: invokevirtual #1278               // Method ghidra/formats/gfilesystem/RefdFile.close:()V
       183: goto          213
       186: astore        6
       188: aload         5
       190: ifnull        210
       193: aload         5
       195: invokevirtual #1278               // Method ghidra/formats/gfilesystem/RefdFile.close:()V
       198: goto          210
       201: astore        7
       203: aload         6
       205: aload         7
       207: invokevirtual #1287               // Method java/lang/Throwable.addSuppressed:(Ljava/lang/Throwable;)V
       210: aload         6
       212: athrow
       213: goto          225
       216: astore        5
       218: aload_0
       219: ldc_w         #1290               // String REPORT: Importing cancelled
       222: invokestatic  #281                // Method ghidra/util/Msg.info:(Ljava/lang/Object;Ljava/lang/Object;)V
       225: return
      Exception table:
         from    to  target type
            13    91   186   Class java/lang/Throwable
           102   132   186   Class java/lang/Throwable
           143   162   186   Class java/lang/Throwable
           193   198   201   Class java/lang/Throwable
             0   101   216   Class ghidra/util/exception/CancelledException
           102   142   216   Class ghidra/util/exception/CancelledException
           143   172   216   Class ghidra/util/exception/CancelledException
           173   213   216   Class ghidra/util/exception/CancelledException

  private void processFS(ghidra.formats.gfilesystem.GFileSystem, ghidra.formats.gfilesystem.GFile, java.lang.String, int) throws ghidra.util.exception.CancelledException, java.io.IOException;
    Code:
         0: aload_3
         1: ldc           #228                // String /
         3: invokevirtual #230                // Method java/lang/String.endsWith:(Ljava/lang/String;)Z
         6: ifne          16
         9: aload_3
        10: invokedynamic #242,  0            // InvokeDynamic #2:makeConcatWithConstants:(Ljava/lang/String;)Ljava/lang/String;
        15: astore_3
        16: aload_3
        17: aload_2
        18: invokeinterface #1292,  1         // InterfaceMethod ghidra/formats/gfilesystem/GFile.getName:()Ljava/lang/String;
        23: invokedynamic #1293,  0           // InvokeDynamic #73:makeConcatWithConstants:(Ljava/lang/String;Ljava/lang/String;)Ljava/lang/String;
        28: astore_3
        29: aload_1
        30: aload_2
        31: invokeinterface #1294,  2         // InterfaceMethod ghidra/formats/gfilesystem/GFileSystem.getListing:(Lghidra/formats/gfilesystem/GFile;)Ljava/util/List;
        36: invokeinterface #563,  1          // InterfaceMethod java/util/List.iterator:()Ljava/util/Iterator;
        41: astore        5
        43: aload         5
        45: invokeinterface #567,  1          // InterfaceMethod java/util/Iterator.hasNext:()Z
        50: ifeq          174
        53: aload         5
        55: invokeinterface #572,  1          // InterfaceMethod java/util/Iterator.next:()Ljava/lang/Object;
        60: checkcast     #1260               // class ghidra/formats/gfilesystem/GFile
        63: astore        6
        65: aload         6
        67: invokeinterface #1292,  1         // InterfaceMethod ghidra/formats/gfilesystem/GFile.getName:()Ljava/lang/String;
        72: astore        7
        74: aload         7
        76: ldc_w         #1300               // String .
        79: invokevirtual #1063               // Method java/lang/String.startsWith:(Ljava/lang/String;)Z
        82: ifeq          99
        85: aload_0
        86: aload         7
        88: invokedynamic #1302,  0           // InvokeDynamic #74:makeConcatWithConstants:(Ljava/lang/String;)Ljava/lang/String;
        93: invokestatic  #225                // Method ghidra/util/Msg.warn:(Ljava/lang/Object;Ljava/lang/Object;)V
        96: goto          43
        99: aload_0
       100: getfield      #127                // Field fsService:Lghidra/formats/gfilesystem/FileSystemService;
       103: aload         6
       105: invokeinterface #1303,  1         // InterfaceMethod ghidra/formats/gfilesystem/GFile.getFSRL:()Lghidra/formats/gfilesystem/FSRL;
       110: getstatic     #300                // Field ghidra/util/task/TaskMonitor.DUMMY:Lghidra/util/task/TaskMonitor;
       113: invokevirtual #1307               // Method ghidra/formats/gfilesystem/FileSystemService.getFullyQualifiedFSRL:(Lghidra/formats/gfilesystem/FSRL;Lghidra/util/task/TaskMonitor;)Lghidra/formats/gfilesystem/FSRL;
       116: astore        8
       118: goto          145
       121: astore        9
       123: aload_0
       124: aload         6
       126: invokeinterface #1303,  1         // InterfaceMethod ghidra/formats/gfilesystem/GFile.getFSRL:()Lghidra/formats/gfilesystem/FSRL;
       131: invokestatic  #181                // Method java/lang/String.valueOf:(Ljava/lang/Object;)Ljava/lang/String;
       134: invokedynamic #1311,  0           // InvokeDynamic #75:makeConcatWithConstants:(Ljava/lang/String;)Ljava/lang/String;
       139: invokestatic  #225                // Method ghidra/util/Msg.warn:(Ljava/lang/Object;Ljava/lang/Object;)V
       142: goto          43
       145: aload         8
       147: invokevirtual #1312               // Method ghidra/formats/gfilesystem/FSRL.getName:()Ljava/lang/String;
       150: invokestatic  #1313               // Method checkValidFilename:(Ljava/lang/String;)V
       153: aload_0
       154: aload         8
       156: aload_3
       157: iload         4
       159: invokestatic  #1262               // Method java/lang/Integer.valueOf:(I)Ljava/lang/Integer;
       162: iconst_0
       163: invokevirtual #1316               // Method processWithImport:(Lghidra/formats/gfilesystem/FSRL;Ljava/lang/String;Ljava/lang/Integer;Z)V
       166: goto          171
       169: astore        9
       171: goto          43
       174: return
      Exception table:
         from    to  target type
            99   118   121   Class java/io/IOException
           145   166   169   Class ghidra/util/exception/InvalidInputException

  private boolean processAsFS(ghidra.formats.gfilesystem.FSRL, java.lang.String, int) throws ghidra.util.exception.CancelledException;
    Code:
         0: aload_0
         1: getfield      #127                // Field fsService:Lghidra/formats/gfilesystem/FileSystemService;
         4: aload_1
         5: getstatic     #300                // Field ghidra/util/task/TaskMonitor.DUMMY:Lghidra/util/task/TaskMonitor;
         8: getstatic     #1321               // Field ghidra/formats/gfilesystem/FileSystemProbeConflictResolver.CHOOSEFIRST:Lghidra/formats/gfilesystem/FileSystemProbeConflictResolver;
        11: invokevirtual #1327               // Method ghidra/formats/gfilesystem/FileSystemService.probeFileForFilesystem:(Lghidra/formats/gfilesystem/FSRL;Lghidra/util/task/TaskMonitor;Lghidra/formats/gfilesystem/FileSystemProbeConflictResolver;)Lghidra/formats/gfilesystem/FileSystemRef;
        14: astore        4
        16: aload         4
        18: ifnonnull     37
        21: iconst_0
        22: istore        5
        24: aload         4
        26: ifnull        34
        29: aload         4
        31: invokevirtual #1331               // Method ghidra/formats/gfilesystem/FileSystemRef.close:()V
        34: iload         5
        36: ireturn
        37: aload_2
        38: ldc           #228                // String /
        40: invokevirtual #230                // Method java/lang/String.endsWith:(Ljava/lang/String;)Z
        43: ifne          53
        46: aload_2
        47: invokedynamic #242,  0            // InvokeDynamic #2:makeConcatWithConstants:(Ljava/lang/String;)Ljava/lang/String;
        52: astore_2
        53: aload_2
        54: aload_1
        55: invokevirtual #1312               // Method ghidra/formats/gfilesystem/FSRL.getName:()Ljava/lang/String;
        58: invokedynamic #1293,  0           // InvokeDynamic #73:makeConcatWithConstants:(Ljava/lang/String;Ljava/lang/String;)Ljava/lang/String;
        63: astore_2
        64: aload_0
        65: aload         4
        67: invokevirtual #1334               // Method ghidra/formats/gfilesystem/FileSystemRef.getFilesystem:()Lghidra/formats/gfilesystem/GFileSystem;
        70: invokeinterface #1335,  1         // InterfaceMethod ghidra/formats/gfilesystem/GFileSystem.getFSRL:()Lghidra/formats/gfilesystem/FSRLRoot;
        75: aload_2
        76: iload_3
        77: iconst_1
        78: isub
        79: invokestatic  #1262               // Method java/lang/Integer.valueOf:(I)Ljava/lang/Integer;
        82: iconst_0
        83: invokevirtual #1316               // Method processWithImport:(Lghidra/formats/gfilesystem/FSRL;Ljava/lang/String;Ljava/lang/Integer;Z)V
        86: iconst_1
        87: istore        5
        89: aload         4
        91: ifnull        99
        94: aload         4
        96: invokevirtual #1331               // Method ghidra/formats/gfilesystem/FileSystemRef.close:()V
        99: iload         5
       101: ireturn
       102: astore        5
       104: aload         4
       106: ifnull        126
       109: aload         4
       111: invokevirtual #1331               // Method ghidra/formats/gfilesystem/FileSystemRef.close:()V
       114: goto          126
       117: astore        6
       119: aload         5
       121: aload         6
       123: invokevirtual #1287               // Method java/lang/Throwable.addSuppressed:(Ljava/lang/Throwable;)V
       126: aload         5
       128: athrow
       129: astore        4
       131: iconst_0
       132: ireturn
      Exception table:
         from    to  target type
            16    24   102   Class java/lang/Throwable
            37    89   102   Class java/lang/Throwable
           109   114   117   Class java/lang/Throwable
             0    34   129   Class java/io/IOException
            37    99   129   Class java/io/IOException
           102   129   129   Class java/io/IOException

  private boolean processWithLoader(ghidra.formats.gfilesystem.FSRL, java.lang.String);
    Code:
         0: aload_0
         1: aload_1
         2: aload_2
         3: invokevirtual #1338               // Method processFileWithImport:(Lghidra/formats/gfilesystem/FSRL;Ljava/lang/String;)Z
         6: istore_3
         7: new           #560                // class java/util/ArrayList
        10: dup
        11: invokespecial #562                // Method java/util/ArrayList."<init>":()V
        14: astore        4
        16: aload         4
        18: invokestatic  #1341               // Method ghidra/framework/data/TransientDataManager.getTransients:(Ljava/util/List;)V
        21: aload         4
        23: invokeinterface #208,  1          // InterfaceMethod java/util/List.size:()I
        28: ifle          35
        31: aload_0
        32: invokestatic  #1346               // Method ghidra/framework/data/TransientDataManager.releaseFiles:(Ljava/lang/Object;)V
        35: iload_3
        36: ifne          52
        39: aload_0
        40: aload_1
        41: invokestatic  #181                // Method java/lang/String.valueOf:(Ljava/lang/Object;)Ljava/lang/String;
        44: invokedynamic #1349,  0           // InvokeDynamic #76:makeConcatWithConstants:(Ljava/lang/String;)Ljava/lang/String;
        49: invokestatic  #163                // Method ghidra/util/Msg.error:(Ljava/lang/Object;Ljava/lang/Object;)V
        52: iload_3
        53: ireturn

  private void processWithImport(java.lang.String, java.util.List<java.io.File>) throws java.io.IOException;
    Code:
         0: aload_0
         1: getfield      #147                // Field storage:Ljava/util/Map;
         4: invokeinterface #1047,  1         // InterfaceMethod java/util/Map.clear:()V
         9: aload_2
        10: ifnull        124
        13: aload_2
        14: invokeinterface #217,  1          // InterfaceMethod java/util/List.isEmpty:()Z
        19: ifne          124
        22: aload_0
        23: ldc_w         #1350               // String REPORT: Processing input files:
        26: invokestatic  #281                // Method ghidra/util/Msg.info:(Ljava/lang/Object;Ljava/lang/Object;)V
        29: aload_0
        30: aload_0
        31: getfield      #132                // Field project:Lghidra/framework/model/Project;
        34: invokeinterface #511,  1          // InterfaceMethod ghidra/framework/model/Project.getProjectLocator:()Lghidra/framework/model/ProjectLocator;
        39: invokestatic  #181                // Method java/lang/String.valueOf:(Ljava/lang/Object;)Ljava/lang/String;
        42: invokedynamic #1352,  0           // InvokeDynamic #77:makeConcatWithConstants:(Ljava/lang/String;)Ljava/lang/String;
        47: invokestatic  #281                // Method ghidra/util/Msg.info:(Ljava/lang/Object;Ljava/lang/Object;)V
        50: aload_2
        51: invokeinterface #1353,  1         // InterfaceMethod java/util/List.stream:()Ljava/util/stream/Stream;
        56: aload_0
        57: invokedynamic #1357,  0           // InvokeDynamic #78:apply:(Lghidra/app/util/headless/HeadlessAnalyzer;)Ljava/util/function/Function;
        62: invokeinterface #1361,  2         // InterfaceMethod java/util/stream/Stream.map:(Ljava/util/function/Function;)Ljava/util/stream/Stream;
        67: invokeinterface #1367,  1         // InterfaceMethod java/util/stream/Stream.toList:()Ljava/util/List;
        72: astore_3
        73: aload_3
        74: invokeinterface #563,  1          // InterfaceMethod java/util/List.iterator:()Ljava/util/Iterator;
        79: astore        4
        81: aload         4
        83: invokeinterface #567,  1          // InterfaceMethod java/util/Iterator.hasNext:()Z
        88: ifeq          121
        91: aload         4
        93: invokeinterface #572,  1          // InterfaceMethod java/util/Iterator.next:()Ljava/lang/Object;
        98: checkcast     #1209               // class ghidra/formats/gfilesystem/FSRL
       101: astore        5
       103: aload_0
       104: aload         5
       106: aload_1
       107: aload_0
       108: getfield      #86                 // Field options:Lghidra/app/util/headless/HeadlessOptions;
       111: getfield      #1370               // Field ghidra/app/util/headless/HeadlessOptions.recursiveDepth:Ljava/lang/Integer;
       114: iconst_1
       115: invokevirtual #1316               // Method processWithImport:(Lghidra/formats/gfilesystem/FSRL;Ljava/lang/String;Ljava/lang/Integer;Z)V
       118: goto          81
       121: goto          227
       124: new           #820                // class ghidra/app/script/GhidraState
       127: dup
       128: aconst_null
       129: aload_0
       130: getfield      #132                // Field project:Lghidra/framework/model/Project;
       133: aconst_null
       134: aconst_null
       135: aconst_null
       136: aconst_null
       137: invokespecial #822                // Method ghidra/app/script/GhidraState."<init>":(Lghidra/framework/plugintool/PluginTool;Lghidra/framework/model/Project;Lghidra/program/model/listing/Program;Lghidra/program/util/ProgramLocation;Lghidra/program/util/ProgramSelection;Lghidra/program/util/ProgramSelection;)V
       140: astore_3
       141: getstatic     #834                // Field ghidra/app/util/headless/HeadlessScript$HeadlessContinuationOption.CONTINUE:Lghidra/app/util/headless/HeadlessScript$HeadlessContinuationOption;
       144: astore        4
       146: aload_0
       147: aload_0
       148: getfield      #86                 // Field options:Lghidra/app/util/headless/HeadlessOptions;
       151: getfield      #213                // Field ghidra/app/util/headless/HeadlessOptions.preScripts:Ljava/util/List;
       154: aload_0
       155: getfield      #86                 // Field options:Lghidra/app/util/headless/HeadlessOptions;
       158: getfield      #688                // Field ghidra/app/util/headless/HeadlessOptions.preScriptFileMap:Ljava/util/Map;
       161: aload_3
       162: aload         4
       164: invokevirtual #841                // Method runScriptsList:(Ljava/util/List;Ljava/util/Map;Lghidra/app/script/GhidraState;Lghidra/app/util/headless/HeadlessScript$HeadlessContinuationOption;)Lghidra/app/util/headless/HeadlessScript$HeadlessContinuationOption;
       167: astore        4
       169: getstatic     #845                // Field ghidra/app/util/headless/HeadlessAnalyzer$3.$SwitchMap$ghidra$app$util$headless$HeadlessScript$HeadlessContinuationOption:[I
       172: aload         4
       174: invokevirtual #851                // Method ghidra/app/util/headless/HeadlessScript$HeadlessContinuationOption.ordinal:()I
       177: iaload
       178: lookupswitch  { // 2
                       1: 204
                       3: 204
                 default: 205
            }
       204: return
       205: aload_0
       206: aload_0
       207: getfield      #86                 // Field options:Lghidra/app/util/headless/HeadlessOptions;
       210: getfield      #220                // Field ghidra/app/util/headless/HeadlessOptions.postScripts:Ljava/util/List;
       213: aload_0
       214: getfield      #86                 // Field options:Lghidra/app/util/headless/HeadlessOptions;
       217: getfield      #695                // Field ghidra/app/util/headless/HeadlessOptions.postScriptFileMap:Ljava/util/Map;
       220: aload_3
       221: aload         4
       223: invokevirtual #841                // Method runScriptsList:(Ljava/util/List;Ljava/util/Map;Lghidra/app/script/GhidraState;Lghidra/app/util/headless/HeadlessScript$HeadlessContinuationOption;)Lghidra/app/util/headless/HeadlessScript$HeadlessContinuationOption;
       226: pop
       227: return

  private ghidra.framework.model.Project openProject(ghidra.framework.model.ProjectLocator) throws java.io.IOException;
    Code:
         0: aload_0
         1: getfield      #86                 // Field options:Lghidra/app/util/headless/HeadlessOptions;
         4: getfield      #347                // Field ghidra/app/util/headless/HeadlessOptions.deleteProject:Z
         7: ifeq          31
        10: aload_0
        11: aload_1
        12: invokestatic  #181                // Method java/lang/String.valueOf:(Ljava/lang/Object;)Ljava/lang/String;
        15: invokedynamic #1374,  0           // InvokeDynamic #79:makeConcatWithConstants:(Ljava/lang/String;)Ljava/lang/String;
        20: invokestatic  #225                // Method ghidra/util/Msg.warn:(Ljava/lang/Object;Ljava/lang/Object;)V
        23: aload_0
        24: getfield      #86                 // Field options:Lghidra/app/util/headless/HeadlessOptions;
        27: iconst_0
        28: putfield      #347                // Field ghidra/app/util/headless/HeadlessOptions.deleteProject:Z
        31: aload_0
        32: aload_1
        33: invokestatic  #181                // Method java/lang/String.valueOf:(Ljava/lang/Object;)Ljava/lang/String;
        36: invokedynamic #1375,  0           // InvokeDynamic #80:makeConcatWithConstants:(Ljava/lang/String;)Ljava/lang/String;
        41: invokestatic  #281                // Method ghidra/util/Msg.info:(Ljava/lang/Object;Ljava/lang/Object;)V
        44: new           #1376               // class ghidra/app/util/headless/HeadlessAnalyzer$HeadlessProject
        47: dup
        48: aload_0
        49: invokevirtual #356                // Method getProjectManager:()Lghidra/app/util/headless/HeadlessAnalyzer$HeadlessGhidraProjectManager;
        52: aload_1
        53: invokespecial #1378               // Method ghidra/app/util/headless/HeadlessAnalyzer$HeadlessProject."<init>":(Lghidra/app/util/headless/HeadlessAnalyzer$HeadlessGhidraProjectManager;Lghidra/framework/model/ProjectLocator;)V
        56: astore_2
        57: goto          70
        60: astore_3
        61: new           #63                 // class java/io/IOException
        64: dup
        65: aload_3
        66: invokespecial #317                // Method java/io/IOException."<init>":(Ljava/lang/Throwable;)V
        69: athrow
        70: aload_2
        71: areturn
      Exception table:
         from    to  target type
            44    57    60   Class ghidra/util/exception/NotFoundException
            44    57    60   Class ghidra/util/NotOwnerException
            44    57    60   Class ghidra/framework/store/LockException

  static void checkValidFilename(java.lang.String) throws ghidra.util.exception.InvalidInputException;
    Code:
         0: aload_0
         1: invokestatic  #1387               // Method org/apache/commons/io/FilenameUtils.getName:(Ljava/lang/String;)Ljava/lang/String;
         4: astore_1
         5: iconst_0
         6: istore_2
         7: iload_2
         8: aload_1
         9: invokevirtual #201                // Method java/lang/String.length:()I
        12: if_icmpge     50
        15: aload_1
        16: iload_2
        17: invokevirtual #1391               // Method java/lang/String.charAt:(I)C
        20: istore_3
        21: iload_3
        22: invokestatic  #1395               // Method ghidra/framework/store/local/LocalFileSystem.isValidNameCharacter:(C)Z
        25: ifne          44
        28: new           #1319               // class ghidra/util/exception/InvalidInputException
        31: dup
        32: aload_1
        33: iload_3
        34: aload_0
        35: invokedynamic #1401,  0           // InvokeDynamic #81:makeConcatWithConstants:(Ljava/lang/String;CLjava/lang/String;)Ljava/lang/String;
        40: invokespecial #1404               // Method ghidra/util/exception/InvalidInputException."<init>":(Ljava/lang/String;)V
        43: athrow
        44: iinc          2, 1
        47: goto          7
        50: return

  private ghidra.app.util.headless.HeadlessAnalyzer$HeadlessGhidraProjectManager getProjectManager();
    Code:
         0: aload_0
         1: getfield      #1405               // Field projectManager:Lghidra/app/util/headless/HeadlessAnalyzer$HeadlessGhidraProjectManager;
         4: ifnonnull     18
         7: aload_0
         8: new           #361                // class ghidra/app/util/headless/HeadlessAnalyzer$HeadlessGhidraProjectManager
        11: dup
        12: invokespecial #1409               // Method ghidra/app/util/headless/HeadlessAnalyzer$HeadlessGhidraProjectManager."<init>":()V
        15: putfield      #1405               // Field projectManager:Lghidra/app/util/headless/HeadlessAnalyzer$HeadlessGhidraProjectManager;
        18: aload_0
        19: getfield      #1405               // Field projectManager:Lghidra/app/util/headless/HeadlessAnalyzer$HeadlessGhidraProjectManager;
        22: areturn

  private ghidra.formats.gfilesystem.FSRL lambda$processWithImport$3(java.io.File);
    Code:
         0: aload_0
         1: getfield      #127                // Field fsService:Lghidra/formats/gfilesystem/FileSystemService;
         4: aload_1
         5: invokevirtual #1410               // Method ghidra/formats/gfilesystem/FileSystemService.getLocalFSRL:(Ljava/io/File;)Lghidra/formats/gfilesystem/FSRL;
         8: areturn

  private static void lambda$processFileWithImport$2(ghidra.app.util.opinion.Loaded);
    Code:
         0: aload_0
         1: invokedynamic #1414,  0           // InvokeDynamic #82:accept:()Ljava/util/function/Consumer;
         6: invokevirtual #1415               // Method ghidra/app/util/opinion/Loaded.apply:(Ljava/util/function/Consumer;)V
         9: return

  private static void lambda$processFileWithImport$1(ghidra.program.model.listing.Program);
    Code:
         0: aload_0
         1: iconst_1
         2: invokeinterface #974,  2          // InterfaceMethod ghidra/program/model/listing/Program.setTemporary:(Z)V
         7: return

  private static boolean lambda$processFileWithImport$0(ghidra.program.model.listing.Program);
    Code:
         0: aload_0
         1: invokeinterface #796,  1          // InterfaceMethod ghidra/program/model/listing/Program.getMemory:()Lghidra/program/model/mem/Memory;
         6: invokeinterface #1417,  1         // InterfaceMethod ghidra/program/model/mem/Memory.getAllInitializedAddressSet:()Lghidra/program/model/address/AddressSetView;
        11: invokeinterface #808,  1          // InterfaceMethod ghidra/program/model/address/AddressSetView.isEmpty:()Z
        16: ireturn
}
